Workbook
Name crp: IF(AND(#REF!="© 2011 Spreadsheet123 Ltd. All rights reserved",#REF!="Small Business Templates by Spreadsheet123.com"),1,0)
Name crp: IF(AND(#REF!="© 2011 Spreadsheet123 Ltd. All rights reserved",#REF!="Small Business Templates by Spreadsheet123.com"),1,0)
Name crp: IF(AND(#REF!="© 2011 Spreadsheet123 Ltd. All rights reserved",#REF!="Small Business Templates by Spreadsheet123.com"),1,0)
Name crp: IF(AND(#REF!="© 2011 Spreadsheet123 Ltd. All rights reserved",#REF!="Small Business Templates by Spreadsheet123.com"),1,0)
Name crp: #REF!
Name crp: IF(AND(#REF!="© 2011 Spreadsheet123 Ltd. All rights reserved",#REF!="Small Business Templates by Spreadsheet123.com"),1,0)
Name crp: IF(AND(#REF!="© 2011 Spreadsheet123 Ltd. All rights reserved",#REF!="Small Business Templates by Spreadsheet123.com"),1,0)
Name crp: IF(AND(#REF!="© 2011 Spreadsheet123 Ltd. All rights reserved",#REF!="Small Business Templates by Spreadsheet123.com"),1,0)
Name crp: IF(AND(#REF!="© 2011 Spreadsheet123 Ltd. All rights reserved",#REF!="Small Business Templates by Spreadsheet123.com"),1,0)
Name crp: IF(AND(#REF!="© 2011 Spreadsheet123 Ltd. All rights reserved",#REF!="Small Business Templates by Spreadsheet123.com"),1,0)
Name crp: IF(AND(#REF!="© 2011 Spreadsheet123 Ltd. All rights reserved",#REF!="Small Business Templates by Spreadsheet123.com"),1,0)
Name crp: IF(AND(#REF!="© 2011 Spreadsheet123 Ltd. All rights reserved",#REF!="Small Business Templates by Spreadsheet123.com"),1,0)
Name crp: IF(AND(#REF!="© 2011 Spreadsheet123 Ltd. All rights reserved",#REF!="Small Business Templates by Spreadsheet123.com"),1,0)
Name crp: IF(AND(#REF!="© 2011 Spreadsheet123 Ltd. All rights reserved",#REF!="Small Business Templates by Spreadsheet123.com"),1,0)
Name crp: IF(AND(#REF!="© 2011 Spreadsheet123 Ltd. All rights reserved",#REF!="Small Business Templates by Spreadsheet123.com"),1,0)
Name crp: IF(AND(#REF!="© 2011 Spreadsheet123 Ltd. All rights reserved",#REF!="Small Business Templates by Spreadsheet123.com"),1,0)
Name crp: IF(AND(#REF!="© 2011 Spreadsheet123 Ltd. All rights reserved",#REF!="Small Business Templates by Spreadsheet123.com"),1,0)
Name crp: IF(AND(#REF!="© 2011 Spreadsheet123 Ltd. All rights reserved",#REF!="Small Business Templates by Spreadsheet123.com"),1,0)
Name crp: IF(AND(#REF!="© 2011 Spreadsheet123 Ltd. All rights reserved",#REF!="Small Business Templates by Spreadsheet123.com"),1,0)
Name crp: IF(AND(#REF!="© 2011 Spreadsheet123 Ltd. All rights reserved",#REF!="Small Business Templates by Spreadsheet123.com"),1,0)
Name crp: IF(AND(#REF!="© 2011 Spreadsheet123 Ltd. All rights reserved",#REF!="Small Business Templates by Spreadsheet123.com"),1,0)
Name crp: IF(AND(#REF!="© 2011 Spreadsheet123 Ltd. All rights reserved",#REF!="Small Business Templates by Spreadsheet123.com"),1,0)
Name crp: IF(AND(#REF!="© 2011 Spreadsheet123 Ltd. All rights reserved",#REF!="Small Business Templates by Spreadsheet123.com"),1,0)
Name crp: IF(AND(#REF!="© 2011 Spreadsheet123 Ltd. All rights reserved",#REF!="Small Business Templates by Spreadsheet123.com"),1,0)
Name crp: IF(AND(#REF!="© 2011 Spreadsheet123 Ltd. All rights reserved",#REF!="Small Business Templates by Spreadsheet123.com"),1,0)
Name crp: IF(AND(#REF!="© 2011 Spreadsheet123 Ltd. All rights reserved",#REF!="Small Business Templates by Spreadsheet123.com"),1,0)
Name crp: IF(AND(#REF!="© 2011 Spreadsheet123 Ltd. All rights reserved",#REF!="Small Business Templates by Spreadsheet123.com"),1,0)
Name crp: IF(AND(#REF!="© 2011 Spreadsheet123 Ltd. All rights reserved",#REF!="Small Business Templates by Spreadsheet123.com"),1,0)
Name crp: IF(AND(#REF!="© 2011 Spreadsheet123 Ltd. All rights reserved",#REF!="Small Business Templates by Spreadsheet123.com"),1,0)
Name crp: IF(AND(#REF!="© 2011 Spreadsheet123 Ltd. All rights reserved",#REF!="Small Business Templates by Spreadsheet123.com"),1,0)
Name crp: IF(AND(#REF!="© 2011 Spreadsheet123 Ltd. All rights reserved",#REF!="Small Business Templates by Spreadsheet123.com"),1,0)
Name crp: IF(AND(#REF!="© 2011 Spreadsheet123 Ltd. All rights reserved",#REF!="Small Business Templates by Spreadsheet123.com"),1,0)
Name crp: IF(AND(#REF!="© 2011 Spreadsheet123 Ltd. All rights reserved",#REF!="Small Business Templates by Spreadsheet123.com"),1,0)
Name crp: IF(AND(#REF!="© 2011 Spreadsheet123 Ltd. All rights reserved",#REF!="Small Business Templates by Spreadsheet123.com"),1,0)
Name crp: IF(AND(#REF!="© 2011 Spreadsheet123 Ltd. All rights reserved",#REF!="Small Business Templates by Spreadsheet123.com"),1,0)
Name crp: IF(AND(#REF!="© 2011 Spreadsheet123 Ltd. All rights reserved",#REF!="Small Business Templates by Spreadsheet123.com"),1,0)
Name crp: #REF!
Name crp: IF(AND(#REF!="© 2011 Spreadsheet123 Ltd. All rights reserved",#REF!="Small Business Templates by Spreadsheet123.com"),1,0)
Name Help: #REF!
Name Help: #REF!
Name Help: #REF!
Name Help: #REF!
Name Help: #REF!
Name Help: #REF!
Name Help: #REF!
Name Help: #REF!
Name Help: #REF!
Name Help: #REF!
Name Help: #REF!
Name Help: #REF!
Name Help: #REF!
Name Help: #REF!
Name Help: #REF!
Name Help: #REF!
Name Help: #REF!
Name Help: #REF!
Name Help: #REF!
Name Help: #REF!
Name Help: #REF!
Name Help: #REF!

Sheet 경쟁사 가격분석
H2: ** KFC 는 바하마 공식 웹사이트 / Popeyes 는 Gofadis 기준
H3: ** 카테고리 평균 가격으로 기입
B4: 구분 | C4: bb.q | D4: KFC | E4: bb.q <> KFC | F4: Popeyes | G4: bb.q <> Popeyes | H4: Note
B5: Whole Chicken | C5: 4.12 | D5: 2.61 | E5: -0.3658 | F5: 단품 없음 (콤보로만 판매) | H5: 타브랜드: 소스 상관없이 가격 동일
B6: Wing | C6: 1.61 | D6: - | F6: - | H6: 타브랜드: 별도 부위 구분 없음
B7: Boneless | C7: 1.62 | D7: - | F7: -
B8: 1-2용 Menu Range (combo, 2/3/5/6p 메뉴) | C8: $9.95~$19.95 | D8: $7.77~$20.00 | F8: $9.15~$56.42 | H8: 각 콤보별 구성 상이 / 파파이스는 일부 콤보 내 음료 포함
B9: French Fries | C9: 4.95 | D9: 4.09 | E9: -0.1737 | F9: 5.65 | G9: 0.1414 | H9: 타브랜드: Large 사이즈 기준
B10: Side Sauce | C10: 1.95 | D10: 0.28 | E10: -0.8564 | F10: 0.65 | G10: -0.6667
B11: Soda | C11: 2.38 | D11: 2.27 | E11: -0.0462 | F11: 3.25 | G11: 0.3655 | H11: 타브랜드: Med 사이즈 기준
B15: bb.q 메뉴 | E15: 판매가_07.26_ver
B16: Sort | D16: Menu | E16: Pcs | F16: Sales Price | G16: Price per pcs | H16: AVG
B17: Chicken | C17: W.C | D17: Golden Original Whole Chicken, Dark | E17: 2 | F17: 11.95 | G17: 5.98 | H17: 4.12
B18: Chicken | C18: W.C | D18: white | E18: 3 | F18: 12.95 | G18: 4.32
B19: Chicken | C19: W.C | D19: (half) | E19: 5 | F19: 17.95 | G19: 3.59
B20: Chicken | C20: W.C | D20: (whole) | E20: 10 | F20: 31.95 | G20: 3.2
B21: Chicken | C21: W.C | D21: Secret Sauce Whole Chicken, Dark | E21: 2 | F21: 11.95 | G21: 5.98
B22: Chicken | C22: W.C | D22: white | E22: 3 | F22: 12.95 | G22: 4.32
B23: Chicken | C23: W.C | D23: (half) | E23: 5 | F23: 17.95 | G23: 3.59
B24: Chicken | C24: W.C | D24: (whole) | E24: 10 | F24: 31.95 | G24: 3.2
B25: Chicken | C25: W.C | D25: Hot Spicy Whole Chicken, Dark | E25: 2 | F25: 11.95 | G25: 5.98
B26: Chicken | C26: W.C | D26: white | E26: 3 | F26: 12.95 | G26: 4.32
B27: Chicken | C27: W.C | D27: (half) | E27: 5 | F27: 17.95 | G27: 3.59
B28: Chicken | C28: W.C | D28: (whole) | E28: 10 | F28: 31.95 | G28: 3.2
B29: Half & Half | C29: W.C | D29: Half & Half Whole Chicken (Secret) | E29: 10 | F29: 31.95 | G29: 3.2
B30: Half & Half | C30: W.C | D30: Half & Half Whole Chicken (Hot spicy) | E30: 10 | F30: 31.95 | G30: 3.2
B31: Chicken | C31: Wings | D31: Golden Original Wings | E31: 6 | F31: 10.95 | G31: 1.83 | H31: 1.7
B32: Chicken | C32: Wings | E32: 12 | F32: 19.95 | G32: 1.66
B33: Chicken | C33: Wings | E33: 18 | F33: 28.95 | G33: 1.61
B34: Chicken | C34: Wings | D34: Secret Sauce Wings | E34: 6 | F34: 10.95 | G34: 1.83
B35: Chicken | C35: Wings | E35: 12 | F35: 19.95 | G35: 1.66
B36: Chicken | C36: Wings | E36: 18 | F36: 28.95 | G36: 1.61
B37: Chicken | C37: Wings | D37: Hot Spicy Wings | E37: 6 | F37: 10.95 | G37: 1.83
B38: Chicken | C38: Wings | E38: 12 | F38: 19.95 | G38: 1.66
B39: Chicken | C39: Wings | E39: 18 | F39: 28.95 | G39: 1.61
B40: Chicken | C40: Wings | D40: Honey Garlic Wings | E40: 6 | F40: 10.95 | G40: 1.83
B41: Chicken | C41: Wings | E41: 12 | F41: 19.95 | G41: 1.66
B42: Chicken | C42: Wings | E42: 18 | F42: 28.95 | G42: 1.61
B43: Chicken | C43: Wings | D43: Soy Garlic Wings | E43: 6 | F43: 10.95 | G43: 1.83
B44: Chicken | C44: Wings | E44: 12 | F44: 19.95 | G44: 1.66
B45: Chicken | C45: Wings | E45: 18 | F45: 28.95 | G45: 1.61
B46: Chicken | C46: Wings | D46: Cheesling Wings | E46: 6 | F46: 10.95 | G46: 1.83
B47: Chicken | C47: Wings | E47: 12 | F47: 19.95 | G47: 1.66
B48: Chicken | C48: Wings | E48: 18 | F48: 28.95 | G48: 1.61
B49: Chicken | C49: Wings | D49: Gangjeong Wings | E49: 6 | F49: 10.95 | G49: 1.83
B50: Chicken | C50: Wings | E50: 12 | F50: 19.95 | G50: 1.66
B51: Chicken | C51: Wings | E51: 18 | F51: 28.95 | G51: 1.61
B52: Chicken | C52: Wings | D52: Galbi Wings | E52: 6 | F52: 10.95 | G52: 1.83
B53: Chicken | C53: Wings | E53: 12 | F53: 19.95 | G53: 1.66
B54: Chicken | C54: Wings | E54: 18 | F54: 28.95 | G54: 1.61
B55: Chicken | C55: Wings | D55: Spicy Galbi Wings | E55: 6 | F55: 10.95 | G55: 1.83
B56: Chicken | C56: Wings | E56: 12 | F56: 19.95 | G56: 1.66
B57: Chicken | C57: Wings | E57: 18 | F57: 28.95 | G57: 1.61
B58: Chicken | C58: Wings | D58: Caribbean Spice Wings | E58: 6 | F58: 10.95 | G58: 1.83
B59: Chicken | C59: Wings | E59: 12 | F59: 19.95 | G59: 1.66
B60: Chicken | C60: Wings | E60: 18 | F60: 28.95 | G60: 1.61
B61: Chicken | C61: BNLS | D61: Golden Original Boneless | E61: 6 | F61: 9.95 | G61: 1.66 | H61: 1.6
B62: Chicken | C62: BNLS | E62: 12 | F62: 18.95 | G62: 1.58
B63: Chicken | C63: BNLS | E63: 18 | F63: 27.95 | G63: 1.55
B64: Chicken | C64: BNLS | D64: Secret Sauce Boneless | E64: 6 | F64: 9.95 | G64: 1.66
B65: Chicken | C65: BNLS | E65: 12 | F65: 18.95 | G65: 1.58
B66: Chicken | C66: BNLS | E66: 18 | F66: 27.95 | G66: 1.55
B67: Chicken | C67: BNLS | D67: Hot Spicy Boneless | E67: 6 | F67: 9.95 | G67: 1.66
B68: Chicken | C68: BNLS | E68: 12 | F68: 18.95 | G68: 1.58
B69: Chicken | C69: BNLS | E69: 18 | F69: 27.95 | G69: 1.55
B70: Chicken | C70: BNLS | D70: Honey Garlic Boneless | E70: 6 | F70: 9.95 | G70: 1.66
B71: Chicken | C71: BNLS | E71: 12 | F71: 18.95 | G71: 1.58
B72: Chicken | C72: BNLS | E72: 18 | F72: 27.95 | G72: 1.55
B73: Chicken | C73: BNLS | D73: Soy Garlic Boneless | E73: 6 | F73: 9.95 | G73: 1.66
B74: Chicken | C74: BNLS | E74: 12 | F74: 18.95 | G74: 1.58
B75: Chicken | C75: BNLS | E75: 18 | F75: 27.95 | G75: 1.55
B76: Chicken | C76: BNLS | D76: Cheesling Boneless | E76: 6 | F76: 9.95 | G76: 1.66
B77: Chicken | C77: BNLS | E77: 12 | F77: 18.95 | G77: 1.58
B78: Chicken | C78: BNLS | E78: 18 | F78: 27.95 | G78: 1.55
B79: Chicken | C79: BNLS | D79: Gangjeong Boneless | E79: 6 | F79: 9.95 | G79: 1.66
B80: Chicken | C80: BNLS | E80: 12 | F80: 18.95 | G80: 1.58
B81: Chicken | C81: BNLS | E81: 18 | F81: 27.95 | G81: 1.55
B82: Chicken | C82: BNLS | D82: Galbi Boneless | E82: 6 | F82: 9.95 | G82: 1.66
B83: Chicken | C83: BNLS | E83: 12 | F83: 18.95 | G83: 1.58
B84: Chicken | C84: BNLS | E84: 18 | F84: 27.95 | G84: 1.55
B85: Chicken | C85: BNLS | D85: Spicy Galbi Boneless | E85: 6 | F85: 9.95 | G85: 1.66
B86: Chicken | C86: BNLS | E86: 12 | F86: 18.95 | G86: 1.58
B87: Chicken | C87: BNLS | E87: 18 | F87: 27.95 | G87: 1.55
B88: Chicken | C88: BNLS | D88: Caribbean Spice Boneless | E88: 6 | F88: 9.95 | G88: 1.66
B89: Chicken | C89: BNLS | E89: 12 | F89: 18.95 | G89: 1.58
B90: Chicken | C90: BNLS | E90: 18 | F90: 27.95 | G90: 1.55
B91: Food | C91: Ddeok-Bokki | D91: Ddeok-Bokki | E91: Add Cheese (+2.00) | F91: 13.95 | G91: 13.95
B92: Food | C92: Ddeok-Bokki | D92: Rose Ddeok-Bokki | E92: Add Cheese (+2.00) | F92: 14.95 | G92: 14.95
B93: Food | C93: Ddeok-Bokki | D93: Carbonara Ddeok-Bokki | E93: Add Cheese (+2.00) | F93: 14.95 | G93: 14.95
B94: Food | C94: Rice Bowl | D94: Fried Rice | E94: Add Cheese (+2.00) | F94: 7.95 | G94: 7.95
B95: Food | C95: Rice Bowl | D95: Chicken Fried Rice | E95: Add Cheese (+2.00) | F95: 9.95 | G95: 9.95
B96: Food | C96: Rice Bowl | D96: The Secret Rice Bowl | F96: 10.95 | G96: 10.95
B97: Food | C97: Rice Bowl | D97: Island Greens Rice Bowl | F97: 10.95 | G97: 10.95
B98: Food | C98: Rice Bowl | D98: Teriyaki Crunch Rice Bowl | F98: 10.95 | G98: 10.95
B99: Side | C99: Side | D99: French Fries (200g) | F99: 4.95 | G99: 4.95
B100: Side | C100: Side | D100: Cheesling Fries | F100: 7.95 | G100: 7.95
B101: Side | C101: Side | D101: Fried Conch | F101: 11.95 | G101: 11.95
B102: Side | C102: Side | D102: Fried Fish (6pcs) | F102: 9.95 | G102: 9.95
B103: Side | C103: Side | D103: Coleslaw | F103: 4.95 | G103: 4.95
B104: Side | C104: Side | D104: Steamed Rice | F104: 1.95 | G104: 1.95
...

Sheet Competitor Price Analysis
B4: Menu Item | C4: Description | D4: Price (JMD) | E4: Price (USD)
A5: * 1 USD = 156JMD
A6: BirdShack
A7: Family Meals | B7: FLEX 9 | C7: 9pcs Chicken + 12 fries +2colslaw + 1.2L Soda | D7: 5125 | E7: =D7/156 -> 32.852564
B8: FLEX 12 | C8: 12pcs Chicken + 12 fries +3colslaw + Cornbread Rolls + 1.2L Soda | D8: 6745 | E8: =D8/156 -> 43.237179
B9: FLEX 15 | C9: 15 pcs Chicken + 1.2L Soda | D9: 6535 | E9: =D9/156 -> 41.891026
B10: FLEX 21 | C10: 21 pcs Chicken + 1.2L Soda | D10: 8735 | E10: =D10/156 -> 55.99359
B11: FLEX BOX COMBO | C11: 1pcs Chicken or 3 wings + 1Chicken sandwich + 3 Wedge . Fries + 16oz Soda | D11: 1800 | E11: =D11/156 -> 11.538462
B12: STARTA BOX | C12: 1pcs Chicken + 3 Potato Wedge or reg fries + 1 Cornbrean Roll + 16 oz Soda | D12: 690 | E12: =D12/156 -> 4.4230769
A13: Combo | B13: Jumbo Wings Combo (6pc) | C13: 6pcs Wing + 3 wedge fries or reg fries + 16oz Soda | D13: 1320 | E13: =D13/156 -> 8.4615385
B14: Jumbo Wings Combo (10pc) | C14: 10pcs Wing + 3 wedge fries or reg fries + 16oz Soda | D14: 1950 | E14: =D14/156 -> 12.5
B15: Jumbo Wings Combo (16pc) | C15: 16pcs Wing + 3 wedge fries or reg fries + 16oz Soda | D15: 2750 | E15: =D15/156 -> 17.628205
B16: Double Up | C16: 2pc of Chicken + 3 Fries + 16oz Soda | D16: 1045 | E16: =D16/156 -> 6.6987179
B17: Hatrik | C17: 3pc of Chicken + 3 Fries + 16oz Soda | D17: 1415 | E17: =D17/156 -> 9.0705128
B18: Chicken Sandwich Combo | C18: Chicken Sandwich + 3 fries + 16oz Soda | D18: 1200 | E18: =D18/156 -> 7.6923077
B19: Hi-5 | C19: 5pc of Chicken + 3 Fries + 16oz Soda | D19: 2445 | E19: =D19/156 -> 15.673077
B20: 6LUV | C20: 6pc of Chicken + 6 Fries + Coleslaw + 2 16oz Soda | D20: 2935 | E20: =D20/156 -> 18.814103
A21: Side | B21: Wedges | D21: 250 | E21: =D21/156 -> 1.6025641
B22: Regular Fries | D22: 250 | E22: =D22/156 -> 1.6025641
B23: Coleslaw | D23: 300 | E23: =D23/156 -> 1.9230769
B24: Cornbread Roll | D24: 150 | E24: =D24/156 -> 0.96153846
B25: Ranch | D25: 120 | E25: =D25/156 -> 0.76923077
B26: Honey Mustard | D26: 120 | E26: =D26/156 -> 0.76923077
A27: Beverages | B27: Tru-Juice | D27: 300 | E27: =D27/156 -> 1.9230769
B28: CranWata | D28: 225 | E28: =D28/156 -> 1.4423077
B29: Wata | D29: 150 | E29: =D29/156 -> 0.96153846
B30: Soda | D30: 225 | E30: =D30/156 -> 1.4423077
A31: KFC
B33: Meal Deal | C33: 2pcs chicken + 1Fries + 1Soda | D33: 1050 | E33: =D33/156 -> 6.7307692
B34: Big Deal | C34: 3pcs Chicken + 1fries + 1 Soda | D34: 1420 | E34: =D34/156 -> 9.1025641
B35: Big Six | C35: 6pcs Chicken + 2 fries + 2 Soda + 1Coleslaw | D35: 2940 | E35: =D35/156 -> 18.846154
B36: Chicken Box | C36: 1pcs Chicken + 1 bread + fries | D36: 600 | E36: =D36/156 -> 3.8461538
B37: Chicken Box Combo | C37: 1 Chicken + 1 bread + 1fries + 1 Soda | D37: 680 | E37: =D37/156 -> 4.3589744
A38: Popeyes
B40: Popeyes 2pc Combo | C40: 2pcs Chicken + 1 bread + 1 side | D40: 1060 | E40: =D40/156 -> 6.7948718
B41: Popeyes 3pc Combo | C41: 3pcs Chicken + 1 bread + 1 side(fries) | D41: 1410 | E41: =D41/156 -> 9.0384615
B42: Popeyes 5pc Combo | C42: 5pcs Chicken + 1 bread + 1 side(fries) | D42: 2370 | E42: =D42/156 -> 15.192308
B43: Popeyes 21pc Combo | C43: 5pcs Chicken + 2 bread + 2 side(fries) | D43: 7850 | E43: =D43/156 -> 50.320513
B44: Popeyes 5pc Tenders Combo | C44: 5pc Tender + 1bread + 2 Sauce | D44: 1490 | E44: =D44/156 -> 9.5512821
B45: Popeyes 3pc Tenders Combo | C45: 3pc Tender + 1bread + 1 side | D45: 990 | E45: =D45/156 -> 6.3461538

Sheet Honduras(Total Final)
A2: bb.q Chicken Honduras Menu Food Cost | O2: Raw chicken (price per kg)
A3: Menu | P3: FL | Q3: Bahama 업데이트 전 | R3: Honduras (10/6)
O4: Whole (1.3~1.4kg) / 2.87~3.08LB | P4: 1.9 | Q4: 3.85 | R4: 3.05
A5: Sort | C5: Menu | E5: Description | F5: Sales Price HNL | G5: Sales Price USD | H5: Food Cost Dine In | I5: Food Cost Take Out | J5: Cost% Dine-In | K5: Cost% Take Out | L5: AVG D/I 50% + T/G 50% | M5: AVG Total | O5: Wing | P5: 3.44 | Q5: 1.7 | R5: 5.39
A6: Chicken (Bone In) | B6: Fried | C6: Golden Fried Chicken | E6: pcs (0.5 Bird) | F6: 300 | G6: =F6/24.65 -> 12.170385 | H6: ='BI_Golden Fried(3)'!$D$6 -> 2.7443571 | I6: ='BI_Golden Fried(3)'!$D$7 -> 3.5375442 | J6: =H6/G6 -> 0.22549467 | K6: =I6/G6 -> 0.29066822 | L6: =AVERAGE(J6:K35) -> #REF! | M6: =AVERAGE(L6,L36,L68,L98,L100,L109,L130,L135) -> #REF! | O6: BNL (Thigh) | P6: 2.23 | Q6: 4.03 | R6: 4.47
E7: pcs (1 Bird) | F7: 600 | G7: =F7/24.65 -> 24.340771 | H7: =#REF! -> #REF! | I7: =#REF! -> #REF! | J7: =H7/G7 -> #REF! | K7: =I7/G7 -> #REF!
C8: Classic Fried Chicken | E8: pcs (0.5 Bird) | F8: 300 | G8: =F8/24.65 -> 12.170385 | H8: ='BI_Classic(5)'!$D$6 -> 4.0231933 | I8: ='BI_Classic(5)'!$D$7 -> 4.6956104 | J8: =H8/G8 -> 0.33057238 | K8: =I8/G8 -> 0.38582266 | O8: BNL (Breast) | P8: - | Q8: - | R8: 6.06
E9: pcs (1 Bird) | F9: 600 | G9: =F9/24.65 -> 24.340771 | H9: =#REF! -> #REF! | I9: =#REF! -> #REF! | J9: =H9/G9 -> #REF! | K9: =I9/G9 -> #REF!
B10: Sauced | C10: Secret Sacued Chicken | E10: pcs (0.5 Bird) | F10: 350 | G10: =F10/24.65 -> 14.198783 | H10: ='BI_Secret (5)'!$D$6 -> 5.6307053 | I10: ='BI_Secret (5)'!$D$7 -> 6.4385207 | J10: =H10/G10 -> 0.39656253 | K10: =I10/G10 -> 0.45345582
E11: pcs (1 Bird) | F11: 700 | G11: =F11/24.65 -> 28.397566 | H11: =#REF! -> #REF! | I11: =#REF! -> #REF! | J11: =H11/G11 -> #REF! | K11: =I11/G11 -> #REF!
C12: Hot Spicy Chicken | E12: pcs (0.5 Bird) | F12: 350 | G12: =F12/24.65 -> 14.198783 | H12: ='BI_Hot Spicy(5)'!$D$6 -> 5.3287118 | I12: ='BI_Hot Spicy(5)'!$D$7 -> 6.1365272 | J12: =H12/G12 -> 0.37529356 | K12: =I12/G12 -> 0.43218685
E13: pcs (1 Bird) | F13: 700 | G13: =F13/24.65 -> 28.397566 | H13: =#REF! -> #REF! | I13: =#REF! -> #REF! | J13: =H13/G13 -> #REF! | K13: =I13/G13 -> #REF!
C14: Honey Garlic Chicken | E14: pcs (0.5 Bird) | F14: 350 | G14: =F14/24.65 -> 14.198783 | H14: ='BI_Honey Garlic(2)'!$D$6 -> 1.8223613 | I14: ='BI_Honey Garlic(2)'!$D$7 -> 2.6301768 | J14: =H14/G14 -> 0.12834631 | K14: =I14/G14 -> 0.18523959
E15: pcs (1 Bird) | F15: 700 | G15: =F15/24.65 -> 28.397566 | H15: =#REF! -> #REF! | I15: =#REF! -> #REF! | J15: =H15/G15 -> #REF! | K15: =I15/G15 -> #REF!
C16: Soy Garlic Chicken | E16: pcs (0.5 Bird) | F16: 350 | G16: =F16/24.65 -> 14.198783 | H16: ='BI_Soy Garlic(5)'!$D$6 -> 4.3531447 | I16: ='BI_Soy Garlic(5)'!$D$7 -> 5.1609601 | J16: =H16/G16 -> 0.30658576 | K16: =I16/G16 -> 0.36347905
E17: pcs (1 Bird) | F17: 700 | G17: =F17/24.65 -> 28.397566 | H17: =#REF! -> #REF! | I17: =#REF! -> #REF! | J17: =H17/G17 -> #REF! | K17: =I17/G17 -> #REF!
C18: Galbi Chicken | E18: pcs (0.5 Bird) | F18: 350 | G18: =F18/24.65 -> 14.198783 | H18: ='BI_Galbi(2)'!$D$6 -> 1.9934195 | I18: ='BI_Galbi(2)'!$D$7 -> 2.8012349 | J18: =H18/G18 -> 0.14039369 | K18: =I18/G18 -> 0.19728697
E19: pcs (1 Bird) | F19: 700 | G19: =F19/24.65 -> 28.397566 | H19: =#REF! -> #REF! | I19: =#REF! -> #REF! | J19: =H19/G19 -> #REF! | K19: =I19/G19 -> #REF!
C20: Hot Galbi Chikcen | E20: pcs (0.5 Bird) | F20: 350 | G20: =F20/24.65 -> 14.198783 | H20: ='BI_Hot Galbi(5)'!$D$6 -> 4.9672523 | I20: ='BI_Hot Galbi(5)'!$D$7 -> 5.7750677 | J20: =H20/G20 -> 0.34983648 | K20: =I20/G20 -> 0.40672977
E21: pcs (1 Bird) | F21: 700 | G21: =F21/24.65 -> 28.397566 | H21: =#REF! -> #REF! | I21: =#REF! -> #REF! | J21: =H21/G21 -> #REF! | K21: =I21/G21 -> #REF!
C22: Gang-Jeong Chicken | E22: pcs (0.5 Bird) | F22: 350 | G22: =F22/24.65 -> 14.198783 | H22: ='BI_Gangjeong(5)'!$D$6 -> 5.004655 | I22: ='BI_Gangjeong(5)'!$D$7 -> 5.8124704 | J22: =H22/G22 -> 0.3524707 | K22: =I22/G22 -> 0.40936399
E23: pcs (1 Bird) | F23: 700 | G23: =F23/24.65 -> 28.397566 | H23: =#REF! -> #REF! | I23: =#REF! -> #REF! | J23: =H23/G23 -> #REF! | K23: =I23/G23 -> #REF!
C24: Gangnam Style Chicken | E24: pcs (0.5 Bird) | F24: 350 | G24: =F24/24.65 -> 14.198783 | H24: ='BI_Gangnam Style(5)'!$D$6 -> 4.5905045 | I24: ='BI_Gangnam Style(5)'!$D$7 -> 5.3983199 | J24: =H24/G24 -> 0.32330267 | K24: =I24/G24 -> 0.38019596
E25: pcs (1 Bird) | F25: 700 | G25: =F25/24.65 -> 28.397566 | H25: =#REF! -> #REF! | I25: =#REF! -> #REF! | J25: =H25/G25 -> #REF! | K25: =I25/G25 -> #REF!
C26: Phase 2_Caribbean Spicy Chicken | E26: pcs (0.5 Bird) | F26: 350 | G26: =F26/24.65 -> 14.198783 | H26: ='BI_Caribbean(5)'!$D$6 -> 4.9618664 | I26: ='BI_Caribbean(5)'!$D$7 -> 5.7696819 | J26: =H26/G26 -> 0.34945716 | K26: =I26/G26 -> 0.40635045
E27: pcs (1 Bird) | F27: 700 | G27: =F27/24.65 -> 28.397566 | H27: =#REF! -> #REF! | I27: =#REF! -> #REF! | J27: =H27/G27 -> #REF! | K27: =I27/G27 -> #REF!
C28: Phase 2_Mala Hot Chicekn | E28: pcs (0.5 Bird) | F28: 350 | G28: =F28/24.65 -> 14.198783 | H28: ='BI_Mala Hot(5)'!$D$6 -> 5.5427957 | I28: ='BI_Mala Hot(5)'!$D$7 -> 6.3506112 | J28: =H28/G28 -> 0.39037118 | K28: =I28/G28 -> 0.44726447
E29: pcs (1 Bird) | F29: 700 | G29: =F29/24.65 -> 28.397566 | H29: =#REF! -> #REF! | I29: =#REF! -> #REF! | J29: =H29/G29 -> #REF! | K29: =I29/G29 -> #REF!
B30: Flakes | C30: Phase 2_Creamy Onion Chicekn | E30: pcs (0.5 Bird) | F30: 350 | G30: =F30/24.65 -> 14.198783 | H30: =#REF! -> #REF! | I30: =#REF! -> #REF! | J30: =H30/G30 -> #REF! | K30: =I30/G30 -> #REF!
E31: pcs (1 Bird) | F31: 700 | G31: =F31/24.65 -> 28.397566 | H31: =#REF! -> #REF! | I31: =#REF! -> #REF! | J31: =H31/G31 -> #REF! | K31: =I31/G31 -> #REF!
C32: Phase 2_Creamy Jalapeno Chicken | E32: pcs (0.5 Bird) | F32: 350 | G32: =F32/24.65 -> 14.198783 | H32: =#REF! -> #REF! | I32: =#REF! -> #REF! | J32: =H32/G32 -> #REF! | K32: =I32/G32 -> #REF!
E33: pcs (1 Bird) | F33: 700 | G33: =F33/24.65 -> 28.397566 | H33: =#REF! -> #REF! | I33: =#REF! -> #REF! | J33: =H33/G33 -> #REF! | K33: =I33/G33 -> #REF!
C34: Cheesling Chicken | E34: pcs (0.5 Bird) | F34: 350 | G34: =F34/24.65 -> 14.198783 | H34: ='BI_Cheesling(5)'!$D$6 -> 4.6052789 | I34: ='BI_Cheesling(5)'!$D$7 -> 5.4130943 | J34: =H34/G34 -> 0.32434321 | K34: =I34/G34 -> 0.3812365
E35: pcs (1 Bird) | F35: 700 | G35: =F35/24.65 -> 28.397566 | H35: =#REF! -> #REF! | I35: =#REF! -> #REF! | J35: =H35/G35 -> #REF! | K35: =I35/G35 -> #REF!
A36: Chicken (Boneless) | B36: Fried | C36: Golden Fried Chicken | E36: 10 pcs | F36: 300 | G36: =F36/24.65 -> 12.170385 | H36: =#REF! -> #REF! | I36: =#REF! -> #REF! | J36: =H36/G36 -> #REF! | K36: =I36/G36 -> #REF! | L36: =AVERAGE(J36:K67) -> #REF!
E37: 20 pcs | F37: 600 | G37: =F37/24.65 -> 24.340771 | H37: =#REF! -> #REF! | I37: =#REF! -> #REF! | J37: =H37/G37 -> #REF! | K37: =I37/G37 -> #REF!
C38: Classic Fried Chicken | E38: 10 pcs | F38: 300 | G38: =F38/24.65 -> 12.170385 | H38: =#REF! -> #REF! | I38: =#REF! -> #REF! | J38: =H38/G38 -> #REF! | K38: =I38/G38 -> #REF!
E39: 20 pcs | F39: 600 | G39: =F39/24.65 -> 24.340771 | H39: =#REF! -> #REF! | I39: =#REF! -> #REF! | J39: =H39/G39 -> #REF! | K39: =I39/G39 -> #REF!
C40: Golden Fried Tender | E40: 10 pcs | F40: 300 | G40: =F40/24.65 -> 12.170385 | H40: =#REF! -> #REF! | I40: =#REF! -> #REF! | J40: =H40/G40 -> #REF! | K40: =I40/G40 -> #REF!
E41: 20 pcs | F41: 600 | G41: =F41/24.65 -> 24.340771 | H41: =#REF! -> #REF! | I41: =#REF! -> #REF! | J41: =H41/G41 -> #REF! | K41: =I41/G41 -> #REF!
B42: Sauced | C42: Secret Sacued Chicken | E42: 10 pcs | F42: 350 | G42: =F42/24.65 -> 14.198783 | H42: =#REF! -> #REF! | I42: =#REF! -> #REF! | J42: =H42/G42 -> #REF! | K42: =I42/G42 -> #REF!
E43: 20 pcs | F43: 700 | G43: =F43/24.65 -> 28.397566 | H43: =#REF! -> #REF! | I43: =#REF! -> #REF! | J43: =H43/G43 -> #REF! | K43: =I43/G43 -> #REF!
C44: Hot Spicy Chicken | E44: 10 pcs | F44: 350 | G44: =F44/24.65 -> 14.198783 | H44: =#REF! -> #REF! | I44: =#REF! -> #REF! | J44: =H44/G44 -> #REF! | K44: =I44/G44 -> #REF!
E45: 20 pcs | F45: 700 | G45: =F45/24.65 -> 28.397566 | H45: =#REF! -> #REF! | I45: =#REF! -> #REF! | J45: =H45/G45 -> #REF! | K45: =I45/G45 -> #REF!
C46: Honey Garlic Chicken | E46: 10 pcs | F46: 350 | G46: =F46/24.65 -> 14.198783 | H46: =#REF! -> #REF! | I46: =#REF! -> #REF! | J46: =H46/G46 -> #REF! | K46: =I46/G46 -> #REF!
E47: 20 pcs | F47: 700 | G47: =F47/24.65 -> 28.397566 | H47: =#REF! -> #REF! | I47: =#REF! -> #REF! | J47: =H47/G47 -> #REF! | K47: =I47/G47 -> #REF!
C48: Soy Garlic Chicken | E48: 10 pcs | F48: 350 | G48: =F48/24.65 -> 14.198783 | H48: =#REF! -> #REF! | I48: =#REF! -> #REF! | J48: =H48/G48 -> #REF! | K48: =I48/G48 -> #REF!
E49: 20 pcs | F49: 700 | G49: =F49/24.65 -> 28.397566 | H49: =#REF! -> #REF! | I49: =#REF! -> #REF! | J49: =H49/G49 -> #REF! | K49: =I49/G49 -> #REF!
C50: Galbi Chicken | E50: 10 pcs | F50: 350 | G50: =F50/24.65 -> 14.198783 | H50: =#REF! -> #REF! | I50: =#REF! -> #REF! | J50: =H50/G50 -> #REF! | K50: =I50/G50 -> #REF!
E51: 20 pcs | F51: 700 | G51: =F51/24.65 -> 28.397566 | H51: =#REF! -> #REF! | I51: =#REF! -> #REF! | J51: =H51/G51 -> #REF! | K51: =I51/G51 -> #REF!
C52: Hot Galbi Chikcen | E52: 10 pcs | F52: 350 | G52: =F52/24.65 -> 14.198783 | H52: =#REF! -> #REF! | I52: =#REF! -> #REF! | J52: =H52/G52 -> #REF! | K52: =I52/G52 -> #REF!
E53: 20 pcs | F53: 700 | G53: =F53/24.65 -> 28.397566 | H53: =#REF! -> #REF! | I53: =#REF! -> #REF! | J53: =H53/G53 -> #REF! | K53: =I53/G53 -> #REF!
C54: Gang-Jeong Chicken | E54: 10 pcs | F54: 350 | G54: =F54/24.65 -> 14.198783 | H54: =#REF! -> #REF! | I54: =#REF! -> #REF! | J54: =H54/G54 -> #REF! | K54: =I54/G54 -> #REF!
E55: 20 pcs | F55: 700 | G55: =F55/24.65 -> 28.397566 | H55: =#REF! -> #REF! | I55: =#REF! -> #REF! | J55: =H55/G55 -> #REF! | K55: =I55/G55 -> #REF!
C56: Gangnam Style Chicken | E56: 10 pcs | F56: 350 | G56: =F56/24.65 -> 14.198783 | H56: =#REF! -> #REF! | I56: =#REF! -> #REF! | J56: =H56/G56 -> #REF! | K56: =I56/G56 -> #REF!
E57: 20 pcs | F57: 700 | G57: =F57/24.65 -> 28.397566 | H57: =#REF! -> #REF! | I57: =#REF! -> #REF! | J57: =H57/G57 -> #REF! | K57: =I57/G57 -> #REF!
C58: Phase 2_Caribbean Spicy Chicken | E58: 10 pcs | F58: 350 | G58: =F58/24.65 -> 14.198783 | H58: =#REF! -> #REF! | I58: =#REF! -> #REF! | J58: =H58/G58 -> #REF! | K58: =I58/G58 -> #REF!
E59: 20 pcs | F59: 700 | G59: =F59/24.65 -> 28.397566 | H59: =#REF! -> #REF! | I59: =#REF! -> #REF! | J59: =H59/G59 -> #REF! | K59: =I59/G59 -> #REF!
C60: Phase 2_Mala Hot Chicekn | E60: 10 pcs | F60: 350 | G60: =F60/24.65 -> 14.198783 | H60: =#REF! -> #REF! | I60: =#REF! -> #REF! | J60: =H60/G60 -> #REF! | K60: =I60/G60 -> #REF!
E61: 20 pcs | F61: 700 | G61: =F61/24.65 -> 28.397566 | H61: =#REF! -> #REF! | I61: =#REF! -> #REF! | J61: =H61/G61 -> #REF! | K61: =I61/G61 -> #REF!
B62: Flakes | C62: Phase 2_Creamy Onion Chicekn | E62: 10 pcs | F62: 350 | G62: =F62/24.65 -> 14.198783 | H62: =#REF! -> #REF! | I62: =#REF! -> #REF! | J62: =H62/G62 -> #REF! | K62: =I62/G62 -> #REF!
E63: 20 pcs | F63: 700 | G63: =F63/24.65 -> 28.397566 | H63: =#REF! -> #REF! | I63: =#REF! -> #REF! | J63: =H63/G63 -> #REF! | K63: =I63/G63 -> #REF!
C64: Phase 2_Creamy Jalapeno Chicken | E64: 10 pcs | F64: 350 | G64: =F64/24.65 -> 14.198783 | H64: =#REF! -> #REF! | I64: =#REF! -> #REF! | J64: =H64/G64 -> #REF! | K64: =I64/G64 -> #REF!
E65: 20 pcs | F65: 700 | G65: =F65/24.65 -> 28.397566 | H65: =#REF! -> #REF! | I65: =#REF! -> #REF! | J65: =H65/G65 -> #REF! | K65: =I65/G65 -> #REF!
C66: Cheesling Chicken | E66: 10 pcs | F66: 350 | G66: =F66/24.65 -> 14.198783 | H66: =#REF! -> #REF! | I66: =#REF! -> #REF! | J66: =H66/G66 -> #REF! | K66: =I66/G66 -> #REF!
E67: 20 pcs | F67: 700 | G67: =F67/24.65 -> 28.397566 | H67: =#REF! -> #REF! | I67: =#REF! -> #REF! | J67: =H67/G67 -> #REF! | K67: =I67/G67 -> #REF!
A68: Chicken (Wing) | B68: Fried | C68: Golden Fried Chicken | E68: 10 pcs | F68: 300 | G68: =F68/24.65 -> 12.170385 | H68: =#REF! -> #REF! | I68: =#REF! -> #REF! | J68: =H68/G68 -> #REF! | K68: =I68/G68 -> #REF! | L68: =AVERAGE(J68:K97) -> #REF!
E69: 20 pcs | F69: 600 | G69: =F69/24.65 -> 24.340771 | H69: =#REF! -> #REF! | I69: =#REF! -> #REF! | J69: =H69/G69 -> #REF! | K69: =I69/G69 -> #REF!
C70: Classic Fried Chicken | E70: 10 pcs | F70: 300 | G70: =F70/24.65 -> 12.170385 | H70: =#REF! -> #REF! | I70: =#REF! -> #REF! | J70: =H70/G70 -> #REF! | K70: =I70/G70 -> #REF!
E71: 20 pcs | F71: 600 | G71: =F71/24.65 -> 24.340771 | H71: =#REF! -> #REF! | I71: =#REF! -> #REF! | J71: =H71/G71 -> #REF! | K71: =I71/G71 -> #REF!
B72: Sauced | C72: Secret Sacued Chicken | E72: 10 pcs | F72: 350 | G72: =F72/24.65 -> 14.198783 | H72: =#REF! -> #REF! | I72: =#REF! -> #REF! | J72: =H72/G72 -> #REF! | K72: =I72/G72 -> #REF!
E73: 20 pcs | F73: 700 | G73: =F73/24.65 -> 28.397566 | H73: =#REF! -> #REF! | I73: =#REF! -> #REF! | J73: =H73/G73 -> #REF! | K73: =I73/G73 -> #REF!
C74: Hot Spicy Chicken | E74: 10 pcs | F74: 350 | G74: =F74/24.65 -> 14.198783 | H74: =#REF! -> #REF! | I74: =#REF! -> #REF! | J74: =H74/G74 -> #REF! | K74: =I74/G74 -> #REF!
E75: 20 pcs | F75: 700 | G75: =F75/24.65 -> 28.397566 | H75: =#REF! -> #REF! | I75: =#REF! -> #REF! | J75: =H75/G75 -> #REF! | K75: =I75/G75 -> #REF!
C76: Honey Garlic Chicken | E76: 10 pcs | F76: 350 | G76: =F76/24.65 -> 14.198783 | H76: =#REF! -> #REF! | I76: =#REF! -> #REF! | J76: =H76/G76 -> #REF! | K76: =I76/G76 -> #REF!
E77: 20 pcs | F77: 700 | G77: =F77/24.65 -> 28.397566 | H77: =#REF! -> #REF! | I77: =#REF! -> #REF! | J77: =H77/G77 -> #REF! | K77: =I77/G77 -> #REF!
C78: Soy Garlic Chicken | E78: 10 pcs | F78: 350 | G78: =F78/24.65 -> 14.198783 | H78: =#REF! -> #REF! | I78: =#REF! -> #REF! | J78: =H78/G78 -> #REF! | K78: =I78/G78 -> #REF!
E79: 20 pcs | F79: 700 | G79: =F79/24.65 -> 28.397566 | H79: =#REF! -> #REF! | I79: =#REF! -> #REF! | J79: =H79/G79 -> #REF! | K79: =I79/G79 -> #REF!
C80: Galbi Chicken | E80: 10 pcs | F80: 350 | G80: =F80/24.65 -> 14.198783 | H80: =#REF! -> #REF! | I80: =#REF! -> #REF! | J80: =H80/G80 -> #REF! | K80: =I80/G80 -> #REF!
E81: 20 pcs | F81: 700 | G81: =F81/24.65 -> 28.397566 | H81: =#REF! -> #REF! | I81: =#REF! -> #REF! | J81: =H81/G81 -> #REF! | K81: =I81/G81 -> #REF!
C82: Hot Galbi Chikcen | E82: 10 pcs | F82: 350 | G82: =F82/24.65 -> 14.198783 | H82: =#REF! -> #REF! | I82: =#REF! -> #REF! | J82: =H82/G82 -> #REF! | K82: =I82/G82 -> #REF!
E83: 20 pcs | F83: 700 | G83: =F83/24.65 -> 28.397566 | H83: =#REF! -> #REF! | I83: =#REF! -> #REF! | J83: =H83/G83 -> #REF! | K83: =I83/G83 -> #REF!
C84: Gang-Jeong Chicken | E84: 10 pcs | F84: 350 | G84: =F84/24.65 -> 14.198783 | H84: =#REF! -> #REF! | I84: =#REF! -> #REF! | J84: =H84/G84 -> #REF! | K84: =I84/G84 -> #REF!
E85: 20 pcs | F85: 700 | G85: =F85/24.65 -> 28.397566 | H85: =#REF! -> #REF! | I85: =#REF! -> #REF! | J85: =H85/G85 -> #REF! | K85: =I85/G85 -> #REF!
C86: Gangnam Style Chicken | E86: 10 pcs | F86: 350 | G86: =F86/24.65 -> 14.198783 | H86: =#REF! -> #REF! | I86: =#REF! -> #REF! | J86: =H86/G86 -> #REF! | K86: =I86/G86 -> #REF!
E87: 20 pcs | F87: 700 | G87: =F87/24.65 -> 28.397566 | H87: =#REF! -> #REF! | I87: =#REF! -> #REF! | J87: =H87/G87 -> #REF! | K87: =I87/G87 -> #REF!
C88: Phase 2_Caribbean Spicy Chicken | E88: 10 pcs | F88: 350 | G88: =F88/24.65 -> 14.198783 | H88: =#REF! -> #REF! | I88: =#REF! -> #REF! | J88: =H88/G88 -> #REF! | K88: =I88/G88 -> #REF!
E89: 20 pcs | F89: 700 | G89: =F89/24.65 -> 28.397566 | H89: =#REF! -> #REF! | I89: =#REF! -> #REF! | J89: =H89/G89 -> #REF! | K89: =I89/G89 -> #REF!
C90: Phase 2_Mala Hot Chicekn | E90: 10 pcs | F90: 350 | G90: =F90/24.65 -> 14.198783 | H90: =#REF! -> #REF! | I90: =#REF! -> #REF! | J90: =H90/G90 -> #REF! | K90: =I90/G90 -> #REF!
E91: 20 pcs | F91: 700 | G91: =F91/24.65 -> 28.397566 | H91: =#REF! -> #REF! | I91: =#REF! -> #REF! | J91: =H91/G91 -> #REF! | K91: =I91/G91 -> #REF!
B92: Flakes | C92: Phase 2_Creamy Onion Chicekn | E92: 10 pcs | F92: 350 | G92: =F92/24.65 -> 14.198783 | H92: =#REF! -> #REF! | I92: =#REF! -> #REF! | J92: =H92/G92 -> #REF! | K92: =I92/G92 -> #REF!
E93: 20 pcs | F93: 700 | G93: =F93/24.65 -> 28.397566 | H93: =#REF! -> #REF! | I93: =#REF! -> #REF! | J93: =H93/G93 -> #REF! | K93: =I93/G93 -> #REF!
C94: Phase 2_Creamy Jalapeno Chicken | E94: 10 pcs | F94: 350 | G94: =F94/24.65 -> 14.198783 | H94: =#REF! -> #REF! | I94: =#REF! -> #REF! | J94: =H94/G94 -> #REF! | K94: =I94/G94 -> #REF!
E95: 20 pcs | F95: 700 | G95: =F95/24.65 -> 28.397566 | H95: =#REF! -> #REF! | I95: =#REF! -> #REF! | J95: =H95/G95 -> #REF! | K95: =I95/G95 -> #REF!
C96: Cheesling Chicken | E96: 10 pcs | F96: 350 | G96: =F96/24.65 -> 14.198783 | H96: =#REF! -> #REF! | I96: =#REF! -> #REF! | J96: =H96/G96 -> #REF! | K96: =I96/G96 -> #REF!
E97: 20 pcs | F97: 700 | G97: =F97/24.65 -> 28.397566 | H97: =#REF! -> #REF! | I97: =#REF! -> #REF! | J97: =H97/G97 -> #REF! | K97: =I97/G97 -> #REF!
A98: Special Chicken | B98: Boneless | C98: Phase 2_UFO Chicken | E98: 20 pcs | F98: 750 | G98: =F98/24.65 -> 30.425963 | H98: =#REF! -> #REF! | I98: =#REF! -> #REF! | J98: =H98/G98 -> #REF! | K98: =I98/G98 -> #REF! | L98: =AVERAGE(J98:K99) -> #REF!
B99: Wing | C99: Phase 2_UFO Chicken | E99: 20 pcs | F99: 750 | G99: =F99/24.65 -> 30.425963 | H99: =#REF! -> #REF! | I99: =#REF! -> #REF! | J99: =H99/G99 -> #REF! | K99: =I99/G99 -> #REF!
A100: Grilled Chicken | B100: Whole Leg | C100: Jamaican (TBA) | E100: 2pcs | F100: 300 | G100: =F100/24.65 -> 12.170385 | H100: =#REF! -> #REF! | I100: =#REF! -> #REF! | J100: =H100/G100 -> #REF! | K100: =I100/G100 -> #REF! | L100: =AVERAGE(J100:K108) -> #REF!
C101: Korean Soy(TBA) | F101: 300 | G101: =F101/24.65 -> 12.170385 | H101: =#REF! -> #REF! | I101: =#REF! -> #REF! | J101: =H101/G101 -> #REF! | K101: =I101/G101 -> #REF!
...

Sheet Honduras(QSR Cost Table)
A2: bb.q Chicken Honduras Menu Food Cost
A3: Menu
A5: Sort | C5: Menu | E5: Description | F5: Sales Price HNL | G5: EST. SALE PPRICE USD | H5: TOTAL COST (Dine-In) | I5: TOTAL COST (Take Out) | J5: Food Cost | K5: NET PROFIT | L5: AVG D/I 50% + T/G 50% | M5: AVG Total
C6: BI_Golden Fried(2) | G6: 11 | H6: 1.8312791 | I6: 2.6252066 | J6: 0.23865514 | K6: 8.3747934 | O6: BI_Golden Fried(2) | P6: BI_Golden Fried Chicken (2pcs)
C7: BI_Golden Fried(3) | G7: 15 | H7: 2.7469186 | I7: 3.5408461 | J7: 0.23605641 | K7: 11.459154 | O7: BI_Golden Fried(3) | P7: BI_Golden Fried Chicken (2pcs)
C8: BI_Golden Fried(5) | G8: 21 | H8: 4.5781977 | I8: 5.3721252 | J8: 0.25581549 | K8: 15.627875 | O8: BI_Golden Fried(5) | P8: BI_Golden Fried Chicken (2pcs)
C9: BI_Classic(2) | G9: 11 | H9: 1.6107794 | I9: 2.2838242 | J9: 0.20762038 | K9: 8.7161758 | O9: BI_Classic(2) | P9: BI_Classic(Classic Chicken (2pcs) | T9: 2 pcs of Chicken 1 Side 1 Soft Drink | U9: 4 pcs of Chicken 1 Side 1 Soft Drink
C10: BI_Classic(3) | G10: 15 | H10: 2.4161691 | I10: 3.0892139 | J10: 0.20594759 | K10: 11.910786 | O10: BI_Classic(3) | P10: BI_Classic(Classic Chicken (2pcs) | T10: 3 pcs of Chicken 1 Side 1 Soft Drink | U10: 6 pcs of Chicken 1 Side 1 Soft Drink
C11: BI_Classic(5) | G11: 21 | H11: 4.0269485 | I11: 4.6999933 | J11: 0.2238092 | K11: 16.300007 | O11: BI_Classic(5) | P11: BI_Classic(Classic Chicken (2pcs) | T11: Couple Pack(5pc) 2 Sides 2 Soft Drinks | U11: Couple Pack(8pc) 2 Sides 2 Soft Drinks
C12: BI_Secret (2) | G12: 11 | H12: 2.2543844 | I12: 3.0629538 | J12: 0.27845035 | K12: 7.9370462 | O12: BI_Secret (2) | P12: BI_Secret (Secret Chicken (2pcs)
C13: BI_Secret (3) | G13: 15 | H13: 3.3815766 | I13: 4.190146 | J13: 0.27934307 | K13: 10.809854 | O13: BI_Secret (3) | P13: BI_Secret (Secret Chicken (2pcs) | T13: Couple Pack(5pc) 2 Sides 2 Soft Drinks | U13: Couple Pack(8pc) 2 Sides 2 Soft Drinks
C14: BI_Secret (5) | G14: 21 | H14: 5.6359609 | I14: 6.4445304 | J14: 0.3068824 | K14: 14.55547 | O14: BI_Secret (5) | P14: BI_Secret (Secret Chicken (2pcs)
C15: BI_Hot Spicy(2) | G15: 11 | H15: 2.1334742 | I15: 2.9420437 | J15: 0.26745852 | K15: 8.0579563 | O15: BI_Hot Spicy(2) | P15: BI_Hot Spicy Chicken (2pcs)
C16: BI_Hot Spicy(3) | G16: 15 | H16: 3.2002113 | I16: 4.0087808 | J16: 0.26725205 | K16: 10.991219 | O16: BI_Hot Spicy(3) | P16: BI_Hot Spicy Chicken (2pcs)
C17: BI_Hot Spicy(5) | G17: 21 | H17: 5.3336856 | I17: 6.142255 | J17: 0.29248833 | K17: 14.857745 | O17: BI_Hot Spicy(5) | P17: BI_Hot Spicy Chicken (2pcs)
C18: BI_Honey Garlic(2) | G18: 11 | H18: 1.8240623 | I18: 2.6326318 | J18: 0.23933016 | K18: 8.3673682 | O18: BI_Honey Garlic(2) | P18: BI_Honey Garlic Chicken (2pcs)
C19: BI_Honey Garlic(3) | G19: 15 | H19: 2.7360935 | I19: 3.5446629 | J19: 0.23631086 | K19: 11.455337 | O19: BI_Honey Garlic(3) | P19: BI_Honey Garlic Chicken (2pcs)
C20: BI_Honey Garlic(5) | G20: 21 | H20: 4.5601558 | I20: 5.3687252 | J20: 0.25565358 | K20: 15.631275 | O20: BI_Honey Garlic(5) | P20: BI_Honey Garlic Chicken (2pcs)
C21: BI_Soy Garlic(2) | G21: 11 | H21: 1.7428831 | I21: 2.5514526 | J21: 0.23195023 | K21: 8.4485474 | O21: BI_Soy Garlic(2) | P21: BI_Soy Garlic Chicken (2pcs)
C22: BI_Soy Garlic(3) | G22: 15 | H22: 2.6143247 | I22: 3.4228941 | J22: 0.22819294 | K22: 11.577106 | O22: BI_Soy Garlic(3) | P22: BI_Soy Garlic Chicken (2pcs)
C23: BI_Soy Garlic(5) | G23: 21 | H23: 4.3572078 | I23: 5.1657773 | J23: 0.24598939 | K23: 15.834223 | O23: BI_Soy Garlic(5) | P23: BI_Soy Garlic Chicken (2pcs)
C24: BI_Galbi(2) | G24: 11 | H24: 1.9952801 | I24: 2.8038496 | J24: 0.25489542 | K24: 8.1961504 | O24: BI_Galbi(2) | P24: BI_Galbi(Galbi Chicken (2pcs)
C25: BI_Galbi(3) | G25: 15 | H25: 2.987483 | I25: 3.7960524 | J25: 0.25307016 | K25: 11.203948 | O25: BI_Galbi(3) | P25: BI_Galbi(Galbi Chicken (2pcs)
... C89: BL_Lemon Cheesling(8) | G89: 14 | H89: 2.2693304 | I89: 3.0778999 | J89: 0.21984999 | K89: 10.9221 | O89: BL_Lemon Cheesling(8) | P89: BL_Lemon Cheesling Chicken (2pcs)
C90: Ddeok-Bokki | G90: 8.1135903 | H90: 1.941335 | I90: 2.1026033 | J90: 0.25914586 | K90: 6.010987
C91: Ddeok-Bokki_Cheese | G91: 10.141988 | H91: 2.4131181 | I91: 2.5743865 | J91: 0.25383451 | K91: 7.5676014
C92: Rose Ddeok-Bokki | G92: 12.170385 | H92: 2.5880918 | I92: 2.7493601 | J92: 0.22590576 | K92: 9.4210253
C93: Rose Ddeok-Bokki_Cheese | G93: 14.198783 | H93: 3.059875 | I93: 3.2211433 | J93: 0.22686052 | K93: 10.97764
C94: Fried Chicken Ricebowl(Soy) | G94: 8.1135903 | H94: 2.4973058 | I94: 2.8645311 | J94: 0.35305346 | K94: 5.2490592
C95: Fried Chicken Ricebowl(Hot) | G95: 8.1135903 | H95: 2.4394257 | I95: 2.806651 | J95: 0.34591974 | K95: 5.3069392
C96: Fried Chicken Ricebowl(Secret) | G96: 8.1135903 | H96: 2.4099 | I96: 2.7771252 | J96: 0.34228069 | K96: 5.336465
C97: Fried Chicken Ricebowl(Jamaican | G97: 8.1135903 | H97: 2.4222092 | I97: 2.7894345 | J97: 0.3437978 | K97: 5.3241558
C98: bb.q Salad | G98: 8.1135903 | H98: 1.2462237 | I98: 1.613449 | J98: 0.19885759 | K98: 6.5001413
C99: Fried Chicken Saladbowl(Soy) | G99: 10.141988 | H99: 3.4025832 | I99: 3.7698085 | J99: 0.37170312 | K99: 6.3721793
C100: Fried Chicken Saladbowl(Hot) | G100: 10.141988 | H100: 3.3447031 | I100: 3.7119284 | J100: 0.36599614 | K100: 6.4300594
C101: Fried Chicken Saladbowl(Secret) | G101: 10.141988 | H101: 3.3151774 | I101: 3.6824026 | J101: 0.3630849 | K101: 6.4595852
... C107: Cheesling Fries | G107: 6.0851927 | H107: 2.0022367 | I107: 2.083572 | J107: 0.34240033 | K107: 4.0016207
C108: Cheesstick | G108: 0 | H108: 2.4995985 | I108: 2.5809338 | J108: #DIV/0! | K108: -2.5809338
C109: Onion Rings | G109: 0 | H109: 0.85322422 | I109: 0.93455955 | J109: #DIV/0! | K109: -0.93455955
C110: Coleslaw | G110: 3.2454361 | H110: 0.13356441 | I110: 0.14409241 | J110: 0.044398473 | K110: 3.1013437
C111: Steamed Rice | G111: 3.2454361 | H111: 0.12714724 | I111: 0.50679981 | J111: 0.15615769 | K111: 2.7386363
C112: Side Sampler | G112: 0 | H112: 4.4080078 | I112: 4.4080078 | J112: #DIV/0! | K112: -4.4080078
C113: Soy Mayo | G113: 2.8397566 | H113: 0.66259085 | I113: 0.68961885 | J113: 0.24284435 | K113: 2.1501377
C114: Spicy Mayo | G114: 2.8397566 | H114: 0.60229911 | I114: 0.62932711 | J114: 0.22161305 | K114: 2.2104295
C115: Mala Mayo | G115: 2.8397566 | H115: 0.79921083 | I115: 0.82623883 | J115: 0.2909541 | K115: 2.0135178
C116: Jamaican Mayo | G116: 2.8397566 | H116: 0.79921083 | I116: 0.82623883 | J116: 0.2909541 | K116: 2.0135178
C117: Extra Sauce(Secret) | G117: 2.0283976 | H117: 0.40586405 | I117: 0.43289205 | J117: 0.21341578 | K117: 1.5955055
C118: Extra Sauce (Hot) | G118: 2.0283976 | H118: 0.46491561 | I118: 0.49194361 | J118: 0.2425282 | K118: 1.536454
C119: Extra Sauce (Honey) | G119: 2.0283976 | H119: 0.71357655 | I119: 0.74060455 | J119: 0.36511804 | K119: 1.287793
C120: Extra Sauce (Soy) | G120: 2.0283976 | H120: 0.58067576 | I120: 0.60770376 | J120: 0.29959795 | K120: 1.4206938
C121: Extra Sauce (GangJeong) | G121: 2.0283976 | H121: 0.48220801 | I121: 0.50923601 | J121: 0.25105336 | K121: 1.5191616
C122: Extra Sauce (Mala) | G122: 2.0283976 | H122: 0.84298611 | I122: 0.87001411 | J122: 0.42891696 | K122: 1.1583835
C123: Extra Sauce (Galbi) | G123: 2.0283976 | H123: 0.55972135 | I123: 0.58674935 | J123: 0.28926743 | K123: 1.4416482
C124: Extra Sauce (Hot Galbi) | G124: 2.0283976 | H124: 0.55972135 | I124: 0.58674935 | J124: 0.28926743 | K124: 1.4416482

Sheet Chicken Sales Unit Configur
B1: Chicken Sales Unit Configuration (Honduras)
B2: no. | D2: Fried Chicken - Whole Chicken | E2: Price / HNL | H2: Food Cost
E3: Half Size (8pcs) | F3: Whole Size(16pcs) | I3: Total
B4: 1 | C4: Phase 1 | D4: Golden Fried Chicken | E4: ='Honduras(Total Final)'!F6 -> 300 | F4: ='Honduras(Total Final)'!F7 -> 600 | H4: ='Honduras(Total Final)'!L6 -> #REF! | I4: =AVERAGE(H4,H20,H37,H53,H55,H59,H71,H76) -> #REF!
D5: Classic Fried Chicken
D6: Secret Sacued Chicken | E6: ='Honduras(Total Final)'!F10 -> 350 | F6: ='Honduras(Total Final)'!F11 -> 700
D7: Hot Spicy Chicken
D8: Honey Garlic Chicken
D9: Soy Garlic Chicken
D10: Galbi Chicken
D11: Hot Galbi Chikcen
D12: Gang-Jeong Chicken
D13: Gangnam Style Chicken
D14: Cheesling Chicken
C15: Phase 2 | D15: Caribbean Spicy Chicken
D16: Mala Hot Chicekn
D17: Creamy Onion Chicekn | E17: ='Honduras(Total Final)'!F30 -> 350 | F17: ='Honduras(Total Final)'!G31 -> 28.397566
D18: Creamy Jalapeno Chicken
D19: Fried Chicken - Boneless | E19: pcs | F19: 20pcs
B20: 1 | C20: Phase 1 | D20: Golden Fried Chicken | E20: ='Honduras(Total Final)'!F36 -> 300 | F20: ='Honduras(Total Final)'!F37 -> 600 | H20: ='Honduras(Total Final)'!L36 -> #REF!
D21: Classic Fried Chicken
D22: Golden Fried Tender
D23: Secret Sacued Chicken | E23: ='Honduras(Total Final)'!F42 -> 350 | F23: ='Honduras(Total Final)'!F43 -> 700
D24: Hot Spicy Chicken
D25: Honey Garlic Chicken
D26: Soy Garlic Chicken
D27: Galbi Chicken
D28: Hot Galbi Chikcen
D29: Gang-Jeong Chicken
D30: Gangnam Style Chicken
D31: Cheesling Chicken
C32: Phase 2 | D32: Caribbean Spicy Chicken
D33: Mala Hot Chicekn
D34: Creamy Onion Chicekn
D35: Creamy Jalapeno Chicken
D36: Fried Chicken - wing | E36: pcs | F36: 20pcs
B37: 1 | C37: Phase 1 | D37: Golden Fried Chicken | E37: ='Honduras(Total Final)'!F68 -> 300 | F37: ='Honduras(Total Final)'!F69 -> 600 | H37: ='Honduras(Total Final)'!L68 -> #REF!
D38: Classic Fried Chicken
D39: Secret Sacued Chicken | E39: ='Honduras(Total Final)'!F72 -> 350 | F39: ='Honduras(Total Final)'!F73 -> 700
D40: Hot Spicy Chicken
D41: Honey Garlic Chicken
D42: Soy Garlic Chicken
D43: Galbi Chicken
D44: Hot Galbi Chikcen
D45: Gang-Jeong Chicken
D46: Gangnam Style Chicken
D47: Cheesling Chicken
C48: Phase 2 | D48: Caribbean Spicy Chicken
D49: Mala Hot Chicekn
D50: Creamy Onion Chicekn
D51: Creamy Jalapeno Chicken
D52: Special Chicken - wing, boneless | E52: Wing | F52: Boneless Thigh
C53: Phase 2 | D53: UFO Chicken (Golden, Secret, Honey Garlic, Hot Galbi) | E53: ='Honduras(Total Final)'!F98 -> 750 | H53: ='Honduras(Total Final)'!L98 -> #REF!
D54: Grilled Chicken | E54: Whole Leg | F54: Wing | G54: Boneless Thigh
C55: Phase 1 | D55: Jamaican (TBA) | E55: ='Honduras(Total Final)'!F100 -> 300 | H55: ='Honduras(Total Final)'!L100 -> #REF!
D56: Korean Soy (TBA)
D57: Korean Gochujang(Spicy) (TBA)
D58: Rice Bowl, Salad Bowl, Meal | E58: Fried Chicken | F58: Grilled Chicken | G58: No Chicken
C59: Phase 1 | D59: Chicken Rice Bowl (Soy Garlic) | E59: ='Honduras(Total Final)'!F109 -> 200 | H59: ='Honduras(Total Final)'!L109 -> #REF!
D60: Chicken Rice Bowl (Hot Spicy)
D61: Chicken Rice Bowl (Secret Sauce)
D62: Chicken Rice Bowl (Jamaican)
C64: Phase 1 | D64: Chicken Salad Bowl (Soy Garlic) | E64: ='Honduras(Total Final)'!F113 -> 250
D65: Chicken Salad Bowl (Hot Spicy)
D66: Chicken Salad Bowl (Secret Sauce)
D67: Chicken Salad Bowl (Jamaican)
D68: BB.Q Salad | G68: ='Honduras(Total Final)'!F134 -> 200
C69: Phase 2 | D69: Chicken Meal(TBA) | E69: ='Honduras(Total Final)'!F128 -> 0
D70: K-Food, Side, Dipping Sauce, Extra Sauce
C71: Phase 1 | D71: Tteok-Bokki | E71: ='Honduras(Total Final)'!F130 -> 200 | H71: ='Honduras(Total Final)'!L130 -> 0.23377758
D72: Tteok-Bokki + Add Cheese | E72: ='Honduras(Total Final)'!F131 -> 250
D73: Rose Tteok-Bokki | E73: ='Honduras(Total Final)'!F132 -> 300
D74: Rose Tteok-Bokki + Add Cheese | E74: ='Honduras(Total Final)'!F133 -> 350
D75: French Fries Plain(250g) | E75: ='Honduras(Total Final)'!F135 -> 120
D76: Secret Fries (250g) | E76: ='Honduras(Total Final)'!F136 -> 150 | H76: ='Honduras(Total Final)'!L135 -> 0.23303094
D77: Soy Garlic Fries (250g)
D78: Spicy Fries (250g)
D79: Cheesling Fries (250g)
D80: Cheese stick | E80: 2000 | F80: The selling price is high. Consider removing it from the menu.
D81: Onion Ring | E81: 800 | F81: The selling price is high. Consider removing it from the menu.
D82: ColeSlaw | E82: 80
D83: Steamed Rice
D84: Side Sampler | E84: 2500 | F84: The selling price is high. Consider removing it from the menu.
D85: Soy 80g | E85: 70
D86: Spicy 80g
D87: Mala hot 80g
D88: Jamaican 80g
D89: Secret 80g | E89: 50
D90: Hot Spicy 80g
D91: Honey Garlic 80g
D92: Soy Garlic 80g
D93: Gang-Jeong 80g
D94: Mala hot 80g
D95: Galbi 80g
D96: Hot Galbi 80g

Sheet Master
A1: bb.q chicken food cost
Q2: 보고용
J3: #VALUE! | K3: {=_FV(J3,"Apertura")} -> 26.3801 | L3: =420/8 -> 52.5
A4: 카테고리 (Category) | B4: 품목명 (Item Name) | C4: 품목명 (Item Name) | D4: Manufacturer or Supplier | E4: Standard package (표준규격) | F4: Unit (무게) | H4: Quantity (g) | J4: Price ($) | K4: Price/g | L4: Input (g or %) | P4: Usage% (수율) | Q4: Note | S4: =16*S21 -> 453.592
I5: Lempiras
A6: 원료육 | B6: 홀치킨 | C6: Whole Chicken | D6: Cardeca | E6: 1 | F6: 1000 | G6: g | H6: 1000 | I6: 74.96 | J6: =+I6/$K$3 -> 2.8415359 | K6: =J6/H6 -> 0.0028415359 | L6: 650 | N6: 1300 | P6: 98 | Q6: Half (M): 650g / Whole (L): 1300g | R6: lb | S6: g
B7: 파티윙 | C7: Party Wings | E7: 1 | F7: 1000 | G7: g | H7: 1000 | I7: 60.5 | J7: =+I7/$K$3 -> 2.2933954 | K7: =J7/H7 -> 0.0022933954 | L7: 300 | M7: =L7*2 -> 600 | O7: =L7*3 -> 900 | P7: 95 | Q7: 윙- S: 8PC(420g) / M: 16PC (840g) / L: 24PC (1260g)] 본레스-S: 8PC(320g) / M: 16PC (640g) / L: 24PC (960g) | R7: 1 | S7: 453.592
B8: 순살 엉치살 | C8: Boneless Thigh | E8: 1 | F8: 1000 | G8: g | H8: 1000 | I8: 110.23 | J8: =+I8/$K$3 -> 4.1785285 | K8: =J8/H8 -> 0.0041785285 | L8: 240 | M8: =L8*2 -> 480 | O8: =L8*3 -> 720 | P8: 80 | R8: kg | S8: g
B9: 순살 가슴살 | C9: Boneless Breast | E9: 1 | F9: 1000 | G9: g | H9: 1000 | I9: 149.91 | J9: =+I9/$K$3 -> 5.6826926 | K9: =J9/H9 -> 0.0056826926 | P9: 80 | R9: 1 | S9: 1000
B11: 홀치킨_시스코 7월 가격 | C11: Whole Chicken | E11: 72/6.5oz | F11: 29.25 | G11: # | H11: =F11*S7 -> 13267.566 | J11: 93.26 | K11: =J11/H11 -> 0.0070291717 | L11: 650 | N11: 1300 | P11: 90 | Q11: Half (M): 650g / Whole L): 1300g | R11: G | S11: g | T11: Cooking Oil
B12: 파티윙_시스코 7월 가격 | C12: Party Wings IQF | E12: 6/5# | F12: 30 | G12: # | H12: =F12*S7 -> 13607.76 | J12: 126.06 | K12: =J12/H12 -> 0.0092638318 | L12: 420 | M12: =L12*2 -> 840 | O12: =L12*3 -> 1260 | P12: 95 | Q12: 윙- S: 8PC(420g) / M: 16PC (840g) / L: 24PC (1260g)] 본레스-S: 8PC(320g) / M: 16PC (640g) / L: 24PC (960g) | R12: 1 | S12: 3785.42
B13: 순살 엉치살_시스코 7월 가격 | C13: Boneless Thigh | E13: 1/40# | F13: 40 | G13: # | H13: =F13*S7 -> 18143.68 | J13: 100.79 | K13: =J13/H13 -> 0.0055551024 | L13: 320 | M13: =L13*2 -> 640 | O13: =L13*3 -> 960 | P13: 80
B14: 순살 가슴살_시스코 7월 가격 | C14: Boneless Breast | E14: 2/5# | F14: 10 | G14: # | H14: =F14*S7 -> 4535.92 | J14: 91.1 | K14: =J14/H14 -> 0.020084128 | P14: 80 | R14: fl.oz | S14: g | T14: Cooking Oil
R15: 1 | S15: 26.02
B16: 파티윙 | C16: Party Wings | E16: 1/40# | F16: 40 | G16: # | H16: =F16*S7 -> 18143.68 | J16: 135.99 | K16: =J16/H16 -> 0.0074951719 | L16: 420 | M16: =L16*2 -> 840 | O16: =L16*3 -> 1260 | P16: 95 | Q16: 윙- S: 8PC(420g) / M: 16PC (840g) / L: 24PC (1260g)] 본레스-S: 8PC(320g) / M: 16PC (640g) / L: 24PC (960g)
B17: 순살 엉치살 | C17: Boneless Thigh | E17: 1/40# | F17: 40 | G17: # | H17: =F17*S7 -> 18143.68 | J17: 89.76 | K17: =J17/H17 -> 0.0049471772 | L17: 320 | M17: =L17*2 -> 640 | O17: =L17*3 -> 960 | P17: 80 | R17: Liter | S17: g
B18: 순살 가슴살 | C18: Boneless Breast | E18: 1/40# | F18: 40 | G18: # | H18: =F18*S7 -> 18143.68 | J18: 86.02 | K18: =J18/H18 -> 0.0047410448 | P18: 80 | R18: 1 | S18: 1000
B20: 홀치킨 | C20: Whole Chicken | E20: 1/50# | F20: 50 | G20: # | H20: =F20*S7 -> 22679.6 | J20: 77.5 | K20: =J20/H20 -> 0.0034171679 | L20: 650 | N20: 1300 | P20: 90 | Q20: Half (M): 650g / Whole L): 1300g | R20: oz | S20: g
B21: 파티윙 | C21: Party Wings | E21: 1/40# | F21: 40 | G21: # | H21: =F21*S7 -> 18143.68 | J21: 148.6 | K21: =J21/H21 -> 0.0081901797 | L21: 420 | M21: =L21*2 -> 840 | O21: =L21*3 -> 1260 | P21: 95 | Q21: 윙- S: 8PC(420g) / M: 16PC (840g) / L: 24PC (1260g)] 본레스-S: 8PC(320g) / M: 16PC (640g) / L: 24PC (960g) | R21: 1 | S21: 28.3495
B22: 순살 엉치살 | C22: Boneless Thigh | E22: 1/40# | F22: 40 | G22: # | H22: =F22*S7 -> 18143.68 | J22: 86.95 | K22: =J22/H22 -> 0.0047923023 | L22: 320 | M22: =L22*2 -> 640 | O22: =L22*3 -> 960 | P22: 80
B23: 순살 가슴살 | C23: Boneless Breast | E23: 1/40# | F23: 40 | G23: # | H23: =F23*S7 -> 18143.68 | J23: 62 | K23: =J23/H23 -> 0.0034171679 | P23: 80 | R23: *원가계산시 원료육 Maximum것 사용함.
B25: 홀치킨 | C25: Whole Chicken | E25: 1/50# | F25: 50 | G25: # | H25: =F25*S7 -> 22679.6 | J25: 69.2 | K25: =J25/H25 -> 0.0030512002 | L25: 650 | N25: 1300 | P25: 90 | Q25: Half (M): 650g / Whole L): 1300g
B26: 파티윙 | C26: Party Wings | E26: 1/40# | F26: 40 | G26: # | H26: =F26*S7 -> 18143.68 | J26: 148.28 | K26: =J26/H26 -> 0.0081725427 | L26: 420 | M26: =L26*2 -> 840 | O26: =L26*3 -> 1260 | P26: 95 | Q26: 윙- S: 8PC(420g) / M: 16PC (840g) / L: 24PC (1260g)] 본레스-S: 8PC(320g) / M: 16PC (640g) / L: 24PC (960g)
B27: 순살 엉치살 | C27: Boneless Thigh | E27: 1/40# | F27: 40 | G27: # | H27: =F27*S7 -> 18143.68 | J27: 90.82 | K27: =J27/H27 -> 0.0050055997 | L27: 320 | M27: =L27*2 -> 640 | O27: =L27*3 -> 960 | P27: 80
A29: 오일 | B29: 카놀라유 | C29: Canola Oil | D29: MAYAB | E29: 1G | F29: 1 | G29: G | H29: =F29*S12 -> 3785.42 | I29: 311 | J29: =+I29/$K$3 -> 11.78919 | K29: =J29/H29 -> 0.0031143676 | L29: 0.25 | P29: 100 | Q29: 원료육 중량대비 25%
B30: 팜유 | C30: Palm Oil | D30: Hondu Palma | E30: 5L | F30: 5 | G30: L | H30: =F30*S18 -> 5000 | J30: =+I30/$K$3 -> 0 | K30: =J30/H30 -> 0 | P30: 100 | Q30: 원료육 중량대비 25%
B31: 해바라기 유 | C31: Sunflower Oil | D31: Hondu Palma | E31: 1.32 L | F31: 1.32 | G31: L | H31: =F31*S18 -> 1320 | I31: 394.95 | J31: =+I31/$K$3 -> 14.971513 | K31: =J31/H31 -> 0.011342055 | L31: 3.5 | M31: 7 | N31: 10 | P31: 100 | Q31: 원료육 중량대비 25%
B32: 올리브오일 | C32: Oilve Oil | D32: Comit | E32: 1L | F32: 1 | G32: L | H32: =F32*S18 -> 1000 | I32: 393.59 | J32: =+I32/$K$3 -> 14.919959 | K32: =J32/H32 -> 0.014919959 | P32: 100 | Q32: 원료육 중량대비 25%
B33: 고추기름 | C33: Chili Oil | E33: 80g | F33: 80 | G33: g | H33: 80 | J33: 5.99 | K33: =J33/H33 -> 0.074875 | P33: 100
B34: 혼합유 | C34: Mix Oil | D34: Hondu Palma | E34: 35LB | F34: 35 | G34: # | H34: =F34*S7 -> 15875.72 | I34: 740 | J34: =+I34/$K$3 -> 28.051448 | K34: =J34/H34 -> 0.0017669402 | Q34: 원료육 중량대비 25%
A35: 파우더 | B35: 치즐링 파우더 | C35: Cheese Flavor Seasoning | D35: HQ | E35: 500g/15bag | F35: =500*15 -> 7500 | G35: g | H35: 7500 | I35: 2480.5 | J35: =+I35/$K$3 -> 94.029211 | K35: =J35/H35 -> 0.012537228 | L35: 0.07 | P35: 98
B36: #2 마리네이드 파우더 | C36: Marinade Powder Mix | D36: HQ | E36: 5kg/4bag | F36: 20 | G36: kg | H36: =F36*$S$9 -> 20000 | I36: 4163.25 | J36: =+I36/$K$3 -> 157.81782 | K36: =J36/H36 -> 0.0078908912 | L36: 0.013 | N36: 0.012 | P36: 98 | Q36: 홀 & 윙: 1.3% / 본레스: 1.2%
B37: 비비윙 염지제 | C37: Marinade No 5 | E37: 5kg/1bag | F37: 5 | G37: kg | H37: =F37*$S$9 -> 5000 | J37: 44.94 | K37: =J37/H37 -> 0.008988 | L37: 0.07 | N37: 0.17 | P37: 100 | Q37: 비비
B38: 치킨 염지제 | C38: Pickle Solution Powder Mix [G28484] | D38: HQ | E38: 5kg/4bag | F38: 20 | G38: kg | H38: =F38*$S$9 -> 20000 | I38: 1960.65 | J38: =+I38/$K$3 -> 74.323069 | K38: =J38/H38 -> 0.0037161535 | L38: 0.065 | M38: 0.003 | N38: 0.17 | P38: 98 | Q38: 일반(6.5%) / BB(0.3%) / 원료육 무게대비(17%)
B39: 저크 시즈닝 | C39: Jerk Seasoning | D39: HQ | E39: 5kg/4bag | F39: =5*4 -> 20 | G39: kg | H39: =F39*$S$9 -> 20000 | I39: 7587.37 | J39: =+I39/$K$3 -> 287.61718 | K39: =J39/H39 -> 0.014380859 | P39: 100
B40: 빠리배터믹스 [A82256] | C40: Battering Powder Mix (P-Type) [A82256] | E40: 5#/5bag | F40: 25 | G40: # | H40: =F40*S7 -> 11339.8 | J40: 72 | K40: =J40/H40 -> 0.0063493183 | L40: 0.1 | P40: 100 | Q40: 원료육 중량대비 10%
B41: 화이트 배터믹스 (White) | C41: Battering Powder Mix | D41: HQ | E41: 5kg/4bag | F41: 20 | G41: kg | H41: 20000 | I41: 2147.41 | J41: =+I41/$K$3 -> 81.402648 | K41: =J41/H41 -> 0.0040701324 | L41: 0.25 | P41: 85 | Q41: White Chicken: 원료육 중량대비 25%
B42: 비비윙스 파우더 [A20021] | C42: Batter Mix #8 [A20021] | E42: 50#/1bag | F42: 50 | G42: # | H42: =F42*S7 -> 22679.6 | J42: 77.68 | K42: =J42/H42 -> 0.0034251045 | P42: 100
B43: 옐로우 배터믹스 [Battering Powder Mix-C] | C43: Battering Powder Mix-C | D43: HQ | E43: 2kg/10bag | F43: 20 | G43: kg | H43: =F43*$S$9 -> 20000 | I43: 2349.93 | J43: =+I43/$K$3 -> 89.079647 | K43: =J43/H43 -> 0.0044539824 | L43: 0.11 | P43: 98 | Q43: 원료육 중량대비 10%
A45: 소스 | B45: 져크바베큐 소스 | C45: Jerk Barbecue Sauce (Cajun Sauce) | D45: HQ | E45: 2kg/5bag | F45: 10 | G45: kg | H45: =F45*S9 -> 10000 | I45: 1361.47 | J45: =+I45/$K$3 -> 51.609736 | K45: =J45/H45 -> 0.0051609736 | P45: 96
B46: 시크릿 양념소스 | C46: BBQ Secret Spicy Sauce | D46: HQ | E46: 2kg/5bag | F46: 10 | G46: kg | H46: =F46*S9 -> 10000 | I46: 1283.61 | J46: =+I46/$K$3 -> 48.658269 | K46: =J46/H46 -> 0.0048658269 | L46: 0.3 | P46: 96
B47: 데리 소스 | C47: Deri Sauce Mix (P-Type) | D47: HQ | E47: 2kg/5bag | F47: 10 | G47: kg | H47: =F47*S9 -> 10000 | I47: 1649.73 | J47: =+I47/$K$3 -> 62.536912 | K47: =J47/H47 -> 0.0062536912 | L47: 0.1 | P47: 96
B48: 소이갈릭소스 | C48: Garlic Flavor Soy Sauce | D48: HQ | E48: 2kg/5bag | F48: 10 | G48: kg | H48: =F48*S9 -> 10000 | I48: 1836.48 | J48: =+I48/$K$3 -> 69.616112 | K48: =J48/H48 -> 0.0069616112 | L48: 0.07 | P48: 96
B49: 강정 소스 | C49: Honey Pepper Sauce | D49: HQ | E49: 2kg/5bag | F49: 10 | G49: kg | H49: =F49*S9 -> 10000 | I49: 1525.06 | J49: =+I49/$K$3 -> 57.811001 | K49: =J49/H49 -> 0.0057811001 | L49: 0.25 | P49: 96
B50: 매운양념 소스 | C50: Hot Spicy Sauce | D50: HQ | E50: 2kg/5bag | F50: 10 | G50: kg | H50: =F50*S9 -> 10000 | I50: 1470.37 | J50: =+I50/$K$3 -> 55.737848 | K50: =J50/H50 -> 0.0055737848 | L50: 0.2 | N50: 0.15 | P50: 96 | Q50: Hot Spicy: 20% / Wings of Fire: 15%
B51: 허니갈릭 소스 | C51: Sweet Soy Sauce | D51: HQ | E51: 2kg/5bag | F51: 10 | G51: kg | H51: =F51*S9 -> 10000 | I51: 2256.8 | J51: =+I51/$K$3 -> 85.549335 | K51: =J51/H51 -> 0.0085549335 | L51: 0.08 | P51: 96
B52: 갈비 소스 | C52: Galbi Flavor Sauce | D52: HQ | E52: 2kg/6bag | F52: 12 | G52: kg | H52: =F52*S9 -> 12000 | I52: 2124.25 | J52: =+I52/$K$3 -> 80.524714 | K52: =J52/H52 -> 0.0067103928 | L52: 0.2 | P52: 96
B53: 떡볶이 소스 | C53: Shin Alltokkbokki Sauce (New Hot Pepper) | D53: HQ | E53: 2kg/5bag | F53: 10 | G53: kg | H53: =F53*S9 -> 10000 | I53: 2680.56 | J53: =+I53/$K$3 -> 101.61296 | K53: =J53/H53 -> 0.010161296 | P53: 96 | Q53: 떡볶이 소스 only
B54: 마라핫 소스 | C54: Mala Hot Sauce | D54: HQ | E54: 3kg/4bag | F54: 12 | G54: kg | H54: =F54*S9 -> 12000 | J54: 121.39 | K54: =J54/H54 -> 0.010115833 | L54: 0.2 | P54: 96
B55: 매운갈비 소스 | C55: Hot Galbi Flavor Sauce Mix | D55: HQ | E55: 2kg/6bag | F55: 12 | G55: kg | H55: =F55*S9 -> 12000 | I55: 2124.25 | J55: =+I55/$K$3 -> 80.524714 | K55: =J55/H55 -> 0.0067103928 | L55: 0.2 | P55: 96
B56: 자소만 소스 | C56: Jasoman Sauce | D56: HQ | E56: 2kg/5bag | F56: 10 | G56: kg | H56: =F56*S9 -> 10000 | I56: 1828.6 | J56: =+I56/$K$3 -> 69.317402 | K56: =J56/H56 -> 0.0069317402 | L56: 0.2 | P56: 96
A58: Dry | B58: 소고기 다시다 | C58: DASHIDA SOGOGI(CJ) | E58: 20/12x60g | F58: 14400 | G58: g | H58: =F58 -> 14400 | J58: 193 | K58: =J58/H58 -> 0.013402778 | P58: 100
B59: 고추가루 | C59: Red Chili Pepper | E59: 5# | F59: 5 | G59: # | H59: =F59*S7 -> 2267.96 | J59: 17.86 | K59: =J59/H59 -> 0.0078749184 | P59: 100
B60: 고추장 | C60: Gochujang Hot 17kg | E60: 17kg | F60: 17 | G60: kg | H60: =F60*S9 -> 17000 | J60: 45 | K60: =J60/H60 -> 0.0026470588 | P60: 100
B61: 치킨스톡 | C61: Fine Sea Salt(Sempio) | E61: 5/3kg | F61: 15 | G61: kg | H61: =F61*S9 -> 15000 | J61: 34.94 | K61: =J61/H61 -> 0.0023293333 | P61: 100
B62: 뉴슈가 | C62: New Sugar 오뚜기 Korean | E62: 100g/10 | F62: 1000 | G62: g | H62: 1000 | J62: 14 | K62: =J62/H62 -> 0.014 | P62: 100
B63: 미원 | C63: MSG (Ajinomodo) | E63: 4/6# | F63: 24 | G63: # | H63: =F63*S7 -> 10886.208 | J63: 93.4 | K63: =J63/H63 -> 0.0085796634 | P63: 100
B64: 간장 | C64: Soy Sauce (Maeil 12/1L) Korean | E64: 12L | F64: 12 | G64: L | H64: =F64*S18 -> 12000 | J64: 39.25 | K64: =J64/H64 -> 0.0032708333 | P64: 100
B65: 데리야끼소스 | C65: Kikkoman Glaze, Teriyaki | E65: 5# | F65: 5 | G65: # | H65: =F65*S7 -> 2267.96 | J65: 15.95 | K65: =J65/H65 -> 0.0070327519 | P65: 100
B66: 스리라차 소스 | C66: Sriracha Sauce | E66: 1# | F66: 1 | G66: # | H66: =F66*S7 -> 453.592 | J66: 3.49 | K66: =J66/H66 -> 0.0076941392 | P66: 100
B67: 물엿 | C67: Corn Syrup | D67: mayab | E67: 16oz | F67: 16 | G67: oz | H67: =F67*S21 -> 453.592 | I67: 71.25 | J67: =+I67/$K$3 -> 2.7008995 | K67: =J67/H67 -> 0.0059544691 | P67: 100
B68: 마요네즈 | C68: Mayonnaise | D68: dinitas | E68: 3.63kg | F68: 3.63 | G68: kg | H68: =F68*S9 -> 3630 | I68: 275.65 | J68: =+I68/$K$3 -> 10.449164 | K68: =J68/H68 -> 0.0028785577 | P68: 100 | Q68: 1 US Gallon of Mayonnaise weighs 7.5#.
B69: 식초 | C69: Vinegar Distilled | D69: Dinitas | E69: 1G | F69: 1 | G69: G | H69: =F69*S12 -> 3785.42 | I69: 105 | J69: =+I69/$K$3 -> 3.980273 | K69: =J69/H69 -> 0.0010514746 | P69: 100 | Q69: 1 US fluid ounce of vinegar weighs 28.7 grams.
B70: 강초 | C70: concentrated Vinegar(korean) | E70: 1.8L/9 | F70: 16.2 | G70: L | H70: =F70*S18 -> 16200 | J70: 42.87 | K70: =J70/H70 -> 0.0026462963 | P70: 100
B71: 미림 | C71: Rice Wine(Cook wine) | D71: alza / Belca / Mayab | E71: 1000 ML | F71: 1 | G71: L | H71: =F71*S18 -> 1000 | I71: 310 | J71: =+I71/$K$3 -> 11.751282 | K71: =J71/H71 -> 0.011751282 | P71: 100 | Q71: 8oz(mirim):272g=16.9oz:x / x=574.6g
B72: 케첩 (벌크) | C72: Ketchup / bulk | D72: Mayab | E72: 7 lb | F72: 7 | G72: # | H72: =F72*S7 -> 3175.144 | I72: 176.67 | J72: =+I72/$K$3 -> 6.6970936 | K72: =J72/H72 -> 0.0021092252 | P72: 100
B73: 레몬주스 | C73: Lemon Juice | D73: Naranjal | E73: 1G | F73: 1 | G73: G | H73: =F73*S12 -> 3785.42 | I73: 300 | J73: =+I73/$K$3 -> 11.372209 | K73: =J73/H73 -> 0.0030042132 | P73: 100 | Q73: 1 US fluid ounce of lemon juice weighs 28.7 grams.
B74: 설탕 | C74: White Sugar | D74: ALZA | E74: 1# | F74: 1 | G74: # | H74: =F74*S7 -> 453.592 | I74: 12.5 | J74: =+I74/$K$3 -> 0.47384202 | K74: =J74/H74 -> 0.0010446437 | P74: 100
B75: 소금 | C75: Salt | D75: DINITAS | E75: 26oz | F75: 26 | G75: oz | H75: =F75*S21 -> 737.087 | I75: 8.58 | J75: =+I75/$K$3 -> 0.32524517 | K75: =J75/H75 -> 0.0004412575 | P75: 100 | Q75: 1LB= 453.592g
B76: 통후추 | C76: Black Pepper (Whole) | E76: 16oz | F76: 16 | G76: oz | H76: =F76*S21 -> 453.592 | J76: 8.33 | K76: =J76/H76 -> 0.018364521 | P76: 100
B77: 후추 | C77: Black Pepper | D77: MAYAB | E77: 40g | F77: 40 | G77: g | H77: 40 | I77: 0.088 | J77: =+I77/$K$3 -> 0.0033358479 | K77: =J77/H77 -> 8.3396196e-05 | P77: 100
B78: 참기름 | C78: Sesame Oil | D78: alza / Belca / Mayab | E78: 56oz | F78: 56 | G78: oz | H78: =F78*S21 -> 1587.572 | I78: 1311.11 | J78: =+I78/$K$3 -> 49.700721 | K78: =J78/H78 -> 0.031306121 | P78: 100
B79: 참깨 | C79: Sesame Seeds | D79: mayab | E79: 16oz | F79: 16 | G79: oz | H79: =F79*S21 -> 453.592 | I79: 130 | J79: =+I79/$K$3 -> 4.9279571 | K79: =J79/H79 -> 0.010864294 | P79: 100
B80: 김치 | C80: Kimchi (토바기) Korea | D80: FRUTVER | E80: 1# | F80: 1 | G80: # | H80: =F80*S7 -> 453.592 | I80: 26 | J80: =+I80/$K$3 -> 0.98559141 | K80: =J80/H80 -> 0.0021728589 | P80: 80
B81: 떡볶이 떡 | C81: Rice Cakes | E81: 600g/12 | F81: 7200 | G81: g | H81: 7200 | J81: 49.07 | K81: =J81/H81 -> 0.0068152778 | P81: 100
B82: 오뎅 | C82: Fish Cake | E82: 10/1kg | F82: 10000 | G82: g | H82: 10000 | J82: 92.74 | K82: =J82/H82 -> 0.009274 | P82: 100
B83: 오뎅 믹스 | C83: O-deng Mixed (Wang) | E83: 58ea/1kg | F83: 1 | G83: kg | H83: =F83*S9 -> 1000 | J83: 4.99 | K83: =J83/H83 -> 0.00499 | P83: 100
B84: 쌀 | C84: Grain Rice (Rice Golden) | D84: alza / Belca / Mayab | E84: 25# | F84: 25 | G84: # | H84: =F84*S7 -> 11339.8 | I84: 380 | J84: =+I84/$K$3 -> 14.404798 | K84: =J84/H84 -> 0.0012702867 | P84: 100
B85: 오이피클 | C85: Pickled Cucumber | D85: Mayab | E85: 1G | F85: 1 | G85: G | H85: =F85*S12 -> 3785.42 | I85: 256 | J85: =+I85/$K$3 -> 9.7042847 | K85: =J85/H85 -> 0.0025635952 | P85: 70
B86: 햄버거번 | C86: Brioche Bun | E86: 72ea | F86: 72 | G86: ea | H86: 72 | J86: 43.49 | K86: =J86/H86 -> 0.60402778 | P86: 100
B87: 또띠아 | C87: Tortillas | E87: 80ea | F87: 80 | G87: ea | H87: 80 | J87: 14.91 | K87: =J87/H87 -> 0.186375 | P87: 100
B88: 라면 | C88: Shin Ramyun | E88: 16ea | F88: 16 | G88: ea | H88: 16 | J88: 18.99 | K88: =J88/H88 -> 1.186875 | P88: 100
B89: Corn Kernel | C89: Corn Kernel | D89: alza / Belca / Mayab | E89: 425g | F89: 425 | G89: g | H89: 425 | I89: 18.74 | J89: =+I89/$K$3 -> 0.71038396 | K89: =J89/H89 -> 0.0016714917 | P89: 100
B90: 멸치 다시팩 | C90: Soup Stock Anchovy | E90: 8ea/1pk | F90: 8 | G90: ea | H90: 8 | J90: 7.99 | K90: =J90/H90 -> 0.99875 | P90: 100 | Q90: 단위는 ea
B91: 치킨스톡 | C91: Chicken Stock | E91: 4/24oz | F91: 96 | G91: oz | H91: =F91*S21 -> 2721.552 | J91: 138.45 | K91: =J91/H91 -> 0.050871708 | P91: 100
B92: 굴소스 | C92: F | E92: 2lb | F92: 2 | G92: lb | H92: =F92*S7 -> 907.184 | J92: 5.99 | K92: =J92/H92 -> 0.0066028501 | P92: 100
B93: 베이크드 빈 | C93: Baked Bean | E93: 443.55g | F93: 443.55 | G93: g | H93: =F93 -> 443.55 | J93: 0.88 | K93: =J93/H93 -> 0.0019839928 | P93: 100
B94: 라면 사리 | C94: Ottogi Ramyonsari (오뚜기) | E94: 1ea | F94: 1 | G94: ea | H94: =F94 -> 1 | J94: 0.99 | K94: =J94/H94 -> 0.99 | P94: 100 | Q94: 1봉지당 $0.99
B95: 파슬리 가루 | C95: Parsely Flakes | D95: comit | E95: 28g | F95: 28 | G95: g | H95: 28 | I95: 18.44 | J95: =+I95/$K$3 -> 0.69901176 | K95: =J95/H95 -> 0.024964706 | P95: 100
B96: 나쵸 | C96: Tostitos Original Restaurant Style Tortilla Chips | E96: 17oz/1bag | F96: 17 | G96: oz | H96: =F96*S21 -> 481.9415 | J96: 5.48 | K96: =J96/H96 -> 0.011370675 | P96: 100
B97: 할라피뇨 통조림(슬라이스) | C97: Pickled Jalape Nacho Slices | E97: 12oz/1can | F97: 12 | G97: oz | H97: =F97*S21 -> 340.194 | J97: 1.73 | K97: =J97/H97 -> 0.0050853337 | P97: 62 | Q97: 1can(340g)에 7servings(210g))(1serving(30g) x 7)
B98: 과카몰리 | C98: Guacamole | D98: pricesmart | E98: 12oz/1can | F98: 12 | G98: oz | H98: =F98*S21 -> 340.194 | I98: 194.95 | J98: =+I98/$K$3 -> 7.3900402 | K98: =J98/H98 -> 0.021723018 | P98: 100
B99: 크러시 피넛 | C99: Crushed Peanut | D99: alza / Belca / Mayab | E99: 1.13kg | F99: 1.13 | G99: kg | H99: =F99*S9 -> 1130 | I99: 217 | J99: =+I99/$K$3 -> 8.2258976 | K99: =J99/H99 -> 0.0072795554 | P99: 100 | Q99: 물에 불렸을 때 무게증가율 : 6배
B100: 콜슬로우 드레싱 | C100: Coleslaw Dressing | E100: 4/1Gal | F100: 4 | G100: G | H100: =F100*S12 -> 15141.68 | J100: 46.02 | K100: =J100/H100 -> 0.0030392929 | P100: 100
B101: 베이컨 | C101: Bacon | D101: ALZA | E101: 1# | F101: 1 | G101: # | H101: =F101*S7 -> 453.592 | I101: 97.68 | J101: =+I101/$K$3 -> 3.7027911 | K101: =J101/H101 -> 0.0081632637 | P101: 100
A103: 야채 | B103: 마늘 | C103: Garlic(Peeled) | D103: FECUNDA | E103: 2.2# | F103: 2.2 | G103: # | H103: =F103*S7 -> 997.9024 | I103: 181 | J103: =+I103/$K$3 -> 6.8612325 | K103: =J103/H103 -> 0.0068756549 | L103: 0.005 | N103: 0.19 | P103: 98 | Q103: Secret Spicy: 0.5% / Honey Garlic: 19% (소스대비)
B104: 양파 | C104: Onion | D104: frutver / Frutali | E104: 1# | F104: 1 | G104: # | H104: =F104*S7 -> 453.592 | I104: 16 | J104: =+I104/$K$3 -> 0.60651779 | K104: =J104/H104 -> 0.0013371439 | P104: 89
B105: 파 | C105: Spring Onion | D105: frutver / Frutali | E105: 180g | F105: 180 | G105: 9 | H105: =F105 -> 180 | I105: 17 | J105: =+I105/$K$3 -> 0.64442515 | K105: =J105/H105 -> 0.0035801397 | L105: 0.05 | P105: 95 | Q105: 갈비, 매운갈비, 마라핫 (소스대비) | S105: =F104*S7 -> 453.592
B106: 다진 마늘 | C106: Minced Garlic | D106: alza / Belca / Mayab | E106: 32oz | F106: 32 | G106: oz | H106: =F106*S21 -> 907.184 | I106: 127 | J106: =+I106/$K$3 -> 4.814235 | K106: =J106/H106 -> 0.00530679 | P106: 98
B107: 양배추 | C107: Cabbage | D107: FRUTALI | E107: 1# | F107: 1 | G107: # | H107: =F107*S7 -> 453.592 | I107: 10 | J107: =+I107/$K$3 -> 0.37907362 | K107: =J107/H107 -> 0.00083571496 | P107: 79
...

Sheet Prep
A1: 1. Sauce & Powder
A3: 김치 베이스 (Kimchi Base) | J3: 떡볶이 소스 믹스 (Ddeok-Bokki Sauce Mix) | S3: Jamaican Mayo
A4: Ingredients | D4: Weight (%) | E4: Input (g) | F4: Usage (%) | G4: Input+ Usage | H4: Price | J4: Ingredients | M4: Weight (%) | N4: Input (g) | O4: Usage (%) | P4: Input+ Usage | Q4: Price | S4: Ingredients | V4: Weight (%) | W4: Input (g) | X4: Usage (%) | Y4: Input+ Usage | Z4: Price
A6: 1 | B6: =Master!B80 -> 김치 | C6: =Master!C80 -> Kimchi (토바기) Korea | D6: 0.852 | E6: =D6*C14 -> 852 | F6: =Master!P80 -> 80 | G6: =E6/F6*100 -> 1065 | H6: =G6*Master!K80 -> 2.3140947 | J6: 1 | K6: =Master!B53 -> 떡볶이 소스 | L6: =Master!C53 -> Shin Alltokkbokki Sauce (New Hot Pepper) | M6: 0.25 | N6: =M6*L14 -> 2000 | O6: =Master!P53 -> 96 | P6: =N6/O6*100 -> 2083.3333 | Q6: =P6*Master!K53 -> 21.169366 | S6: 1 | T6: =Master!B68 -> 마요네즈 | U6: =Master!C68 -> Mayonnaise | V6: 0.5 | W6: 900 | X6: =Master!P68 -> 100 | Y6: =W6/X6*100 -> 900 | Z6: =Y6*Master!K68 -> 2.5907019
A7: 2 | B7: =Master!B74 -> 설탕 | C7: =Master!C74 -> White Sugar | D7: 0.028 | E7: =D7*C14 -> 28 | F7: =Master!P74 -> 100 | G7: =E7/F7*100 -> 28 | H7: =G7*Master!K74 -> 0.029250024 | S7: 2 | T7: =Master!B54 -> 마라핫 소스 | U7: =Master!C54 -> Mala Hot Sauce | V7: 0.5 | W7: 300 | X7: =Master!P54 -> 96 | Y7: =W7/X7*100 -> 312.5 | Z7: =Y7*Master!K54 -> 3.1611979
A8: 3 | B8: =Master!B64 -> 간장 | C8: =Master!C64 -> Soy Sauce (Maeil 12/1L) Korean | D8: 0.02 | E8: =D8*C14 -> 20 | F8: =Master!P64 -> 100 | G8: =E8/F8*100 -> 20 | H8: =G8*Master!K64 -> 0.065416667 | J8: 2 | K8: 물 | L8: Filtered Water | M8: 0.75 | N8: =M8*L14 -> 6000 | O8: 100 | P8: =N8/O8*100 -> 6000 | Q8: -
A9: 4 | B9: =Master!B63 -> 미원 | C9: =Master!C63 -> MSG (Ajinomodo) | D9: 0.012 | E9: =D9*C14 -> 12 | F9: =Master!P63 -> 100 | G9: =E9/F9*100 -> 12 | H9: =G9*Master!K63 -> 0.10295596
A10: 5 | B10: =Master!B58 -> 소고기 다시다 | C10: =Master!C58 -> DASHIDA SOGOGI(CJ) | D10: 0.034 | E10: =D10*C14 -> 34 | F10: =Master!P58 -> 100 | G10: =E10/F10*100 -> 34 | H10: =G10*Master!K58 -> 0.45569444
A11: 6 | B11: =Master!B78 -> 참기름 | C11: =Master!C78 -> Sesame Oil | D11: 0.014 | E11: =D11*C14 -> 14 | F11: =Master!P78 -> 100 | G11: =E11/F11*100 -> 14 | H11: =G11*Master!K78 -> 0.4382857
A12: 7 | B12: =Master!B59 -> 고추가루 | C12: =Master!C59 -> Red Chili Pepper | D12: 0.03 | E12: =D12*C14 -> 30 | F12: =Master!P59 -> 100 | G12: =E12/F12*100 -> 30 | H12: =G12*Master!K59 -> 0.23624755
A13: 8 | B13: =Master!B29 -> 카놀라유 | C13: =Master!C29 -> Canola Oil | D13: 0.01 | E13: =D13*C14 -> 10 | F13: =Master!P29 -> 100 | G13: =E13/F13*100 -> 10 | H13: =G13*Master!K29 -> 0.031143676 | S13: 600g | U13: 600 | V13: =SUM(V6:V12) -> 1 | W13: =SUM(W6:W12) -> 1200 | X13: - | Y13: - | Z13: =SUM(Z6:Z12) -> 5.7518998
A14: 1kg | C14: 1000 | D14: =SUM(D6:D13) -> 1 | E14: =SUM(E6:E13) -> 1000 | F14: - | G14: - | H14: =SUM(H6:H13) -> 3.6730887 | J14: 8kg | L14: 8000 | M14: =SUM(M6:M13) -> 1 | N14: =SUM(N6:N13) -> 8000 | O14: - | P14: - | Q14: =SUM(Q6:Q13) -> 21.169366
A17: 스리라차 마요 (Sriracha Mayo) | J17: BB 파우더 (BB Powder) | S17: Soy Mayo
A18: Ingredients | D18: Weight (%) | E18: Input (g) | F18: Usage (%) | G18: Input+ Usage | H18: Price | J18: Ingredients | M18: Weight (%) | N18: Input (g) | O18: Usage (%) | P18: Input+ Usage | Q18: Price | S18: Ingredients | V18: Weight (%) | W18: Input (g) | X18: Usage (%) | Y18: Input+ Usage | Z18: Price
A20: 1 | B20: =Master!B68 -> 마요네즈 | C20: =Master!C68 -> Mayonnaise | D20: 0.058823 | E20: =D20*C25 -> 58.823 | F20: =Master!P68 -> 100 | G20: =E20/F20*100 -> 58.823 | H20: =G20*Master!K68 -> 0.1693254 | J20: 1 | K20: =Master!B42 -> 비비윙스 파우더 [A20021] | L20: =Master!C42 -> Batter Mix #8 [A20021] | M20: 0.3 | N20: =M20*L25 -> 3000 | O20: =Master!P42 -> 100 | P20: =N20/O20*100 -> 3000 | Q20: =P20*Master!K42 -> 10.275313 | S20: 1 | T20: =Master!B48 -> 소이갈릭소스 | U20: =Master!C48 -> Garlic Flavor Soy Sauce | V20: 0.5 | W20: 300 | X20: =Master!P48 -> 96 | Y20: =W20/X20*100 -> 312.5 | Z20: =Y20*Master!K48 -> 2.1755035
A21: 2 | B21: =Master!B66 -> 스리라차 소스 | C21: =Master!C66 -> Sriracha Sauce | D21: 0.941176 | E21: =D21*C25 -> 941.176 | F21: =Master!P66 -> 100 | G21: =E21/F21*100 -> 941.176 | H21: =G21*Master!K66 -> 7.2415392 | J21: 2 | K21: =Master!B41 -> 화이트 배터믹스 (White) | L21: =Master!C41 -> Battering Powder Mix | M21: 0.7 | N21: =M21*L25 -> 7000 | O21: =Master!P41 -> 85 | P21: =N21/O21*100 -> 8235.2941 | Q21: =P21*Master!K41 -> 33.518737 | S21: 2 | T21: =Master!B68 -> 마요네즈 | U21: =Master!C68 -> Mayonnaise | V21: 0.5 | W21: 900 | X21: =Master!P68 -> 100 | Y21: =W21/X21*100 -> 900 | Z21: =Y21*Master!K68 -> 2.5907019
A25: 1kg | C25: 1000 | D25: =SUM(D20:D24) -> 0.999999 | E25: =SUM(E20:E24) -> 999.999 | F25: - | G25: - | H25: =SUM(H20:H24) -> 7.4108646 | J25: 10kg | L25: 10000 | M25: =SUM(M20:M24) -> 1 | N25: =SUM(N20:N24) -> 10000 | O25: - | P25: - | Q25: =SUM(Q20:Q24) -> 43.794051
S27: 600g | U27: 600 | V27: =SUM(V20:V26) -> 1 | W27: =SUM(W20:W26) -> 1200 | X27: - | Y27: - | Z27: =SUM(Z20:Z26) -> 4.7662054
A28: 2. Sides
A30: 콜슬로우 (Coleslaw) | J30: 콘샐러드 (Corn Salad) | S30: Mala Mayo
A31: Ingredients | D31: Weight (%) | E31: Input (g) | F31: Usage (%) | G31: Input+ Usage | H31: Price | J31: Ingredients | M31: Weight (%) | N31: Input (g) | O31: Usage (%) | P31: Input+ Usage | Q31: Price | S31: Ingredients | V31: Weight (%) | W31: Input (g) | X31: Usage (%) | Y31: Input+ Usage | Z31: Price
A33: 1 | B33: =Master!B107 -> 양배추 | C33: =Master!C107 -> Cabbage | D33: 0.63 | E33: =D33*C46 -> 3150 | F33: =Master!P107 -> 79 | G33: =E33/F33*100 -> 3987.3418 | H33: =G33*Master!K107 -> 3.3322812 | J33: 1 | K33: =Master!B109 -> 옥수수(스위트콘) | L33: =Master!C109 -> Sweet Corn | M33: 0.675 | N33: =M33*L46 -> 3375 | O33: =Master!P109 -> 50 | P33: =N33/O33*100 -> 6750 | Q33: =P33*Master!K109 -> 25.384842 | S33: 1 | T33: =Master!B54 -> 마라핫 소스 | U33: =Master!C54 -> Mala Hot Sauce | V33: 0.5 | W33: 300 | X33: =Master!P54 -> 96 | Y33: =W33/X33*100 -> 312.5 | Z33: =Y33*Master!K54 -> 3.1611979
A34: 2 | B34: =Master!B108 -> 당근 | C34: =Master!C108 -> Carrot | D34: 0.037 | E34: =D34*C46 -> 185 | F34: =Master!P108 -> 81.3 | G34: =E34/F34*100 -> 227.55228 | H34: =G34*Master!K108 -> 0.20918572 | J34: 2 | K34: =Master!B68 -> 마요네즈 | L34: =Master!C68 -> Mayonnaise | M34: 0.14 | N34: =M34*L46 -> 700 | O34: =Master!P68 -> 100 | P34: =N34/O34*100 -> 700 | Q34: =P34*Master!K68 -> 2.0149904 | S34: 2 | T34: =Master!B68 -> 마요네즈 | U34: =Master!C68 -> Mayonnaise | V34: 0.5 | W34: 900 | X34: =Master!P68 -> 100 | Y34: =W34/X34*100 -> 900 | Z34: =Y34*Master!K68 -> 2.5907019
A35: 3 | B35: =Master!B104 -> 양파 | C35: =Master!C104 -> Onion | D35: 0.027 | E35: =D35*C46 -> 135 | F35: =Master!P104 -> 89 | G35: =E35/F35*100 -> 151.68539 | H35: =G35*Master!K104 -> 0.2028252 | J35: 3 | K35: =Master!B74 -> 설탕 | L35: =Master!C74 -> White Sugar | M35: 0.03 | N35: =M35*L46 -> 150 | O35: =Master!P74 -> 100 | P35: =N35/O35*100 -> 150 | Q35: =P35*Master!K74 -> 0.15669655
A36: 4 | B36: =Master!B68 -> 마요네즈 | C36: =Master!C68 -> Mayonnaise | D36: 0.12 | E36: =D36*C46 -> 600 | F36: =Master!P68 -> 100 | G36: =E36/F36*100 -> 600 | H36: =G36*Master!K68 -> 1.7271346 | J36: 4 | K36: =Master!B75 -> 소금 | L36: =Master!C75 -> Salt | M36: 0.002 | N36: =M36*L46 -> 10 | O36: =Master!P75 -> 100 | P36: =N36/O36*100 -> 10 | Q36: =P36*Master!K75 -> 0.004412575
A37: 5 | B37: =Master!B67 -> 물엿 | C37: =Master!C67 -> Corn Syrup | D37: 0.07 | E37: =D37*C46 -> 350 | F37: =Master!P67 -> 100 | G37: =E37/F37*100 -> 350 | H37: =G37*Master!K67 -> 2.0840642 | J37: 5 | K37: =Master!B108 -> 당근 | L37: =Master!C108 -> Carrot | M37: 0.028 | N37: =M37*L46 -> 140 | O37: =Master!P108 -> 81.3 | P37: =N37/O37*100 -> 172.20172 | Q37: =P37*Master!K108 -> 0.15830271
A38: 6 | B38: =Master!B74 -> 설탕 | C38: =Master!C74 -> White Sugar | D38: 0.068 | E38: =D38*C46 -> 340 | F38: =Master!P74 -> 100 | G38: =E38/F38*100 -> 340 | H38: =G38*Master!K74 -> 0.35517886 | J38: 6 | K38: =Master!B104 -> 양파 | L38: =Master!C104 -> Onion | M38: 0.019 | N38: =M38*L46 -> 95 | O38: =Master!P104 -> 89 | P38: =N38/O38*100 -> 106.74157 | Q38: =P38*Master!K104 -> 0.14272885
A39: 7 | B39: =Master!B69 -> 식초 | C39: =Master!C69 -> Vinegar Distilled | D39: 0.022 | E39: =D39*C46 -> 110 | F39: =Master!P69 -> 100 | G39: =E39/F39*100 -> 110 | H39: =G39*Master!K69 -> 0.11566221 | J39: 7 | K39: =Master!B110 -> 홍피망 | L39: =Master!C110 -> Red Bell Pepper | M39: 0.021 | N39: =M39*L46 -> 105 | O39: =Master!P110 -> 65 | P39: =N39/O39*100 -> 161.53846 | Q39: =P39*Master!K110 -> 1.1396212
A40: 8 | B40: =Master!B73 -> 레몬주스 | C40: =Master!C73 -> Lemon Juice | D40: 0.02 | E40: =D40*C46 -> 100 | F40: =Master!P73 -> 100 | G40: =E40/F40*100 -> 100 | H40: =G40*Master!K73 -> 0.30042132 | J40: 8 | K40: =Master!B111 -> 청피망 | L40: =Master!C111 -> Green Bell Pepper | M40: 0.021 | N40: =M40*L46 -> 105 | O40: =Master!P111 -> 65 | P40: =N40/O40*100 -> 161.53846 | Q40: =P40*Master!K111 -> 0.54000044 | S40: 600g | U40: 600 | V40: =SUM(V33:V39) -> 1 | W40: =SUM(W33:W39) -> 1200 | X40: - | Y40: - | Z40: =SUM(Z33:Z39) -> 5.7518998
A41: 9 | B41: =Master!B75 -> 소금 | C41: =Master!C75 -> Salt | D41: 0.006 | E41: =D41*C46 -> 30 | F41: =Master!P75 -> 100 | G41: =E41/F41*100 -> 30 | H41: =G41*Master!K75 -> 0.013237725 | J41: 9 | K41: =Master!B32 -> 올리브오일 | L41: =Master!C32 -> Oilve Oil | M41: 0.02 | N41: =M41*L46 -> 100 | O41: =Master!P32 -> 100 | P41: =N41/O41*100 -> 100 | Q41: =P41*Master!K32 -> 1.4919959
J42: 10 | K42: =Master!B67 -> 물엿 | L42: =Master!C67 -> Corn Syrup | M42: 0.015 | N42: =M42*L46 -> 75 | O42: =Master!P67 -> 100 | P42: =N42/O42*100 -> 75 | Q42: =P42*Master!K67 -> 0.44658518 | S42: Spicy Mayo
J43: 11 | K43: =Master!B69 -> 식초 | L43: =Master!C69 -> Vinegar Distilled | M43: 0.015 | N43: =M43*L46 -> 75 | O43: =Master!P69 -> 100 | P43: =N43/O43*100 -> 75 | Q43: =P43*Master!K69 -> 0.078860596 | S43: Ingredients | V43: Weight (%) | W43: Input (g) | X43: Usage (%) | Y43: Input+ Usage | Z43: Price
J44: 12 | K44: =Master!B73 -> 레몬주스 | L44: =Master!C73 -> Lemon Juice | M44: 0.004 | N44: =M44*L46 -> 20 | O44: =Master!P73 -> 100 | P44: =N44/O44*100 -> 20 | Q44: =P44*Master!K73 -> 0.060084263
J45: 13 | K45: =Master!B71 -> 미림 | L45: =Master!C71 -> Rice Wine(Cook wine) | M45: 0.01 | N45: =M45*L46 -> 50 | O45: =Master!P71 -> 100 | P45: =N45/O45*100 -> 50 | Q45: =P45*Master!K71 -> 0.58756411 | S45: 1 | T45: =Master!B50 -> 매운양념 소스 | U45: =Master!C50 -> Hot Spicy Sauce | V45: 0.5 | W45: 300 | X45: =Master!P50 -> 96 | Y45: =W45/X45*100 -> 312.5 | Z45: =Y45*Master!K50 -> 1.7418077
A46: 5kg | C46: 5000 | D46: =SUM(D33:D45) -> 1 | E46: =SUM(E33:E45) -> 5000 | F46: - | G46: - | H46: =SUM(H33:H45) -> 8.339991 | J46: 5kg | L46: 5000 | M46: =SUM(M33:M45) -> 1 | N46: =SUM(N33:N45) -> 5000 | O46: - | P46: - | Q46: =SUM(Q33:Q45) -> 32.206685 | S46: 2 | T46: =Master!B68 -> 마요네즈 | U46: =Master!C68 -> Mayonnaise | V46: 0.5 | W46: 900 | X46: =Master!P68 -> 100 | Y46: =W46/X46*100 -> 900 | Z46: =Y46*Master!K68 -> 2.5907019
A49: 치킨무 (Pickled Radish) | J49: 밥 (Steamed Rice)
A50: Ingredients | D50: Weight (%) | E50: Input (g) | F50: Usage (%) | G50: Input+ Usage | H50: Price | J50: Ingredients | M50: Weight (%) | N50: Input (g) | O50: Usage (%) | P50: Input+ Usage | Q50: Price
A52: 1 | B52: =Master!B219 -> 흰 무 | C52: =Master!C219 -> White Radish | D52: 0.5707 | E52: =D52*C59 -> 19061.38 | F52: =Master!P219 -> 90 | G52: =E52/F52*100 -> 21179.311 | H52: =G52*Master!K219 -> 21.478516 | J52: 1 | K52: =Master!B84 -> 쌀 | L52: =Master!C84 -> Grain Rice (Rice Golden) | M52: 0.5 | N52: =M52*L59 -> 1500 | O52: =Master!P84 -> 100 | P52: =N52/O52*100 -> 1500 | Q52: =P52*Master!K84 -> 1.9054301 | S52: 600g | U52: 600 | V52: =SUM(V45:V51) -> 1 | W52: =SUM(W45:W51) -> 1200 | X52: - | Y52: - | Z52: =SUM(Z45:Z51) -> 4.3325096
A53: 2 | B53: =Master!B75 -> 소금 | C53: =Master!C75 -> Salt | D53: 0.0046 | E53: =D53*C59 -> 153.64 | F53: =Master!P75 -> 100 | G53: =E53/F53*100 -> 153.64 | H53: =G53*Master!K75 -> 0.067794802 | J53: 2 | K53: 물 | L53: Filtered Water | M53: 0.5 | N53: =M53*L60 -> 0 | O53: 100 | P53: =N53/O53*100 -> 0 | Q53: -
A54: 3 | B54: =Master!B104 -> 양파 | C54: =Master!C104 -> Onion | D54: 0.0092 | E54: =D54*C59 -> 307.28 | F54: =Master!P104 -> 89 | G54: =E54/F54*100 -> 345.25843 | H54: =G54*Master!K104 -> 0.46166021 | S54: Creamy Onions Sauce ※Shelft life : 3 Days
A55: 4 | B55: =Master!B74 -> 설탕 | C55: =Master!C74 -> White Sugar | D55: 0.01 | E55: =D55*C59 -> 334 | F55: =Master!P74 -> 100 | G55: =E55/F55*100 -> 334 | H55: =G55*Master!K74 -> 0.348911 | S55: Ingredients | V55: Weight (%) | W55: Input (g) | X55: Usage (%) | Y55: Input+ Usage | Z55: Price
A56: 5 | B56: =Master!B70 -> 강초 | C56: =Master!C70 -> concentrated Vinegar(korean) | D56: 0.0411 | E56: =D56*C59 -> 1372.74 | F56: =Master!P70 -> 100 | G56: =E56/F56*100 -> 1372.74 | H56: =G56*Master!K70 -> 3.6326768
A57: 6 | B57: 물 | C57: Filtered Water | D57: 0.3644 | E57: =D57*C59 -> 12170.96 | F57: 100 | G57: =E57/F57*100 -> 12170.96 | H57: - | S57: 1 | T57: =Master!B104 -> 양파 | U57: =Master!C104 -> Onion | V57: 0.1562 | W57: =V57*U64 -> 999.68 | X57: =Master!P104 -> 89 | Y57: =W57/X57*100 -> 1123.236 | Z57: =Y57*Master!K104 -> 1.5019281
S58: 2 | T58: =Master!B68 -> 마요네즈 | U58: =Master!C68 -> Mayonnaise | V58: 0.3125 | W58: =V58*U64 -> 2000 | X58: =Master!P68 -> 100 | Y58: =W58/X58*100 -> 2000 | Z58: =Y58*Master!K68 -> 5.7571153
A59: 33.4kg | C59: 33400 | D59: =SUM(D52:D58) -> 1 | E59: =SUM(E52:E58) -> 33400 | F59: - | G59: - | H59: =SUM(H52:H58) -> 25.989559 | J59: 3kg | L59: 3000 | M59: =SUM(M52:M58) -> 1 | N59: =SUM(N52:N58) -> 1500 | O59: - | P59: - | Q59: =SUM(Q52:Q58) -> 1.9054301 | S59: 3 | T59: =Master!B216 -> 플레인 요거트 | U59: =Master!C216 -> Plain Yogurt | V59: 0.3125 | W59: =V59*U64 -> 2000 | X59: =Master!P216 -> 100 | Y59: =W59/X59*100 -> 2000 | Z59: =Y59*Master!K216 -> 6.9682651
S60: 4 | T60: =Master!B74 -> 설탕 | U60: =Master!C74 -> White Sugar | V60: 0.1562 | W60: =V60*U64 -> 999.68 | X60: =Master!P74 -> 100 | Y60: =W60/X60*100 -> 999.68 | Z60: =Y60*Master!K74 -> 1.0443094
A61: 오뎅육수 (O-deng Soup Base) | J61: 볶음밥 (Fried Rice) | S61: 5 | T61: =Master!B69 -> 식초 | U61: =Master!C69 -> Vinegar Distilled | V61: 0.0469 | W61: =V61*U64 -> 300.16 | X61: =Master!P69 -> 100 | Y61: =W61/X61*100 -> 300.16 | Z61: =Y61*Master!K69 -> 0.31561062
A62: Ingredients | D62: Weight (%) | E62: Input (g) | F62: Usage (%) | G62: Input+ Usage | H62: Price | J62: Ingredients | M62: Weight (%) | N62: Input (g) | O62: Usage (%) | P62: Input+ Usage | Q62: Price | S62: 6 | T62: =Master!B189 -> 머스타드 | U62: =Master!C189 -> Mustard | V62: 0.0156 | W62: =V62*U64 -> 99.84 | X62: =Master!P189 -> 100 | Y62: =W62/X62*100 -> 99.84 | Z62: =Y62*Master!K189 -> 0.66750225
A64: 1 | B64: =Master!B8 -> 순살 엉치살 | C64: =Master!C8 -> Boneless Thigh | D64: =E64/E72 -> 0.65667966 | E64: 320 | F64: =Master!P8 -> 80 | G64: =E64/F64*100 -> 400 | H64: =G64*Master!K8 -> 1.6714114 | J64: 1 | K64: =Master!B145 -> 밥 | L64: =Master!C145 -> Steamed Rice | M64: =N64/N72 -> 0.72098053 | N64: 3000 | O64: =Master!P145 -> 100 | P64: =N64/O64*100 -> 3000 | Q64: =P64*Master!K145 -> 1.9054301 | S64: 6400g | U64: 6400 | V64: =SUM(V57:V63) -> 0.9999 | W64: =SUM(W57:W63) -> 6399.36 | X64: - | Y64: - | Z64: =SUM(Z57:Z63) -> 16.254731
A65: 2 | B65: =Master!B38 -> 치킨 염지제 | C65: =Master!C38 -> Pickle Solution Powder Mix [G28484] | D65: =E65/E72 -> 0.0071824338 | E65: 3.5 | F65: =Master!P38 -> 98 | G65: =E65/F65*100 -> 3.5714286 | H65: =G65*Master!K38 -> 0.013271977 | J65: 2 | K65: =Master!B134 -> 야채믹스 | L65: =Master!C134 -> Vegetable Mix | M65: =N65/N72 -> 0.18024513 | N65: 750 | O65: =Master!P134 -> 100 | P65: =N65/O65*100 -> 750 | Q65: =P65*Master!K134 -> 2.9707314
A66: 3 | B66: =Master!B36 -> #2 마리네이드 파우더 | C66: =Master!C36 -> Marinade Powder Mix | D66: =E66/E72 -> 0.007798071 | E66: 3.8 | F66: =Master!P35 -> 98 | G66: =E66/F66*100 -> 3.877551 | H66: =G66*Master!K36 -> 0.030597333 | J66: 3 | K66: =Master!B48 -> 소이갈릭소스 | L66: =Master!C48 -> Garlic Flavor Soy Sauce | M66: =N66/N72 -> 0.08074982 | N66: 336 | O66: =Master!P48 -> 96 | P66: =N66/O66*100 -> 350 | Q66: =P66*Master!K48 -> 2.4365639 | S66: Creamy Jalapeno Sauce ※Shelft life : 3 Days
A67: 4 | B67: =Master!B41 -> 화이트 배터믹스 (White) | C67: =Master!C41 -> Battering Powder Mix | D67: =E67/E72 -> 0.16416992 | E67: 80 | F67: =Master!P41 -> 85 | G67: =E67/F67*100 -> 94.117647 | H67: =G67*Master!K41 -> 0.38307129 | J67: 4 | K67: =Master!B29 -> 카놀라유 | L67: =Master!C29 -> Canola Oil | M67: =N67/N72 -> 0.018024513 | N67: 75 | O67: =Master!P29 -> 100 | P67: =N67/O67*100 -> 75 | Q67: =P67*Master!K29 -> 0.23357757 | S67: Ingredients | V67: Weight (%) | W67: Input (g) | X67: Usage (%) | Y67: Input+ Usage | Z67: Price
A68: 5 | B68: =Master!B29 -> 카놀라유 | C68: =Master!C29 -> Canola Oil | D68: =E68/E72 -> 0.16416992 | E68: 80 | F68: =Master!P29 -> 100 | G68: =E68/F68*100 -> 80 | H68: =G68*Master!K29 -> 0.24914941 | J68: 5
J69: 6 | S69: 1 | T69: =Master!B52 -> 갈비 소스 | U69: =Master!C52 -> Galbi Flavor Sauce | V69: 0.4975 | W69: =V69*U76 -> 999.975 | X69: =Master!P52 -> 96 | Y69: =W69/X69*100 -> 1041.6406 | Z69: =Y69*Master!K52 -> 6.9898178
J70: 7 | S70: 2 | T70: =Master!B68 -> 마요네즈 | U70: =Master!C68 -> Mayonnaise | V70: 0.4975 | W70: =V70*U76 -> 999.975 | X70: =Master!P68 -> 100 | Y70: =W70/X70*100 -> 999.975 | Z70: =Y70*Master!K68 -> 2.8784857
S71: 3 | T71: =Master!B217 -> 스모크 리퀴드 | U71: =Master!C217 -> Somke Liquid | V71: 0.005 | W71: =V71*U76 -> 10.05 | X71: =Master!P217 -> 100 | Y71: =W71/X71*100 -> 10.05 | Z71: =Y71*Master!K217 -> 0.041866715
A72: 8ea | C72: 8 | D72: =SUM(D64:D71) -> 1 | E72: =SUM(E64:E71) -> 487.3 | F72: - | G72: - | H72: =SUM(H64:H71) -> 2.3475014 | J72: 4kg | L72: 4000 | M72: =SUM(M64:M71) -> 1 | N72: =SUM(N64:N71) -> 4161 | O72: - | P72: - | Q72: =SUM(Q64:Q71) -> 7.546303
S76: 2010g | U76: 2010 | V76: =SUM(V69:V75) -> 1 | W76: =SUM(W69:W75) -> 2010 | X76: - | Y76: - | Z76: =SUM(Z69:Z75) -> 9.9101702
A77: 알프레도 소스 (Alfredo Sauce) | J77: 토마토 소스 (Tomato Sauce)
A78: Ingredients | D78: Weight (%) | E78: Input (g) | F78: Usage (%) | G78: Input+ Usage | H78: Price | J78: Ingredients | M78: Weight (%) | N78: Input (g) | O78: Usage (%) | P78: Input+ Usage | Q78: Price | S78: bb.q Salad Dressing Sauce
S79: Ingredients | V79: Weight (%) | W79: Input (g) | X79: Usage (%) | Y79: Input+ Usage | Z79: Price
A80: 1 | B80: =Master!B104 -> 양파 | C80: =Master!C104 -> Onion | D80: =E80/E90 -> 0.27100271 | E80: 200 | F80: =Master!P104 -> 89 | G80: =E80/F80*100 -> 224.7191 | H80: =G80*Master!K104 -> 0.30048178 | J80: 1 | K80: =Master!#REF! -> #REF! | L80: =Master!#REF! -> #REF! | M80: =N80/N87 -> 0.74547391 | N80: 700 | O80: =Master!#REF! -> #REF! | P80: =N80/O80*100 -> #REF! | Q80: =P80*Master!#REF! -> #REF!
A81: 2 | B81: =Master!B103 -> 마늘 | C81: =Master!C103 -> Garlic(Peeled) | D81: =E81/E90 -> 0.054200542 | E81: 40 | F81: =Master!P103 -> 98 | G81: =E81/F81*100 -> 40.816327 | H81: =G81*Master!K103 -> 0.28063898 | J81: 2 | K81: =Master!#REF! -> #REF! | L81: =Master!#REF! -> #REF! | M81: =N81/N87 -> 0.0031948882 | N81: 3 | O81: =Master!#REF! -> #REF! | P81: =N81/O81*100 -> #REF! | Q81: =P81*Master!#REF! -> #REF! | S81: 1 | T81: =Master!B48 -> 소이갈릭소스 | U81: =Master!C48 -> Garlic Flavor Soy Sauce | V81: 0.1923 | W81: =V81*U88 -> 99.996 | X81: =Master!P48 -> 96 | Y81: =W81/X81*100 -> 104.1625 | Z81: =Y81*Master!K48 -> 0.72513883
A82: 3 | B82: =Master!B127 -> 헤비크림 | C82: =Master!C127 -> Heavy Cream | D82: =E82/E90 -> 0.61517615 | E82: 454 | F82: =Master!P131 -> 100 | G82: =E82/F82*100 -> 454 | H82: =G82*Master!K127 -> 2.2565676 | J82: 3 | K82: 페퍼론치노 | L82: =Master!C75 -> Salt | M82: =N82/N87 -> 0.0021299255 | N82: 2 | O82: =Master!#REF! -> #REF! | P82: =N82/O82*100 -> #REF! | Q82: =P82*Master!#REF! -> #REF! | S82: 2 | T82: =Master!B51 -> 허니갈릭 소스 | U82: =Master!C51 -> Sweet Soy Sauce | V82: 0.1923 | W82: =V82*U88 -> 99.996 | X82: =Master!P51 -> 96 | Y82: =W82/X82*100 -> 104.1625 | Z82: =Y82*Master!K51 -> 0.89110326
A83: 4 | B83: =Master!#REF! -> #REF! | C83: =Master!#REF! -> #REF! | D83: =E83/E90 -> 0.0081300813 | E83: 6 | F83: =Master!P127 -> 100 | G83: =E83/F83*100 -> 6 | H83: =G83*Master!#REF! -> #REF! | J83: 4 | K83: 마늘 | L83: =Master!C103 -> Garlic(Peeled) | M83: =N83/N87 -> 0.021299255 | N83: 20 | O83: =Master!#REF! -> #REF! | P83: =N83/O83*100 -> #REF! | Q83: =P83*Master!K103 -> #REF! | S83: 3 | T83: =Master!B73 -> 레몬주스 | U83: =Master!C73 -> Lemon Juice | V83: 0.0769 | W83: =V83*U88 -> 39.988 | X83: =Master!P73 -> 100 | Y83: =W83/X83*100 -> 39.988 | Z83: =Y83*Master!K73 -> 0.12013248
A84: 5 | B84: =Master!#REF! -> #REF! | C84: =Master!#REF! -> #REF! | D84: =E84/E90 -> 0.0054200542 | E84: 4 | F84: =Master!#REF! -> #REF! | G84: =E84/F84*100 -> #REF! | H84: =G83*Master!#REF! -> #REF! | J84: 5 | K84: 양파 | L84: =Master!C104 -> Onion | M84: =N84/N87 -> 0.21299255 | N84: 200 | O84: =Master!P104 -> 89 | P84: =N84/O84*100 -> 224.7191 | Q84: =P84*Master!#REF! -> #REF! | S84: 4 | T84: =Master!B69 -> 식초 | U84: =Master!C69 -> Vinegar Distilled | V84: 0.1538 | W84: =V84*U88 -> 79.976 | X84: =Master!P69 -> 100 | Y84: =W84/X84*100 -> 79.976 | Z84: =Y84*Master!K69 -> 0.084092733
A85: 6 | B85: =Master!#REF! -> #REF! | C85: =Master!#REF! -> #REF! | D85: =E85/E90 -> 0.0067750678 | E85: 5 | F85: =Master!#REF! -> #REF! | G85: =E85/F85*100 -> #REF! | H85: =G85*Master!#REF! -> #REF! | J85: 6 | K85: 버터 | L85: =Master!#REF! -> #REF! | M85: =N85/N87 -> 0.010649627 | N85: 10 | O85: =Master!#REF! -> #REF! | P85: =N85/O85*100 -> #REF! | Q85: =P85*Master!#REF! -> #REF! | S85: 5 | T85: =Master!B78 -> 참기름 | U85: =Master!C78 -> Sesame Oil | V85: 0.0962 | W85: =V85*U88 -> 50.024 | X85: =Master!P78 -> 100 | Y85: =W85/X85*100 -> 50.024 | Z85: =Y85*Master!K78 -> 1.5660574
A86: 7 | B86: =Master!#REF! -> #REF! | C86: =Master!#REF! -> #REF! | D86: =E86/E90 -> 0.0027100271 | E86: 2 | F86: =Master!#REF! -> #REF! | G86: =E86/F86*100 -> #REF! | H86: =G86*Master!#REF! -> #REF! | J86: 7 | K86: =Master!#REF! -> #REF! | L86: =Master!#REF! -> #REF! | M86: =N86/N87 -> 0.0042598509 | N86: 4 | O86: =Master!#REF! -> #REF! | P86: =N86/O86*100 -> #REF! | Q86: =P86*Master!#REF! -> #REF! | S86: 6 | T86: =Master!B29 -> 카놀라유 | U86: =Master!C29 -> Canola Oil | V86: 0.2885 | W86: =V86*U88 -> 150.02 | X86: =Master!P29 -> 100 | Y86: =W86/X86*100 -> 150.02 | Z86: =Y86*Master!K29 -> 0.46721743
A87: 8 | B87: =Master!#REF! -> #REF! | C87: =Master!#REF! -> #REF! | D87: =E87/E90 -> 0.0040650407 | E87: 3 | F87: =Master!#REF! -> #REF! | G87: =E87/F87*100 -> #REF! | H87: =G83*Master!#REF! -> #REF! | J87: 939g | L87: 939 | M87: =SUM(M80:M86) -> 1 | N87: =SUM(N80:N86) -> 939 | O87: - | P87: - | Q87: =SUM(Q80:Q86) -> #REF!
A88: 9 | B88: =Master!#REF! -> #REF! | C88: =Master!#REF! -> #REF! | D88: =E88/E90 -> 0.01897019 | E88: 14 | F88: =Master!#REF! -> #REF! | G88: =E88/F88*100 -> #REF! | H88: =G88*Master!#REF! -> #REF! | S88: 520g | U88: 520 | V88: =SUM(V81:V87) -> 1 | W88: =SUM(W81:W87) -> 520 | X88: - | Y88: - | Z88: =SUM(Z81:Z87) -> 3.8537421
A89: 10 | B89: =Master!#REF! -> #REF! | C89: =Master!#REF! -> #REF! | D89: =E89/E90 -> 0.013550136 | E89: 10 | F89: =Master!#REF! -> #REF! | G89: =E89/F89*100 -> #REF! | H89: =G89*Master!#REF! -> #REF!
A90: 738g | C90: =E90 -> 738 | D90: =SUM(D80:D89) -> 1 | E90: =SUM(E80:E89) -> 738 | F90: - | G90: - | H90: =SUM(H80:H89) -> #REF!
A92: 토마토 샐러드 | J92: 불닭소스 | T92: =Master!$C$103 -> Garlic(Peeled) | U92: =Master!$H$103 -> 997.9024 | V92: =Master!$J$103 -> 6.8612325 | W92: =Master!$K$103 -> 0.0068756549 | X92: 150 | Y92: =Master!$P$103 -> 98 | Z92: =X92/Y92*100 -> 153.06122 | AA92: =W92*Z92 -> 1.0523962 | AB92: =AA92/$J$43% -> 9.5672378
A93: Ingredients | D93: Weight (%) | E93: Input (g) | F93: Usage (%) | G93: Input+ Usage | H93: Price | J93: Ingredients | M93: Weight (%) | N93: Input (g) | O93: Usage (%) | P93: Input+ Usage | Q93: Price | T93: =Master!$C$105 -> Spring Onion | U93: =Master!$H$105 -> 180 | V93: =Master!$J$105 -> 0.64442515 | W93: =Master!$K$105 -> 0.0035801397 | X93: 12 | Y93: =Master!$P$105 -> 95 | Z93: =X93/Y93*100 -> 12.631579 | AA93: =W93*Z93 -> 0.045222818 | AB93: =AA93/$J$43% -> 0.41111653
T94: =Master!$C$104 -> Onion | U94: =Master!$H$104 -> 453.592 | V94: =Master!$J$104 -> 0.60651779 | W94: =Master!$K$104 -> 0.0013371439 | X94: 100 | Y94: =Master!$P$104 -> 89 | Z94: =X94/Y94*100 -> 112.35955 | AA94: =W94*Z94 -> 0.15024089 | AB94: =AA94/$J$43% -> 1.3658263
A95: 1 | B95: =Master!$B$121 -> 방울 토마토 | C95: =Master!$C$121 -> Cherry Tomato | D95: =E95/E110 -> 0.3444564 | E95: 320 | F95: =Master!P121 -> 91 | G95: =E95/F95*100 -> 351.64835 | H95: =G95*Master!K121 -> 1.9102056 | J95: 1 | K95: =Master!$B$103 -> 마늘 | L95: =Master!$C$103 -> Garlic(Peeled) | M95: =N95/N110 -> 0.15072464 | N95: 150.8 | O95: =Master!P103 -> 98 | P95: =N95/O95*100 -> 153.87755 | Q95: =P95*Master!K103 -> 1.0580089 | T95: =Master!$C$61 -> Fine Sea Salt(Sempio) | U95: =Master!$H$61 -> 15000 | V95: =Master!$J$61 -> 34.94 | W95: =Master!$K$61 -> 0.0023293333 | X95: 0.5 | Y95: =Master!$P$61 -> 100 | Z95: =X95/Y95*100 -> 0.5 | AA95: =W95*Z95 -> 0.0011646667 | AB95: =AA95/$J$43% -> 0.010587879
A96: 2 | B96: =Master!$B$104 -> 양파 | C96: =Master!$C$104 -> Onion | D96: =E96/E110 -> 0.38751346 | E96: 360 | F96: =Master!P104 -> 89 | G96: =E96/F96*100 -> 404.49438 | H96: =G96*Master!K104 -> 0.54086721 | J96: 2 | K96: =Master!$B$105 -> 파 | L96: =Master!$C$105 -> Spring Onion | M96: =N96/N110 -> 0.012593703 | N96: 12.6 | O96: =Master!P105 -> 95 | P96: =N96/O96*100 -> 13.263158 | Q96: =P96*Master!K105 -> 0.047483959 | T96: =Master!$C$76 -> Black Pepper (Whole) | U96: =Master!$H$76 -> 453.592 | V96: =Master!$J$76 -> 8.33 | W96: =Master!$K$76 -> 0.018364521 | X96: 0.3 | Y96: =Master!$P$76 -> 100 | Z96: =X96/Y96*100 -> 0.3 | AA96: =W96*Z96 -> 0.0055093564 | AB96: =AA96/$J$43% -> 0.050085058
A97: 3 | B97: =Master!$B$111 -> 청피망 | C97: =Master!$C$111 -> Green Bell Pepper | D97: =E97/E110 -> 0.21528525 | E97: 200 | F97: =Master!P111 -> 65 | G97: =E97/F97*100 -> 307.69231 | H97: =G97*Master!K111 -> 1.0285723 | J97: 3 | K97: =Master!B113 -> 청고추(할라피뇨) | L97: =Master!C113 -> Jalapeno | M97: =N97/N110 -> 0.012593703 | N97: 12.6 | O97: =Master!P113 -> 86.75 | P97: =N97/O97*100 -> 14.524496 | Q97: =P97*Master!K113 -> 0.018207507 | T97: =Master!$C$31 -> Sunflower Oil | U97: =Master!$H$31 -> 1320 | V97: =Master!$J$31 -> 14.971513 | W97: =Master!$K$31 -> 0.011342055 | X97: 10 | Y97: =Master!$P$31 -> 100 | Z97: =X97/Y97*100 -> 10 | AA97: =W97*Z97 -> 0.11342055 | AB97: =AA97/$J$43% -> 1.0310959
A98: 4 | B98: =Master!$B$73 -> 레몬주스 | C98: =Master!$C$73 -> Lemon Juice | D98: =E98/E110 -> 0.032292788 | E98: 30 | F98: =Master!P73 -> 100 | G98: =E98/F98*100 -> 30 | H98: =G98*Master!K73 -> 0.090126395 | J98: 4 | K98: =Master!B60 -> 고추장 | L98: =Master!C60 -> Gochujang Hot 17kg | M98: =N98/N110 -> 0.19090455 | N98: 191 | O98: =Master!P60 -> 100 | P98: =N98/O98*100 -> 191 | Q98: =P98*Master!K60 -> 0.50558824 | T98: =Master!$C$78 -> Sesame Oil | U98: =Master!$H$78 -> 1587.572 | V98: =Master!$J$78 -> 49.700721 | W98: =Master!$K$78 -> 0.031306121 | X98: 2 | Y98: =Master!$P$78 -> 100 | Z98: =X98/Y98*100 -> 2 | AA98: =W98*Z98 -> 0.062612242 | AB98: =AA98/$J$43% -> 0.5692022
A99: 5 | B99: =Master!$B$75 -> 소금 | C99: =Master!$C$75 -> Salt | D99: =E99/E110 -> 0.016146394 | E99: 15 | F99: =Master!P75 -> 100 | G99: =E99/F99*100 -> 15 | H99: =G99*Master!K75 -> 0.0066188625 | J99: 5 | K99: =Master!B64 -> 간장 | L99: =Master!C64 -> Soy Sauce (Maeil 12/1L) Korean | M99: =N99/N110 -> 0.090454773 | N99: 90.5 | O99: =Master!P64 -> 100 | P99: =N99/O99*100 -> 90.5 | Q99: =P99*Master!K64 -> 0.29601042 | T99: Green Chili | U99: 453.5932 | V99: 2.48 | W99: =V99/U99 -> 0.0054674541 | X99: 12 | Y99: 86.75 | Z99: =X99/Y99*100 -> 13.832853 | AA99: =W99*Z99 -> 0.075630489 | AB99: =AA99/$J$43% -> 0.6875499
A100: 6 | B100: =Master!$B$77 -> 후추 | C100: =Master!$C$77 -> Black Pepper | D100: =E100/E110 -> 0.0021528525 | E100: 2 | F100: =Master!P77 -> 100 | G100: =E100/F100*100 -> 2 | H100: =G100*Master!K77 -> 0.00016679239 | J100: 6 | K100: =Master!B193 -> 케첩(작은사이즈) | L100: =Master!C193 -> Tomato Ketchup(Small Packed) | M100: =N100/N110 -> 0.045177411 | N100: 45.2 | O100: =Master!P193 -> 100 | P100: =N100/O100*100 -> 45.2 | Q100: =P100*Master!K193 -> 1.7116993 | T100: Gochujang | U100: 17000 | V100: 45 | W100: =V100/U100 -> 0.0026470588 | X100: 12 | Y100: 100 | Z100: =X100/Y100*100 -> 12 | AA100: =W100*Z100 -> 0.031764706 | AB100: =AA100/$J$43% -> 0.28877005
A101: 7 | B101: =Master!$B$95 -> 파슬리 가루 | C101: =Master!$C$95 -> Parsely Flakes | D101: =E101/E110 -> 0.0021528525 | E101: 2 | F101: =Master!P95 -> 100 | G101: =E101/F101*100 -> 2 | H101: =G101*Master!K95 -> 0.049929411 | J101: 7 | K101: =Master!B67 -> 물엿 | L101: =Master!C67 -> Corn Syrup | M101: =N101/N110 -> 0.13563218 | N101: 135.7 | O101: =Master!P67 -> 100 | P101: =N101/O101*100 -> 135.7 | Q101: =P101*Master!K67 -> 0.80802145 | T101: Ketchup
J102: 8 | K102: =Master!B74 -> 설탕 | L102: =Master!C74 -> White Sugar | M102: =N102/N110 -> 0.11554223 | N102: 115.6 | O102: =Master!P74 -> 100 | P102: =N102/O102*100 -> 115.6 | Q102: =P102*Master!K74 -> 0.12076081
J103: 9 | K103: =Master!B92 -> 굴소스 | L103: =Master!C92 -> F | M103: =N103/N110 -> 0.042678661 | N103: 42.7 | O103: =Master!P92 -> 100 | P103: =N103/O103*100 -> 42.7 | Q103: =P103*Master!K92 -> 0.2819417
J104: 10 | K104: =Master!B71 -> 미림 | L104: =Master!C71 -> Rice Wine(Cook wine) | M104: =N104/N110 -> 0.037681159 | N104: 37.7 | O104: =Master!P71 -> 100 | P104: =N104/O104*100 -> 37.7 | Q104: =P104*Master!K71 -> 0.44302334
J105: 11 | K105: =Master!B59 -> 고추가루 | L105: =Master!C59 -> Red Chili Pepper | M105: =N105/N110 -> 0.030184908 | N105: 30.2 | O105: =Master!P59 -> 100 | P105: =N105/O105*100 -> 30.2 | Q105: =P105*Master!K59 -> 0.23782254
J106: 12 | K106: =Master!B58 -> 소고기 다시다 | L106: =Master!C58 -> DASHIDA SOGOGI(CJ) | M106: =N106/N110 -> 0.020089955 | N106: 20.1 | O106: =Master!P58 -> 100 | P106: =N106/O106*100 -> 20.1 | Q106: =P106*Master!K58 -> 0.26939583
J107: 13 | K107: =Master!$B$76 -> 통후추 | L107: =Master!$C$76 -> Black Pepper (Whole) | M107: =N107/N110 -> 0.0007996002 | N107: 0.8 | O107: =Master!P76 -> 100 | P107: =N107/O107*100 -> 0.8 | Q107: =P107*Master!K76 -> 0.014691617
J108: 14 | K108: 물 | L108: Water | M108: =N108/N110 -> 0.11294353 | N108: 113 | O108: 100 | P108: =N108/O108*100 -> 113 | Q108: =P108*Master!K123 -> 0.70826843
J109: 15 | K109: =Master!$B$78 -> 참기름 | L109: =Master!$C$78 -> Sesame Oil | M109: =N109/N110 -> 0.0019990005 | N109: 2 | O109: =Master!P78 -> 100 | P109: =N109/O109*100 -> 2 | Q109: =P109*Master!K78 -> 0.062612242
A110: 929g | C110: 929 | D110: =SUM(D95:D109) -> 1 | E110: =SUM(E95:E109) -> 929 | F110: - | G110: - | H110: =SUM(H95:H109) -> 3.6264865 | J110: =N110 -> 1000.5 | L110: =N110 -> 1000.5 | M110: =SUM(M95:M109) -> 1 | N110: =SUM(N95:N109) -> 1000.5 | O110: - | P110: - | Q110: =SUM(Q95:Q104) -> 5.2907457
A111: 4.Salad Dressing
A113: 유자소스 | J113: 소이 갈릭 참깨 소스
A114: Ingredients | D114: Weight (%) | E114: Input (g) | F114: Usage (%) | G114: Input+ Usage | H114: Price | J114: Ingredients | M114: Weight (%) | N114: Input (g) | O114: Usage (%) | P114: Input+ Usage | Q114: Price
A116: 1 | B116: =Master!B185 -> 유자티 | C116: =Master!$C$103 -> Garlic(Peeled) | D116: =E52/E123 -> 0.26736266 | E116: 120 | F116: =Master!P185 -> 100 | G116: =E52/F52*100 -> 21179.311 | H116: =G52*Master!K185 -> 302.28653 | J116: 1 | K116: =Master!B48 -> 소이갈릭소스 | L116: =Master!C48 -> Garlic Flavor Soy Sauce | M116: =N52/N123 -> 0.097853741 | N116: 75 | O116: =Master!P48 -> 96 | P116: =N52/O52*100 -> 1500 | Q116: =P52*Master!K48 -> 10.442417
A117: 2 | B117: =Master!B186 -> 화이트 와인 비네거 | C117: =Master!$C$105 -> Spring Onion | D117: =E117/E123 -> 0.00049092421 | E117: 35 | F117: =Master!P186 -> 100 | G117: =E117/F117*100 -> 35 | H117: =G117*Master!K186 -> 0.27993 | J117: 2 | K117: =Master!$B$78 -> 참기름 | L117: =Master!$C$78 -> Sesame Oil | M117: =N117/N123 -> 0.00097853741 | N117: 15 | O117: =Master!P78 -> 100 | P117: =N117/O117*100 -> 15 | Q117: =P117*Master!K78 -> 0.46959182
A118: 3 | B118: =Master!B75 -> 소금 | C118: =Master!C75 -> Salt | D118: =E118/E123 -> 7.0132031e-06 | E118: 0.5 | F118: =Master!P75 -> 100 | G118: =E118/F118*100 -> 0.5 | H118: =G118*Master!K75 -> 0.00022062875 | J118: 3 | K118: =Master!B79 -> 참깨 | L118: =Master!C79 -> Sesame Seeds | M118: =N118/N123 -> 0.00019570748 | N118: 3 | O118: =Master!P79 -> 100 | P118: =N118/O118*100 -> 3 | Q118: =P118*Master!K79 -> 0.032592883
A119: 4 | B119: =Master!B30 -> 팜유 | C119: =Master!C30 -> Palm Oil | D119: =E119/E123 -> 0.00042079218 | E119: 30 | F119: =Master!P30 -> 100 | G119: =E119/F119*100 -> 30 | H119: =G119*Master!K30 -> 0 | J119: 4 | K119: =Master!B186 -> 화이트 와인 비네거 | L119: =Master!C93 -> Baked Bean | M119: =N119/N123 -> 0.0013047166 | N119: 20 | O119: =Master!P93 -> 100 | P119: =N119/O119*100 -> 20 | Q119: =P119*Master!K186 -> 0.15996
J120: 5 | K120: =Master!B30 -> 팜유 | L120: =Master!$C$30 -> Palm Oil | M120: =N120/N123 -> 0.00097853741 | N120: 15 | O120: =Master!P30 -> 100 | P120: =N120/O120*100 -> 15 | Q120: =P120*Master!K30 -> 0
A123: =C123 -> 71294.1 | C123: =E123 -> 71294.1 | D123: =SUM(D52:D122) -> 8.2682814 | E123: =SUM(E52:E122) -> 71294.1 | F123: - | G123: - | H123: =SUM(H52:H122) -> #REF! | J123: =L123 -> 15329 | L123: =N123 -> 15329 | M123: =SUM(M52:M122) -> 8.1013112 | N123: =SUM(N52:N122) -> 15329 | O123: - | P123: - | Q123: =SUM(Q52:Q122) -> #REF!
...

Sheet BI_Golden Fried(2)
A1: RECIPE COST CALCULATOR
B3: ITEM NAME | D3: Golden Fried_Bone In_2pcs
B5: EST. SALE PRICE | D5: 11
B6: TOTAL COST(Dine In) | D6: =$J$25 -> 1.8295714
B7: TOTAL COST(Take Out) | D7: =$J$40 -> 2.6227585
B9: Food Cost | D9: =IF(D7="","",IF(ISBLANK(D5),"",D7/D5)) -> 0.23843259
B11: NET PROFIT | D11: =D5-D7 -> 8.3772415
B13: PRIMARY INGREDIENTS
B14: Product Name | D14: Weight (g) | E14: Price | F14: Price/g | G14: Input/g | H14: Usage(%) | I14: Input+ Usage | J14: Price | K14: Price(%)/ Portion
B16: =Master!$B$6 -> 홀치킨 | C16: =Master!$C$6 -> Whole Chicken | D16: =Master!$H$6 -> 1000 | E16: =Master!$J$6 -> 2.8415359 | F16: =Master!$K$6 -> 0.0028415359 | G16: 260 | H16: =Master!$P$6 -> 98 | I16: =G16/H16*100 -> 265.30612 | J16: =F16*I16 -> 0.75387686 | K16: =J16/$J$25% -> 41.205108
B17: =Master!$B$36 -> #2 마리네이드 파우더 | C17: =Master!$C$36 -> Marinade Powder Mix | D17: =Master!$H$36 -> 20000 | E17: =Master!$J$36 -> 157.81782 | F17: =Master!$K$36 -> 0.0078908912 | G17: =G16*0.013 -> 3.38 | H17: =Master!$P$36 -> 98 | I17: =G17/H17*100 -> 3.4489796 | J17: =F17*I17 -> 0.027215523 | K17: =J17/$J$25% -> 1.4875355
B18: =Master!$B$41 -> 화이트 배터믹스 (White) | C18: =Master!$C$41 -> Battering Powder Mix | D18: =Master!$H$41 -> 20000 | E18: =Master!$J$41 -> 81.402648 | F18: =Master!$K$41 -> 0.0040701324 | G18: =G16*25% -> 65 | H18: =Master!$P$41 -> 85 | I18: =G18/H18*100 -> 76.470588 | J18: =F18*I18 -> 0.31124542 | K18: =J18/$J$25% -> 17.011931
B19: =Master!$B$31 -> 해바라기 유 | C19: =Master!$C$31 -> Sunflower Oil | D19: =Master!$H$31 -> 1320 | E19: =Master!$J$31 -> 14.971513 | F19: =Master!$K$31 -> 0.011342055 | G19: =G16*25% -> 65 | H19: =Master!$P$31 -> 100 | I19: =G19/H19*100 -> 65 | J19: =F19*I19 -> 0.73723358 | K19: =J19/$J$25% -> 40.295426
K20: =J20/$J$25% -> 0
K21: =J21/$J$25% -> 0
K22: =J22/$J$25% -> 0
K23: =J23/$J$25% -> 0
K24: =J24/$J$25% -> 0
B25: TOTAL | G25: =SUM(G16:G24) -> 393.38 | J25: =SUM(J16:J24) -> 1.8295714 | K25: =SUM(K16:K24) -> 100
B27: SECONDARY INGREDIENTS
B28: Product Name | D28: Weight (g) | E28: Price | F28: Price/g | G28: Input/g | H28: Usage(%) | I28: Input+ Usage | J28: Price | K28: Price(%)/ Portion
B30: =Master!$B$150 -> 치킨패키지(대) | C30: =Master!$C$150 -> Chicken Package (L) | D30: =Master!$H$150 -> 400 | E30: =Master!$J$150 -> 99.025402 | F30: =Master!$K$150 -> 0.2475635 | G30: 1 | H30: =Master!$P$150 -> 100 | I30: =G30/H30*100 -> 1 | J30: =F30*I30 -> 0.2475635 | K30: =J30/$J$40% -> 9.4390506
B31: =Master!$B$157 -> 치킨트레이(소) | C31: =Master!$C$157 -> To Go Tray (S) | D31: =Master!$H$157 -> 100 | E31: =Master!$J$157 -> 8.4 | F31: =Master!$K$157 -> 0.084 | G31: 0 | H31: =Master!$P$157 -> 100 | I31: =G31/H31*100 -> 0 | J31: =F31*I31 -> 0 | K31: =J31/$J$40% -> 0
B32: =Master!$B$175 -> 종이백 (S,M) | C32: =Master!$C$175 -> Paper Bag (S,M) | D32: =Master!$H$175 -> 200 | E32: =Master!$J$175 -> 61.106668 | F32: =Master!$K$175 -> 0.30553334 | G32: 1 | H32: =Master!$P$175 -> 100 | I32: =G32/H32*100 -> 1 | J32: =F32*I32 -> 0.30553334 | K32: =J32/$J$40% -> 11.649313
B33: =Master!$B$166 -> 비비큐 냅킨 | C33: =Master!$C$166 -> BBQ New LOGO Napkin | D33: =Master!$H$166 -> 5000 | E33: =Master!$J$166 -> 21.816824 | F33: =Master!$K$166 -> 0.0043633648 | G33: 1 | H33: =Master!$P$166 -> 100 | I33: =G33/H33*100 -> 1 | J33: =F33*I33 -> 0.0043633648 | K33: =J33/$J$40% -> 0.16636548
B34: =Master!$B$164 -> 비비큐 젓가락 | C34: =Master!$C$164 -> BBQ Chopstick Logo | D34: =Master!$H$164 -> 500 | E34: =Master!$J$164 -> 117.86347 | F34: =Master!$K$164 -> 0.23572693 | G34: 1 | H34: =Master!$P$164 -> 100 | I34: =G34/H34*100 -> 1 | J34: =F34*I34 -> 0.23572693 | K34: =J34/$J$40% -> 8.9877482
B35: =Master!$B$165 -> 왁스페이퍼 | C35: =Master!$C$165 -> BBQ Wax Paper Logo / Parchment paper | D35: =Master!$H$165 -> 2500 | E35: =Master!$J$165 -> 36.570748 | F35: =Master!$K$165 -> 0.014628299 | G35: 0 | H35: =Master!$P$165 -> 100 | I35: =G35/H35*100 -> 0 | J35: =F35*I35 -> 0 | K35: =J35/$J$40% -> 0
B38: TOTAL | G38: =SUM(G30:G37) -> 4 | J38: =SUM(J30:J37) -> 0.79318714 | K38: =SUM(K30:K37) -> 30.242477
B40: TOTAL INGREDIENTS | J40: =J25+J38 -> 2.6227585 | K40: =K25+K38 -> 130.24248

Sheet BI_Golden Fried(3)
A1: RECIPE COST CALCULATOR
B3: ITEM NAME | D3: Golden Fried_Bone In_3pcs
B5: EST. SALE PRICE | D5: 15
B6: TOTAL COST(Dine In) | D6: =$J$25 -> 2.7443571
B7: TOTAL COST(Take Out) | D7: =$J$40 -> 3.5375442
B9: Food Cost | D9: =IF(D7="","",IF(ISBLANK(D5),"",D7/D5)) -> 0.23583628
B11: NET PROFIT | D11: =D5-D7 -> 11.462456
B13: PRIMARY INGREDIENTS
B14: Product Name | D14: Weight (g) | E14: Price | F14: Price/g | G14: Input/g | H14: Usage(%) | I14: Input+ Usage | J14: Price | K14: Price(%)/ Portion
B16: =Master!$B$6 -> 홀치킨 | C16: =Master!$C$6 -> Whole Chicken | D16: =Master!$H$6 -> 1000 | E16: =Master!$J$6 -> 2.8415359 | F16: =Master!$K$6 -> 0.0028415359 | G16: 390 | H16: =Master!$P$6 -> 98 | I16: =G16/H16*100 -> 397.95918 | J16: =F16*I16 -> 1.1308153 | K16: =J16/$J$25% -> 41.205108
B17: =Master!$B$36 -> #2 마리네이드 파우더 | C17: =Master!$C$36 -> Marinade Powder Mix | D17: =Master!$H$36 -> 20000 | E17: =Master!$J$36 -> 157.81782 | F17: =Master!$K$36 -> 0.0078908912 | G17: =G16*0.013 -> 5.07 | H17: =Master!$P$36 -> 98 | I17: =G17/H17*100 -> 5.1734694 | J17: =F17*I17 -> 0.040823284 | K17: =J17/$J$25% -> 1.4875355
B18: =Master!$B$41 -> 화이트 배터믹스 (White) | C18: =Master!$C$41 -> Battering Powder Mix | D18: =Master!$H$41 -> 20000 | E18: =Master!$J$41 -> 81.402648 | F18: =Master!$K$41 -> 0.0040701324 | G18: =G16*25% -> 97.5 | H18: =Master!$P$41 -> 85 | I18: =G18/H18*100 -> 114.70588 | J18: =F18*I18 -> 0.46686813 | K18: =J18/$J$25% -> 17.011931
B19: =Master!$B$31 -> 해바라기 유 | C19: =Master!$C$31 -> Sunflower Oil | D19: =Master!$H$31 -> 1320 | E19: =Master!$J$31 -> 14.971513 | F19: =Master!$K$31 -> 0.011342055 | G19: =G16*25% -> 97.5 | H19: =Master!$P$31 -> 100 | I19: =G19/H19*100 -> 97.5 | J19: =F19*I19 -> 1.1058504 | K19: =J19/$J$25% -> 40.295426
K20: =J20/$J$25% -> 0
K21: =J21/$J$25% -> 0
K22: =J22/$J$25% -> 0
K23: =J23/$J$25% -> 0
K24: =J24/$J$25% -> 0
B25: TOTAL | G25: =SUM(G16:G24) -> 590.07 | J25: =SUM(J16:J24) -> 2.7443571 | K25: =SUM(K16:K24) -> 100
B27: SECONDARY INGREDIENTS
B28: Product Name | D28: Weight (g) | E28: Price | F28: Price/g | G28: Input/g | H28: Usage(%) | I28: Input+ Usage | J28: Price | K28: Price(%)/ Portion
B30: =Master!$B$150 -> 치킨패키지(대) | C30: =Master!$C$150 -> Chicken Package (L) | D30: =Master!$H$150 -> 400 | E30: =Master!$J$150 -> 99.025402 | F30: =Master!$K$150 -> 0.2475635 | G30: 1 | H30: =Master!$P$150 -> 100 | I30: =G30/H30*100 -> 1 | J30: =F30*I30 -> 0.2475635 | K30: =J30/$J$40% -> 6.9981742
B31: =Master!$B$157 -> 치킨트레이(소) | C31: =Master!$C$157 -> To Go Tray (S) | D31: =Master!$H$157 -> 100 | E31: =Master!$J$157 -> 8.4 | F31: =Master!$K$157 -> 0.084 | G31: 0 | H31: =Master!$P$157 -> 100 | I31: =G31/H31*100 -> 0 | J31: =F31*I31 -> 0 | K31: =J31/$J$40% -> 0
B32: =Master!$B$175 -> 종이백 (S,M) | C32: =Master!$C$175 -> Paper Bag (S,M) | D32: =Master!$H$175 -> 200 | E32: =Master!$J$175 -> 61.106668 | F32: =Master!$K$175 -> 0.30553334 | G32: 1 | H32: =Master!$P$175 -> 100 | I32: =G32/H32*100 -> 1 | J32: =F32*I32 -> 0.30553334 | K32: =J32/$J$40% -> 8.6368769
B33: =Master!$B$166 -> 비비큐 냅킨 | C33: =Master!$C$166 -> BBQ New LOGO Napkin | D33: =Master!$H$166 -> 5000 | E33: =Master!$J$166 -> 21.816824 | F33: =Master!$K$166 -> 0.0043633648 | G33: 1 | H33: =Master!$P$166 -> 100 | I33: =G33/H33*100 -> 1 | J33: =F33*I33 -> 0.0043633648 | K33: =J33/$J$40% -> 0.12334446
B34: =Master!$B$164 -> 비비큐 젓가락 | C34: =Master!$C$164 -> BBQ Chopstick Logo | D34: =Master!$H$164 -> 500 | E34: =Master!$J$164 -> 117.86347 | F34: =Master!$K$164 -> 0.23572693 | G34: 1 | H34: =Master!$P$164 -> 100 | I34: =G34/H34*100 -> 1 | J34: =F34*I34 -> 0.23572693 | K34: =J34/$J$40% -> 6.6635755
B35: =Master!$B$165 -> 왁스페이퍼 | C35: =Master!$C$165 -> BBQ Wax Paper Logo / Parchment paper | D35: =Master!$H$165 -> 2500 | E35: =Master!$J$165 -> 36.570748 | F35: =Master!$K$165 -> 0.014628299 | G35: 0 | H35: =Master!$P$165 -> 100 | I35: =G35/H35*100 -> 0 | J35: =F35*I35 -> 0 | K35: =J35/$J$40% -> 0
B38: TOTAL | G38: =SUM(G30:G37) -> 4 | J38: =SUM(J30:J37) -> 0.79318714 | K38: =SUM(K30:K37) -> 22.421971
B40: TOTAL INGREDIENTS | J40: =J25+J38 -> 3.5375442 | K40: =K25+K38 -> 122.42197

Sheet BI_Golden Fried(5)
A1: RECIPE COST CALCULATOR
B3: ITEM NAME | D3: Golden Fried_Bone In_5pcs
B5: EST. SALE PRICE | D5: 21
B6: TOTAL COST(Dine In) | D6: =$J$25 -> 4.5739284
B7: TOTAL COST(Take Out) | D7: =$J$40 -> 5.3671156
B9: Food Cost | D9: =IF(D7="","",IF(ISBLANK(D5),"",D7/D5)) -> 0.25557693
B11: NET PROFIT | D11: =D5-D7 -> 15.632884
B13: PRIMARY INGREDIENTS
B14: Product Name | D14: Weight (g) | E14: Price | F14: Price/g | G14: Input/g | H14: Usage(%) | I14: Input+ Usage | J14: Price | K14: Price(%)/ Portion
B16: =Master!$B$6 -> 홀치킨 | C16: =Master!$C$6 -> Whole Chicken | D16: =Master!$H$6 -> 1000 | E16: =Master!$J$6 -> 2.8415359 | F16: =Master!$K$6 -> 0.0028415359 | G16: 650 | H16: =Master!$P$6 -> 98 | I16: =G16/H16*100 -> 663.26531 | J16: =F16*I16 -> 1.8846921 | K16: =J16/$J$25% -> 41.205108
B17: =Master!$B$36 -> #2 마리네이드 파우더 | C17: =Master!$C$36 -> Marinade Powder Mix | D17: =Master!$H$36 -> 20000 | E17: =Master!$J$36 -> 157.81782 | F17: =Master!$K$36 -> 0.0078908912 | G17: =G16*0.013 -> 8.45 | H17: =Master!$P$36 -> 98 | I17: =G17/H17*100 -> 8.622449 | J17: =F17*I17 -> 0.068038807 | K17: =J17/$J$25% -> 1.4875355
B18: =Master!$B$41 -> 화이트 배터믹스 (White) | C18: =Master!$C$41 -> Battering Powder Mix | D18: =Master!$H$41 -> 20000 | E18: =Master!$J$41 -> 81.402648 | F18: =Master!$K$41 -> 0.0040701324 | G18: =G16*25% -> 162.5 | H18: =Master!$P$41 -> 85 | I18: =G18/H18*100 -> 191.17647 | J18: =F18*I18 -> 0.77811355 | K18: =J18/$J$25% -> 17.011931
B19: =Master!$B$31 -> 해바라기 유 | C19: =Master!$C$31 -> Sunflower Oil | D19: =Master!$H$31 -> 1320 | E19: =Master!$J$31 -> 14.971513 | F19: =Master!$K$31 -> 0.011342055 | G19: =G16*25% -> 162.5 | H19: =Master!$P$31 -> 100 | I19: =G19/H19*100 -> 162.5 | J19: =F19*I19 -> 1.8430839 | K19: =J19/$J$25% -> 40.295426
K20: =J20/$J$25% -> 0
K21: =J21/$J$25% -> 0
K22: =J22/$J$25% -> 0
K23: =J23/$J$25% -> 0
K24: =J24/$J$25% -> 0
B25: TOTAL | G25: =SUM(G16:G24) -> 983.45 | J25: =SUM(J16:J24) -> 4.5739284 | K25: =SUM(K16:K24) -> 100
B27: SECONDARY INGREDIENTS
B28: Product Name | D28: Weight (g) | E28: Price | F28: Price/g | G28: Input/g | H28: Usage(%) | I28: Input+ Usage | J28: Price | K28: Price(%)/ Portion
B30: =Master!$B$150 -> 치킨패키지(대) | C30: =Master!$C$150 -> Chicken Package (L) | D30: =Master!$H$150 -> 400 | E30: =Master!$J$150 -> 99.025402 | F30: =Master!$K$150 -> 0.2475635 | G30: 1 | H30: =Master!$P$150 -> 100 | I30: =G30/H30*100 -> 1 | J30: =F30*I30 -> 0.2475635 | K30: =J30/$J$40% -> 4.6125987
B31: =Master!$B$157 -> 치킨트레이(소) | C31: =Master!$C$157 -> To Go Tray (S) | D31: =Master!$H$157 -> 100 | E31: =Master!$J$157 -> 8.4 | F31: =Master!$K$157 -> 0.084 | G31: 0 | H31: =Master!$P$157 -> 100 | I31: =G31/H31*100 -> 0 | J31: =F31*I31 -> 0 | K31: =J31/$J$40% -> 0
B32: =Master!$B$175 -> 종이백 (S,M) | C32: =Master!$C$175 -> Paper Bag (S,M) | D32: =Master!$H$175 -> 200 | E32: =Master!$J$175 -> 61.106668 | F32: =Master!$K$175 -> 0.30553334 | G32: 1 | H32: =Master!$P$175 -> 100 | I32: =G32/H32*100 -> 1 | J32: =F32*I32 -> 0.30553334 | K32: =J32/$J$40% -> 5.6926916
B33: =Master!$B$166 -> 비비큐 냅킨 | C33: =Master!$C$166 -> BBQ New LOGO Napkin | D33: =Master!$H$166 -> 5000 | E33: =Master!$J$166 -> 21.816824 | F33: =Master!$K$166 -> 0.0043633648 | G33: 1 | H33: =Master!$P$166 -> 100 | I33: =G33/H33*100 -> 1 | J33: =F33*I33 -> 0.0043633648 | K33: =J33/$J$40% -> 0.081298134
B34: =Master!$B$164 -> 비비큐 젓가락 | C34: =Master!$C$164 -> BBQ Chopstick Logo | D34: =Master!$H$164 -> 500 | E34: =Master!$J$164 -> 117.86347 | F34: =Master!$K$164 -> 0.23572693 | G34: 1 | H34: =Master!$P$164 -> 100 | I34: =G34/H34*100 -> 1 | J34: =F34*I34 -> 0.23572693 | K34: =J34/$J$40% -> 4.3920599
B35: =Master!$B$165 -> 왁스페이퍼 | C35: =Master!$C$165 -> BBQ Wax Paper Logo / Parchment paper | D35: =Master!$H$165 -> 2500 | E35: =Master!$J$165 -> 36.570748 | F35: =Master!$K$165 -> 0.014628299 | G35: 0 | H35: =Master!$P$165 -> 100 | I35: =G35/H35*100 -> 0 | J35: =F35*I35 -> 0 | K35: =J35/$J$40% -> 0
B38: TOTAL | G38: =SUM(G30:G37) -> 4 | J38: =SUM(J30:J37) -> 0.79318714 | K38: =SUM(K30:K37) -> 14.778648
B40: TOTAL INGREDIENTS | J40: =J25+J38 -> 5.3671156 | K40: =K25+K38 -> 114.77865

Sheet BI_Classic(2)
A1: RECIPE COST CALCULATOR
B3: ITEM NAME | D3: Classic_Bone In_2pcs
B5: EST. SALE PRICE | D5: 11
B6: TOTAL COST(Dine In) | D6: =J26 -> 1.6092773
B7: TOTAL COST(Take Out) | D7: =J42 -> 2.2816944
B9: Food Cost | D9: =IF(D7="","",IF(ISBLANK(D5),"",D7/D5)) -> 0.20742677
B11: NET PROFIT | D11: =D5-D7 -> 8.7183056
B13: PRIMARY INGREDIENTS
B14: Product Name | D14: Wheigh (g) | E14: Price | F14: Price/g | G14: Input/g | H14: Usage(%) | I14: Input+ Usage | J14: Price | K14: Price(%)/ Portion
B16: =Master!$B$6 -> 홀치킨 | C16: =Master!$C$6 -> Whole Chicken | D16: =Master!$H$6 -> 1000 | E16: =Master!$J$6 -> 2.8415359 | F16: =Master!$K$6 -> 0.0028415359 | G16: 260 | H16: =Master!$P$6 -> 98 | I16: =G16/H16*100 -> 265.30612 | J16: =F16*I16 -> 0.75387686 | K16: =J16/$J$26% -> 46.845677
B17: =Master!$B$43 -> 옐로우 배터믹스 [Battering Powder Mix-C] | C17: =Master!$C$43 -> Battering Powder Mix-C | D17: =Master!$H$43 -> 20000 | E17: =Master!$J$43 -> 89.079647 | F17: =Master!$K$43 -> 0.0044539824 | G17: =G16*10% -> 26 | H17: =Master!$P$43 -> 98 | I17: =G17/H17*100 -> 26.530612 | J17: =F17*I17 -> 0.11816688 | K17: =J17/$J$26% -> 7.3428537
B18: =Master!$B$31 -> 해바라기 유 | C18: =Master!$C$31 -> Sunflower Oil | D18: =Master!$H$31 -> 1320 | E18: =Master!$J$31 -> 14.971513 | F18: =Master!$K$31 -> 0.011342055 | G18: =G16*25% -> 65 | H18: =Master!$P$31 -> 100 | I18: =G18/H18*100 -> 65 | J18: =F18*I18 -> 0.73723358 | K18: =J18/$J$26% -> 45.811469
K19: =J19/$J$26% -> 0
K20: =J20/$J$26% -> 0
K21: =J21/$J$26% -> 0
K22: =J22/$J$26% -> 0
K23: =J23/$J$26% -> 0
K24: =J24/$J$26% -> 0
K25: =J25/$J$26% -> 0
B26: TOTAL | G26: =SUM(G16:G25) -> 351 | J26: =SUM(J16:J25) -> 1.6092773 | K26: =SUM(K16:K25) -> 100
B28: SECONDARY INGREDIENTS
B29: Product Name | D29: Wheigh (g) | E29: Price | F29: Price/g | G29: Input/g | H29: Usage(%) | I29: Input+ Usage | J29: Price | K29: Price(%)/ Portion
B31: =Master!$B$151 -> 치킨패키지(중) | C31: =Master!$C$151 -> Chicken Package (M) | D31: =Master!$H$151 -> 400 | E31: =Master!$J$151 -> 50.717397 | F31: =Master!$K$151 -> 0.12679349 | G31: 1 | H31: =Master!$P$151 -> 100 | I31: =G31/H31*100 -> 1 | J31: =F31*I31 -> 0.12679349 | K31: =J31/$J$42% -> 5.5569883
B32: =Master!$B$157 -> 치킨트레이(소) | C32: =Master!$C$157 -> To Go Tray (S) | D32: =Master!$H$157 -> 100 | E32: =Master!$J$157 -> 8.4 | F32: =Master!$K$157 -> 0.084 | G32: 0 | H32: =Master!$P$157 -> 100 | I32: =G32/H32*100 -> 0 | J32: =F32*I32 -> 0 | K32: =J32/$J$42% -> 0
B33: =Master!$B$175 -> 종이백 (S,M) | C33: =Master!$C$175 -> Paper Bag (S,M) | D33: =Master!$H$175 -> 200 | E33: =Master!$J$175 -> 61.106668 | F33: =Master!$K$175 -> 0.30553334 | G33: 1 | H33: =Master!$P$175 -> 100 | I33: =G33/H33*100 -> 1 | J33: =F33*I33 -> 0.30553334 | K33: =J33/$J$42% -> 13.390633
B34: =Master!$B$166 -> 비비큐 냅킨 | C34: =Master!$C$166 -> BBQ New LOGO Napkin | D34: =Master!$H$166 -> 5000 | E34: =Master!$J$166 -> 21.816824 | F34: =Master!$K$166 -> 0.0043633648 | G34: 1 | H34: =Master!$P$166 -> 100 | I34: =G34/H34*100 -> 1 | J34: =F34*I34 -> 0.0043633648 | K34: =J34/$J$42% -> 0.19123353
B35: =Master!$B$165 -> 왁스페이퍼 | C35: =Master!$C$165 -> BBQ Wax Paper Logo / Parchment paper | D35: =Master!$H$165 -> 2500 | E35: =Master!$J$165 -> 36.570748 | F35: =Master!$K$165 -> 0.014628299 | G35: 0 | H35: =Master!$P$165 -> 100 | I35: =G35/H35*100 -> 0 | J35: =F35*I35 -> 0 | K35: =J35/$J$42% -> 0
B36: =Master!$B$164 -> 비비큐 젓가락 | C36: =Master!$C$164 -> BBQ Chopstick Logo | D36: =Master!$H$164 -> 500 | E36: =Master!$J$164 -> 117.86347 | F36: =Master!$K$164 -> 0.23572693 | G36: 1 | H36: =Master!$P$164 -> 100 | I36: =G36/H36*100 -> 1 | J36: =F36*I36 -> 0.23572693 | K36: =J36/$J$42% -> 10.331223
B40: TOTAL | G40: =SUM(G31:G39) -> 4 | J40: =SUM(J31:J39) -> 0.67241713 | K40: =SUM(K31:K39) -> 29.470078
B42: TOTAL INGREDIENTS | J42: =J26+J40 -> 2.2816944 | K42: =K26+K40 -> 129.47008

Sheet BI_Classic(3)
A1: RECIPE COST CALCULATOR
B3: ITEM NAME | D3: Classic_Bone In_3pcs
B5: EST. SALE PRICE | D5: 15
B6: TOTAL COST(Dine In) | D6: =J26 -> 2.413916
B7: TOTAL COST(Take Out) | D7: =J42 -> 3.0863331
B9: Food Cost | D9: =IF(D7="","",IF(ISBLANK(D5),"",D7/D5)) -> 0.20575554
B11: NET PROFIT | D11: =D5-D7 -> 11.913667
B13: PRIMARY INGREDIENTS
B14: Product Name | D14: Wheigh (g) | E14: Price | F14: Price/g | G14: Input/g | H14: Usage(%) | I14: Input+ Usage | J14: Price | K14: Price(%)/ Portion
B16: =Master!$B$6 -> 홀치킨 | C16: =Master!$C$6 -> Whole Chicken | D16: =Master!$H$6 -> 1000 | E16: =Master!$J$6 -> 2.8415359 | F16: =Master!$K$6 -> 0.0028415359 | G16: 390 | H16: =Master!$P$6 -> 98 | I16: =G16/H16*100 -> 397.95918 | J16: =F16*I16 -> 1.1308153 | K16: =J16/$J$26% -> 46.845677
B17: =Master!$B$43 -> 옐로우 배터믹스 [Battering Powder Mix-C] | C17: =Master!$C$43 -> Battering Powder Mix-C | D17: =Master!$H$43 -> 20000 | E17: =Master!$J$43 -> 89.079647 | F17: =Master!$K$43 -> 0.0044539824 | G17: =G16*10% -> 39 | H17: =Master!$P$43 -> 98 | I17: =G17/H17*100 -> 39.795918 | J17: =F17*I17 -> 0.17725032 | K17: =J17/$J$26% -> 7.3428537
B18: =Master!$B$31 -> 해바라기 유 | C18: =Master!$C$31 -> Sunflower Oil | D18: =Master!$H$31 -> 1320 | E18: =Master!$J$31 -> 14.971513 | F18: =Master!$K$31 -> 0.011342055 | G18: =G16*25% -> 97.5 | H18: =Master!$P$31 -> 100 | I18: =G18/H18*100 -> 97.5 | J18: =F18*I18 -> 1.1058504 | K18: =J18/$J$26% -> 45.811469
K19: =J19/$J$26% -> 0
K20: =J20/$J$26% -> 0
K21: =J21/$J$26% -> 0
K22: =J22/$J$26% -> 0
K23: =J23/$J$26% -> 0
K24: =J24/$J$26% -> 0
K25: =J25/$J$26% -> 0
B26: TOTAL | G26: =SUM(G16:G25) -> 526.5 | J26: =SUM(J16:J25) -> 2.413916 | K26: =SUM(K16:K25) -> 100
B28: SECONDARY INGREDIENTS
B29: Product Name | D29: Wheigh (g) | E29: Price | F29: Price/g | G29: Input/g | H29: Usage(%) | I29: Input+ Usage | J29: Price | K29: Price(%)/ Portion
B31: =Master!$B$151 -> 치킨패키지(중) | C31: =Master!$C$151 -> Chicken Package (M) | D31: =Master!$H$151 -> 400 | E31: =Master!$J$151 -> 50.717397 | F31: =Master!$K$151 -> 0.12679349 | G31: 1 | H31: =Master!$P$151 -> 100 | I31: =G31/H31*100 -> 1 | J31: =F31*I31 -> 0.12679349 | K31: =J31/$J$42% -> 4.1082245
B32: =Master!$B$157 -> 치킨트레이(소) | C32: =Master!$C$157 -> To Go Tray (S) | D32: =Master!$H$157 -> 100 | E32: =Master!$J$157 -> 8.4 | F32: =Master!$K$157 -> 0.084 | G32: 0 | H32: =Master!$P$157 -> 100 | I32: =G32/H32*100 -> 0 | J32: =F32*I32 -> 0 | K32: =J32/$J$42% -> 0
B33: =Master!$B$175 -> 종이백 (S,M) | C33: =Master!$C$175 -> Paper Bag (S,M) | D33: =Master!$H$175 -> 200 | E33: =Master!$J$175 -> 61.106668 | F33: =Master!$K$175 -> 0.30553334 | G33: 1 | H33: =Master!$P$175 -> 100 | I33: =G33/H33*100 -> 1 | J33: =F33*I33 -> 0.30553334 | K33: =J33/$J$42% -> 9.8995581
B34: =Master!$B$166 -> 비비큐 냅킨 | C34: =Master!$C$166 -> BBQ New LOGO Napkin | D34: =Master!$H$166 -> 5000 | E34: =Master!$J$166 -> 21.816824 | F34: =Master!$K$166 -> 0.0043633648 | G34: 1 | H34: =Master!$P$166 -> 100 | I34: =G34/H34*100 -> 1 | J34: =F34*I34 -> 0.0043633648 | K34: =J34/$J$42% -> 0.14137699
B35: =Master!$B$165 -> 왁스페이퍼 | C35: =Master!$C$165 -> BBQ Wax Paper Logo / Parchment paper | D35: =Master!$H$165 -> 2500 | E35: =Master!$J$165 -> 36.570748 | F35: =Master!$K$165 -> 0.014628299 | G35: 0 | H35: =Master!$P$165 -> 100 | I35: =G35/H35*100 -> 0 | J35: =F35*I35 -> 0 | K35: =J35/$J$42% -> 0
B36: =Master!$B$164 -> 비비큐 젓가락 | C36: =Master!$C$164 -> BBQ Chopstick Logo | D36: =Master!$H$164 -> 500 | E36: =Master!$J$164 -> 117.86347 | F36: =Master!$K$164 -> 0.23572693 | G36: 1 | H36: =Master!$P$164 -> 100 | I36: =G36/H36*100 -> 1 | J36: =F36*I36 -> 0.23572693 | K36: =J36/$J$42% -> 7.637767
B40: TOTAL | G40: =SUM(G31:G39) -> 4 | J40: =SUM(J31:J39) -> 0.67241713 | K40: =SUM(K31:K39) -> 21.786927
B42: TOTAL INGREDIENTS | J42: =J26+J40 -> 3.0863331 | K42: =K26+K40 -> 121.78693

Sheet BI_Classic(5)
A1: RECIPE COST CALCULATOR
B3: ITEM NAME | D3: Classic_Bone In_5pcs
B5: EST. SALE PRICE | D5: 21
B6: TOTAL COST(Dine In) | D6: =J26 -> 4.0231933
B7: TOTAL COST(Take Out) | D7: =J42 -> 4.6956104
B9: Food Cost | D9: =IF(D7="","",IF(ISBLANK(D5),"",D7/D5)) -> 0.2236005
B11: NET PROFIT | D11: =D5-D7 -> 16.30439
B13: PRIMARY INGREDIENTS
B14: Product Name | D14: Wheigh (g) | E14: Price | F14: Price/g | G14: Input/g | H14: Usage(%) | I14: Input+ Usage | J14: Price | K14: Price(%)/ Portion
B16: =Master!$B$6 -> 홀치킨 | C16: =Master!$C$6 -> Whole Chicken | D16: =Master!$H$6 -> 1000 | E16: =Master!$J$6 -> 2.8415359 | F16: =Master!$K$6 -> 0.0028415359 | G16: 650 | H16: =Master!$P$6 -> 98 | I16: =G16/H16*100 -> 663.26531 | J16: =F16*I16 -> 1.8846921 | K16: =J16/$J$26% -> 46.845677
B17: =Master!$B$43 -> 옐로우 배터믹스 [Battering Powder Mix-C] | C17: =Master!$C$43 -> Battering Powder Mix-C | D17: =Master!$H$43 -> 20000 | E17: =Master!$J$43 -> 89.079647 | F17: =Master!$K$43 -> 0.0044539824 | G17: =G16*10% -> 65 | H17: =Master!$P$43 -> 98 | I17: =G17/H17*100 -> 66.326531 | J17: =F17*I17 -> 0.2954172 | K17: =J17/$J$26% -> 7.3428537
B18: =Master!$B$31 -> 해바라기 유 | C18: =Master!$C$31 -> Sunflower Oil | D18: =Master!$H$31 -> 1320 | E18: =Master!$J$31 -> 14.971513 | F18: =Master!$K$31 -> 0.011342055 | G18: =G16*25% -> 162.5 | H18: =Master!$P$31 -> 100 | I18: =G18/H18*100 -> 162.5 | J18: =F18*I18 -> 1.8430839 | K18: =J18/$J$26% -> 45.811469
K19: =J19/$J$26% -> 0
K20: =J20/$J$26% -> 0
K21: =J21/$J$26% -> 0
K22: =J22/$J$26% -> 0
K23: =J23/$J$26% -> 0
K24: =J24/$J$26% -> 0
K25: =J25/$J$26% -> 0
B26: TOTAL | G26: =SUM(G16:G25) -> 877.5 | J26: =SUM(J16:J25) -> 4.0231933 | K26: =SUM(K16:K25) -> 100
B28: SECONDARY INGREDIENTS
B29: Product Name | D29: Wheigh (g) | E29: Price | F29: Price/g | G29: Input/g | H29: Usage(%) | I29: Input+ Usage | J29: Price | K29: Price(%)/ Portion
B31: =Master!$B$151 -> 치킨패키지(중) | C31: =Master!$C$151 -> Chicken Package (M) | D31: =Master!$H$151 -> 400 | E31: =Master!$J$151 -> 50.717397 | F31: =Master!$K$151 -> 0.12679349 | G31: 1 | H31: =Master!$P$151 -> 100 | I31: =G31/H31*100 -> 1 | J31: =F31*I31 -> 0.12679349 | K31: =J31/$J$42% -> 2.7002558
B32: =Master!$B$157 -> 치킨트레이(소) | C32: =Master!$C$157 -> To Go Tray (S) | D32: =Master!$H$157 -> 100 | E32: =Master!$J$157 -> 8.4 | F32: =Master!$K$157 -> 0.084 | G32: 0 | H32: =Master!$P$157 -> 100 | I32: =G32/H32*100 -> 0 | J32: =F32*I32 -> 0 | K32: =J32/$J$42% -> 0
B33: =Master!$B$175 -> 종이백 (S,M) | C33: =Master!$C$175 -> Paper Bag (S,M) | D33: =Master!$H$175 -> 200 | E33: =Master!$J$175 -> 61.106668 | F33: =Master!$K$175 -> 0.30553334 | G33: 1 | H33: =Master!$P$175 -> 100 | I33: =G33/H33*100 -> 1 | J33: =F33*I33 -> 0.30553334 | K33: =J33/$J$42% -> 6.5067864
B34: =Master!$B$166 -> 비비큐 냅킨 | C34: =Master!$C$166 -> BBQ New LOGO Napkin | D34: =Master!$H$166 -> 5000 | E34: =Master!$J$166 -> 21.816824 | F34: =Master!$K$166 -> 0.0043633648 | G34: 1 | H34: =Master!$P$166 -> 100 | I34: =G34/H34*100 -> 1 | J34: =F34*I34 -> 0.0043633648 | K34: =J34/$J$42% -> 0.092924336
B35: =Master!$B$165 -> 왁스페이퍼 | C35: =Master!$C$165 -> BBQ Wax Paper Logo / Parchment paper | D35: =Master!$H$165 -> 2500 | E35: =Master!$J$165 -> 36.570748 | F35: =Master!$K$165 -> 0.014628299 | G35: 0 | H35: =Master!$P$165 -> 100 | I35: =G35/H35*100 -> 0 | J35: =F35*I35 -> 0 | K35: =J35/$J$42% -> 0
B36: =Master!$B$164 -> 비비큐 젓가락 | C36: =Master!$C$164 -> BBQ Chopstick Logo | D36: =Master!$H$164 -> 500 | E36: =Master!$J$164 -> 117.86347 | F36: =Master!$K$164 -> 0.23572693 | G36: 1 | H36: =Master!$P$164 -> 100 | I36: =G36/H36*100 -> 1 | J36: =F36*I36 -> 0.23572693 | K36: =J36/$J$42% -> 5.0201552
B40: TOTAL | G40: =SUM(G31:G39) -> 4 | J40: =SUM(J31:J39) -> 0.67241713 | K40: =SUM(K31:K39) -> 14.320122
B42: TOTAL INGREDIENTS | J42: =J26+J40 -> 4.6956104 | K42: =K26+K40 -> 114.32012

Sheet BI_Secret (2)
A1: RECIPE COST CALCULATOR
B3: ITEM NAME | D3: Secret Sauced Chicken_Bone_In_2pcs
B5: EST. SALE PRICE | D5: 11
B6: TOTAL COST(Dine In) | D6: =$J$27 -> 2.2522821
B7: TOTAL COST(Take Out) | D7: =$J$42 -> 3.0600975
B9: Food Cost | D9: =IF(D7="","",IF(ISBLANK(D5),"",D7/D5)) -> 0.27819069
B11: NET PROFIT | D11: =D5-D7 -> 7.9399025
B13: PRIMARY INGREDIENTS
B14: Product Name | D14: Weight (g) | E14: Price | F14: Price/g | G14: Input/g | H14: Usage(%) | I14: Input+ Usage | J14: Price | K14: Price(%)/ Portion
B16: =Master!$B$6 -> 홀치킨 | C16: =Master!$C$6 -> Whole Chicken | D16: =Master!$H$6 -> 1000 | E16: =Master!$J$6 -> 2.8415359 | F16: =Master!$K$6 -> 0.0028415359 | G16: 260 | H16: =Master!$P$6 -> 98 | I16: =G16/H16*100 -> 265.30612 | J16: =F16*I16 -> 0.75387686 | K16: =J16/$J$27% -> 33.471689
B17: =Master!$B$36 -> #2 마리네이드 파우더 | C17: =Master!$C$36 -> Marinade Powder Mix | D17: =Master!$H$36 -> 20000 | E17: =Master!$J$36 -> 157.81782 | F17: =Master!$K$36 -> 0.0078908912 | G17: =G16*1.3% -> 3.38 | H17: =Master!$P$36 -> 98 | I17: =G17/H17*100 -> 3.4489796 | J17: =F17*I17 -> 0.027215523 | K17: =J17/$J$27% -> 1.2083532
B18: =Master!$B$41 -> 화이트 배터믹스 (White) | C18: =Master!$C$41 -> Battering Powder Mix | D18: =Master!$H$41 -> 20000 | E18: =Master!$J$41 -> 81.402648 | F18: =Master!$K$41 -> 0.0040701324 | G18: =G16*25% -> 65 | H18: =Master!$P$41 -> 85 | I18: =G18/H18*100 -> 76.470588 | J18: =F18*I18 -> 0.31124542 | K18: =J18/$J$27% -> 13.819113
B19: =Master!$B$31 -> 해바라기 유 | C19: =Master!$C$31 -> Sunflower Oil | D19: =Master!$H$31 -> 1320 | E19: =Master!$J$31 -> 14.971513 | F19: =Master!$K$31 -> 0.011342055 | G19: =G16*25% -> 65 | H19: =Master!$P$31 -> 100 | I19: =G19/H19*100 -> 65 | J19: =F19*I19 -> 0.73723358 | K19: =J19/$J$27% -> 32.732737
B20: =Master!$B$46 -> 시크릿 양념소스 | C20: =Master!$C$46 -> BBQ Secret Spicy Sauce | D20: =Master!$H$46 -> 10000 | E20: =Master!$J$46 -> 48.658269 | F20: =Master!$K$46 -> 0.0048658269 | G20: =G16*30% -> 78 | H20: =Master!$P$46 -> 96 | I20: =G20/H20*100 -> 81.25 | J20: =F20*I20 -> 0.39534843 | K20: =J20/$J$27% -> 17.553238
B21: =Master!$B$103 -> 마늘 | C21: =Master!$C$103 -> Garlic(Peeled) | D21: =Master!$H$103 -> 997.9024 | E21: =Master!$J$103 -> 6.8612325 | F21: =Master!$K$103 -> 0.0068756549 | G21: =G20*5% -> 3.9 | H21: =Master!$P$103 -> 98 | I21: =G21/H21*100 -> 3.9795918 | J21: =F21*I21 -> 0.0273623 | K21: =J21/$J$27% -> 1.21487
K22: =J22/$J$27% -> 0
K23: =J23/$J$27% -> 0
K24: =J24/$J$27% -> 0
K25: =J25/$J$27% -> 0
K26: =J26/$J$27% -> 0
B27: TOTAL | G27: =SUM(G16:G26) -> 475.28 | J27: =SUM(J16:J26) -> 2.2522821 | K27: =SUM(K16:K26) -> 100
B29: SECONDARY INGREDIENTS
B30: Product Name | D30: Weight (g) | E30: Price | F30: Price/g | G30: Input/g | H30: Usage(%) | I30: Input+ Usage | J30: Price | K30: Price(%)/ Portion
B32: =Master!$B$150 -> 치킨패키지(대) | C32: =Master!$C$150 -> Chicken Package (L) | D32: =Master!$H$150 -> 400 | E32: =Master!$J$150 -> 99.025402 | F32: =Master!$K$150 -> 0.2475635 | G32: 1 | H32: =Master!$P$150 -> 100 | I32: =G32/H32*100 -> 1 | J32: =F32*I32 -> 0.2475635 | K32: =J32/$J$42% -> 8.0900527
B33: =Master!$B$157 -> 치킨트레이(소) | C33: =Master!$C$157 -> To Go Tray (S) | D33: =Master!$H$157 -> 100 | E33: =Master!$J$157 -> 8.4 | F33: =Master!$K$157 -> 0.084 | G33: 0 | H33: =Master!$P$157 -> 100 | I33: =G33/H33*100 -> 0 | J33: =F33*I33 -> 0 | K33: =J33/$J$42% -> 0
B34: =Master!$B$175 -> 종이백 (S,M) | C34: =Master!$C$175 -> Paper Bag (S,M) | D34: =Master!$H$175 -> 200 | E34: =Master!$J$175 -> 61.106668 | F34: =Master!$K$175 -> 0.30553334 | G34: 1 | H34: =Master!$P$175 -> 100 | I34: =G34/H34*100 -> 1 | J34: =F34*I34 -> 0.30553334 | K34: =J34/$J$42% -> 9.9844313
B35: =Master!$B$166 -> 비비큐 냅킨 | C35: =Master!$C$166 -> BBQ New LOGO Napkin | D35: =Master!$H$166 -> 5000 | E35: =Master!$J$166 -> 21.816824 | F35: =Master!$K$166 -> 0.0043633648 | G35: 1 | H35: =Master!$P$166 -> 100 | I35: =G35/H35*100 -> 1 | J35: =F35*I35 -> 0.0043633648 | K35: =J35/$J$42% -> 0.14258908
B36: =Master!$B$164 -> 비비큐 젓가락 | C36: =Master!$C$164 -> BBQ Chopstick Logo | D36: =Master!$H$164 -> 500 | E36: =Master!$J$164 -> 117.86347 | F36: =Master!$K$164 -> 0.23572693 | G36: 1 | H36: =Master!$P$164 -> 100 | I36: =G36/H36*100 -> 1 | J36: =F36*I36 -> 0.23572693 | K36: =J36/$J$42% -> 7.7032489
B37: =Master!$B$165 -> 왁스페이퍼 | C37: =Master!$C$165 -> BBQ Wax Paper Logo / Parchment paper | D37: =Master!$H$165 -> 2500 | E37: =Master!$J$165 -> 36.570748 | F37: =Master!$K$165 -> 0.014628299 | G37: 1 | H37: =Master!$P$165 -> 100 | I37: =G37/H37*100 -> 1 | J37: =F37*I37 -> 0.014628299 | K37: =J37/$J$42% -> 0.47803376
B40: TOTAL | G40: =SUM(G32:G39) -> 5 | J40: =SUM(J32:J39) -> 0.80781544 | K40: =SUM(K32:K39) -> 26.398356
B42: TOTAL INGREDIENTS | J42: =J27+J40 -> 3.0600975 | K42: =K27+K40 -> 126.39836

Sheet BI_Secret (3)
A1: RECIPE COST CALCULATOR
B3: ITEM NAME | D3: Secret Sauced Chicken_Bone_In_3pcs
B5: EST. SALE PRICE | D5: 15
B6: TOTAL COST(Dine In) | D6: =$J$27 -> 3.3784232
B7: TOTAL COST(Take Out) | D7: =$J$42 -> 4.1862386
B9: Food Cost | D9: =IF(D7="","",IF(ISBLANK(D5),"",D7/D5)) -> 0.27908257
B11: NET PROFIT | D11: =D5-D7 -> 10.813761
B13: PRIMARY INGREDIENTS
B14: Product Name | D14: Weight (g) | E14: Price | F14: Price/g | G14: Input/g | H14: Usage(%) | I14: Input+ Usage | J14: Price | K14: Price(%)/ Portion
B16: =Master!$B$6 -> 홀치킨 | C16: =Master!$C$6 -> Whole Chicken | D16: =Master!$H$6 -> 1000 | E16: =Master!$J$6 -> 2.8415359 | F16: =Master!$K$6 -> 0.0028415359 | G16: 390 | H16: =Master!$P$6 -> 98 | I16: =G16/H16*100 -> 397.95918 | J16: =F16*I16 -> 1.1308153 | K16: =J16/$J$27% -> 33.471689
B17: =Master!$B$36 -> #2 마리네이드 파우더 | C17: =Master!$C$36 -> Marinade Powder Mix | D17: =Master!$H$36 -> 20000 | E17: =Master!$J$36 -> 157.81782 | F17: =Master!$K$36 -> 0.0078908912 | G17: =G16*1.3% -> 5.07 | H17: =Master!$P$36 -> 98 | I17: =G17/H17*100 -> 5.1734694 | J17: =F17*I17 -> 0.040823284 | K17: =J17/$J$27% -> 1.2083532
B18: =Master!$B$41 -> 화이트 배터믹스 (White) | C18: =Master!$C$41 -> Battering Powder Mix | D18: =Master!$H$41 -> 20000 | E18: =Master!$J$41 -> 81.402648 | F18: =Master!$K$41 -> 0.0040701324 | G18: =G16*25% -> 97.5 | H18: =Master!$P$41 -> 85 | I18: =G18/H18*100 -> 114.70588 | J18: =F18*I18 -> 0.46686813 | K18: =J18/$J$27% -> 13.819113
B19: =Master!$B$31 -> 해바라기 유 | C19: =Master!$C$31 -> Sunflower Oil | D19: =Master!$H$31 -> 1320 | E19: =Master!$J$31 -> 14.971513 | F19: =Master!$K$31 -> 0.011342055 | G19: =G16*25% -> 97.5 | H19: =Master!$P$31 -> 100 | I19: =G19/H19*100 -> 97.5 | J19: =F19*I19 -> 1.1058504 | K19: =J19/$J$27% -> 32.732737
B20: =Master!$B$46 -> 시크릿 양념소스 | C20: =Master!$C$46 -> BBQ Secret Spicy Sauce | D20: =Master!$H$46 -> 10000 | E20: =Master!$J$46 -> 48.658269 | F20: =Master!$K$46 -> 0.0048658269 | G20: =G16*30% -> 117 | H20: =Master!$P$46 -> 96 | I20: =G20/H20*100 -> 121.875 | J20: =F20*I20 -> 0.59302265 | K20: =J20/$J$27% -> 17.553238
B21: =Master!$B$103 -> 마늘 | C21: =Master!$C$103 -> Garlic(Peeled) | D21: =Master!$H$103 -> 997.9024 | E21: =Master!$J$103 -> 6.8612325 | F21: =Master!$K$103 -> 0.0068756549 | G21: =G20*5% -> 5.85 | H21: =Master!$P$103 -> 98 | I21: =G21/H21*100 -> 5.9693878 | J21: =F21*I21 -> 0.04104345 | K21: =J21/$J$27% -> 1.21487
K22: =J22/$J$27% -> 0
K23: =J23/$J$27% -> 0
K24: =J24/$J$27% -> 0
K25: =J25/$J$27% -> 0
K26: =J26/$J$27% -> 0
B27: TOTAL | G27: =SUM(G16:G26) -> 712.92 | J27: =SUM(J16:J26) -> 3.3784232 | K27: =SUM(K16:K26) -> 100
B29: SECONDARY INGREDIENTS
B30: Product Name | D30: Weight (g) | E30: Price | F30: Price/g | G30: Input/g | H30: Usage(%) | I30: Input+ Usage | J30: Price | K30: Price(%)/ Portion
B32: =Master!$B$150 -> 치킨패키지(대) | C32: =Master!$C$150 -> Chicken Package (L) | D32: =Master!$H$150 -> 400 | E32: =Master!$J$150 -> 99.025402 | F32: =Master!$K$150 -> 0.2475635 | G32: 1 | H32: =Master!$P$150 -> 100 | I32: =G32/H32*100 -> 1 | J32: =F32*I32 -> 0.2475635 | K32: =J32/$J$42% -> 5.9137457
B33: =Master!$B$157 -> 치킨트레이(소) | C33: =Master!$C$157 -> To Go Tray (S) | D33: =Master!$H$157 -> 100 | E33: =Master!$J$157 -> 8.4 | F33: =Master!$K$157 -> 0.084 | G33: 0 | H33: =Master!$P$157 -> 100 | I33: =G33/H33*100 -> 0 | J33: =F33*I33 -> 0 | K33: =J33/$J$42% -> 0
B34: =Master!$B$175 -> 종이백 (S,M) | C34: =Master!$C$175 -> Paper Bag (S,M) | D34: =Master!$H$175 -> 200 | E34: =Master!$J$175 -> 61.106668 | F34: =Master!$K$175 -> 0.30553334 | G34: 1 | H34: =Master!$P$175 -> 100 | I34: =G34/H34*100 -> 1 | J34: =F34*I34 -> 0.30553334 | K34: =J34/$J$42% -> 7.298517
B35: =Master!$B$166 -> 비비큐 냅킨 | C35: =Master!$C$166 -> BBQ New LOGO Napkin | D35: =Master!$H$166 -> 5000 | E35: =Master!$J$166 -> 21.816824 | F35: =Master!$K$166 -> 0.0043633648 | G35: 1 | H35: =Master!$P$166 -> 100 | I35: =G35/H35*100 -> 1 | J35: =F35*I35 -> 0.0043633648 | K35: =J35/$J$42% -> 0.10423115
B36: =Master!$B$164 -> 비비큐 젓가락 | C36: =Master!$C$164 -> BBQ Chopstick Logo | D36: =Master!$H$164 -> 500 | E36: =Master!$J$164 -> 117.86347 | F36: =Master!$K$164 -> 0.23572693 | G36: 1 | H36: =Master!$P$164 -> 100 | I36: =G36/H36*100 -> 1 | J36: =F36*I36 -> 0.23572693 | K36: =J36/$J$42% -> 5.630996
B37: =Master!$B$165 -> 왁스페이퍼 | C37: =Master!$C$165 -> BBQ Wax Paper Logo / Parchment paper | D37: =Master!$H$165 -> 2500 | E37: =Master!$J$165 -> 36.570748 | F37: =Master!$K$165 -> 0.014628299 | G37: 1 | H37: =Master!$P$165 -> 100 | I37: =G37/H37*100 -> 1 | J37: =F37*I37 -> 0.014628299 | K37: =J37/$J$42% -> 0.34943778
B40: TOTAL | G40: =SUM(G32:G39) -> 5 | J40: =SUM(J32:J39) -> 0.80781544 | K40: =SUM(K32:K39) -> 19.296928
B42: TOTAL INGREDIENTS | J42: =J27+J40 -> 4.1862386 | K42: =K27+K40 -> 119.29693

Sheet BI_Secret (5)
A1: RECIPE COST CALCULATOR
B3: ITEM NAME | D3: Secret Sauced Chicken_Bone_In_5pcs
B5: EST. SALE PRICE | D5: 21
B6: TOTAL COST(Dine In) | D6: =$J$27 -> 5.6307053
B7: TOTAL COST(Take Out) | D7: =$J$42 -> 6.4385207
B9: Food Cost | D9: =IF(D7="","",IF(ISBLANK(D5),"",D7/D5)) -> 0.30659622
B11: NET PROFIT | D11: =D5-D7 -> 14.561479
B13: PRIMARY INGREDIENTS
B14: Product Name | D14: Weight (g) | E14: Price | F14: Price/g | G14: Input/g | H14: Usage(%) | I14: Input+ Usage | J14: Price | K14: Price(%)/ Portion
B16: =Master!$B$6 -> 홀치킨 | C16: =Master!$C$6 -> Whole Chicken | D16: =Master!$H$6 -> 1000 | E16: =Master!$J$6 -> 2.8415359 | F16: =Master!$K$6 -> 0.0028415359 | G16: 650 | H16: =Master!$P$6 -> 98 | I16: =G16/H16*100 -> 663.26531 | J16: =F16*I16 -> 1.8846921 | K16: =J16/$J$27% -> 33.471689
B17: =Master!$B$36 -> #2 마리네이드 파우더 | C17: =Master!$C$36 -> Marinade Powder Mix | D17: =Master!$H$36 -> 20000 | E17: =Master!$J$36 -> 157.81782 | F17: =Master!$K$36 -> 0.0078908912 | G17: =G16*1.3% -> 8.45 | H17: =Master!$P$36 -> 98 | I17: =G17/H17*100 -> 8.622449 | J17: =F17*I17 -> 0.068038807 | K17: =J17/$J$27% -> 1.2083532
B18: =Master!$B$41 -> 화이트 배터믹스 (White) | C18: =Master!$C$41 -> Battering Powder Mix | D18: =Master!$H$41 -> 20000 | E18: =Master!$J$41 -> 81.402648 | F18: =Master!$K$41 -> 0.0040701324 | G18: =G16*25% -> 162.5 | H18: =Master!$P$41 -> 85 | I18: =G18/H18*100 -> 191.17647 | J18: =F18*I18 -> 0.77811355 | K18: =J18/$J$27% -> 13.819113
B19: =Master!$B$31 -> 해바라기 유 | C19: =Master!$C$31 -> Sunflower Oil | D19: =Master!$H$31 -> 1320 | E19: =Master!$J$31 -> 14.971513 | F19: =Master!$K$31 -> 0.011342055 | G19: =G16*25% -> 162.5 | H19: =Master!$P$31 -> 100 | I19: =G19/H19*100 -> 162.5 | J19: =F19*I19 -> 1.8430839 | K19: =J19/$J$27% -> 32.732737
B20: =Master!$B$46 -> 시크릿 양념소스 | C20: =Master!$C$46 -> BBQ Secret Spicy Sauce | D20: =Master!$H$46 -> 10000 | E20: =Master!$J$46 -> 48.658269 | F20: =Master!$K$46 -> 0.0048658269 | G20: =G16*30% -> 195 | H20: =Master!$P$46 -> 96 | I20: =G20/H20*100 -> 203.125 | J20: =F20*I20 -> 0.98837109 | K20: =J20/$J$27% -> 17.553238
B21: =Master!$B$103 -> 마늘 | C21: =Master!$C$103 -> Garlic(Peeled) | D21: =Master!$H$103 -> 997.9024 | E21: =Master!$J$103 -> 6.8612325 | F21: =Master!$K$103 -> 0.0068756549 | G21: =G20*5% -> 9.75 | H21: =Master!$P$103 -> 98 | I21: =G21/H21*100 -> 9.9489796 | J21: =F21*I21 -> 0.06840575 | K21: =J21/$J$27% -> 1.21487
K22: =J22/$J$27% -> 0
K23: =J23/$J$27% -> 0
K24: =J24/$J$27% -> 0
K25: =J25/$J$27% -> 0
K26: =J26/$J$27% -> 0
B27: TOTAL | G27: =SUM(G16:G26) -> 1188.2 | J27: =SUM(J16:J26) -> 5.6307053 | K27: =SUM(K16:K26) -> 100
B29: SECONDARY INGREDIENTS
B30: Product Name | D30: Weight (g) | E30: Price | F30: Price/g | G30: Input/g | H30: Usage(%) | I30: Input+ Usage | J30: Price | K30: Price(%)/ Portion
B32: =Master!$B$150 -> 치킨패키지(대) | C32: =Master!$C$150 -> Chicken Package (L) | D32: =Master!$H$150 -> 400 | E32: =Master!$J$150 -> 99.025402 | F32: =Master!$K$150 -> 0.2475635 | G32: 1 | H32: =Master!$P$150 -> 100 | I32: =G32/H32*100 -> 1 | J32: =F32*I32 -> 0.2475635 | K32: =J32/$J$42% -> 3.845037
B33: =Master!$B$157 -> 치킨트레이(소) | C33: =Master!$C$157 -> To Go Tray (S) | D33: =Master!$H$157 -> 100 | E33: =Master!$J$157 -> 8.4 | F33: =Master!$K$157 -> 0.084 | G33: 0 | H33: =Master!$P$157 -> 100 | I33: =G33/H33*100 -> 0 | J33: =F33*I33 -> 0 | K33: =J33/$J$42% -> 0
B34: =Master!$B$175 -> 종이백 (S,M) | C34: =Master!$C$175 -> Paper Bag (S,M) | D34: =Master!$H$175 -> 200 | E34: =Master!$J$175 -> 61.106668 | F34: =Master!$K$175 -> 0.30553334 | G34: 1 | H34: =Master!$P$175 -> 100 | I34: =G34/H34*100 -> 1 | J34: =F34*I34 -> 0.30553334 | K34: =J34/$J$42% -> 4.7453965
B35: =Master!$B$166 -> 비비큐 냅킨 | C35: =Master!$C$166 -> BBQ New LOGO Napkin | D35: =Master!$H$166 -> 5000 | E35: =Master!$J$166 -> 21.816824 | F35: =Master!$K$166 -> 0.0043633648 | G35: 1 | H35: =Master!$P$166 -> 100 | I35: =G35/H35*100 -> 1 | J35: =F35*I35 -> 0.0043633648 | K35: =J35/$J$42% -> 0.067769679
B36: =Master!$B$164 -> 비비큐 젓가락 | C36: =Master!$C$164 -> BBQ Chopstick Logo | D36: =Master!$H$164 -> 500 | E36: =Master!$J$164 -> 117.86347 | F36: =Master!$K$164 -> 0.23572693 | G36: 1 | H36: =Master!$P$164 -> 100 | I36: =G36/H36*100 -> 1 | J36: =F36*I36 -> 0.23572693 | K36: =J36/$J$42% -> 3.661197
B37: =Master!$B$165 -> 왁스페이퍼 | C37: =Master!$C$165 -> BBQ Wax Paper Logo / Parchment paper | D37: =Master!$H$165 -> 2500 | E37: =Master!$J$165 -> 36.570748 | F37: =Master!$K$165 -> 0.014628299 | G37: 1 | H37: =Master!$P$165 -> 100 | I37: =G37/H37*100 -> 1 | J37: =F37*I37 -> 0.014628299 | K37: =J37/$J$42% -> 0.22719969
B40: TOTAL | G40: =SUM(G32:G39) -> 5 | J40: =SUM(J32:J39) -> 0.80781544 | K40: =SUM(K32:K39) -> 12.5466
B42: TOTAL INGREDIENTS | J42: =J27+J40 -> 6.4385207 | K42: =K27+K40 -> 112.5466

Sheet BI_Hot Spicy(2)
A1: RECIPE COST CALCULATOR
B3: ITEM NAME | D3: Hot Spicy Chicken_Bone In_2pcs
B5: EST. SALE PRICE | D5: 11
B6: TOTAL COST(Dine In) | D6: =$J$27 -> 2.1314847
B7: TOTAL COST(Take Out) | D7: =$J$42 -> 2.9393002
B9: Food Cost | D9: =IF(D7="","",IF(ISBLANK(D5),"",D7/D5)) -> 0.26720911
B11: NET PROFIT | D11: =D5-D7 -> 8.0606998
B13: PRIMARY INGREDIENTS
B14: Product Name | D14: Weight (g) | E14: Price | F14: Price/g | G14: Input/g | H14: Usage(%) | I14: Input+ Usage | J14: Price | K14: Price(%)/ Portion
B16: =Master!$B$6 -> 홀치킨 | C16: =Master!$C$6 -> Whole Chicken | D16: =Master!$H$6 -> 1000 | E16: =Master!$J$6 -> 2.8415359 | F16: =Master!$K$6 -> 0.0028415359 | G16: 260 | H16: =Master!$P$6 -> 98 | I16: =G16/H16*100 -> 265.30612 | J16: =F16*I16 -> 0.75387686 | K16: =J16/$J$27% -> 35.368626
B17: =Master!$B$36 -> #2 마리네이드 파우더 | C17: =Master!$C$36 -> Marinade Powder Mix | D17: =Master!$H$36 -> 20000 | E17: =Master!$J$36 -> 157.81782 | F17: =Master!$K$36 -> 0.0078908912 | G17: =G16*1.3% -> 3.38 | H17: =Master!$P$36 -> 98 | I17: =G17/H17*100 -> 3.4489796 | J17: =F17*I17 -> 0.027215523 | K17: =J17/$J$27% -> 1.2768341
B18: =Master!$B$41 -> 화이트 배터믹스 (White) | C18: =Master!$C$41 -> Battering Powder Mix | D18: =Master!$H$41 -> 20000 | E18: =Master!$J$41 -> 81.402648 | F18: =Master!$K$41 -> 0.0040701324 | G18: =G16*25% -> 65 | H18: =Master!$P$41 -> 85 | I18: =G18/H18*100 -> 76.470588 | J18: =F18*I18 -> 0.31124542 | K18: =J18/$J$27% -> 14.602282
B19: =Master!$B$31 -> 해바라기 유 | C19: =Master!$C$31 -> Sunflower Oil | D19: =Master!$H$31 -> 1320 | E19: =Master!$J$31 -> 14.971513 | F19: =Master!$K$31 -> 0.011342055 | G19: =G16*25% -> 65 | H19: =Master!$P$31 -> 100 | I19: =G19/H19*100 -> 65 | J19: =F19*I19 -> 0.73723358 | K19: =J19/$J$27% -> 34.587795
B20: =Master!$B$50 -> 매운양념 소스 | C20: =Master!$C$50 -> Hot Spicy Sauce | D20: =Master!$H$50 -> 10000 | E20: =Master!$J$50 -> 55.737848 | F20: =Master!$K$50 -> 0.0055737848 | G20: =G16*20% -> 52 | H20: =Master!$P$50 -> 96 | I20: =G20/H20*100 -> 54.166667 | J20: =F20*I20 -> 0.30191334 | K20: =J20/$J$27% -> 14.164462
K21: =J21/$J$27% -> 0
K22: =J22/$J$27% -> 0
K23: =J23/$J$27% -> 0
K24: =J24/$J$27% -> 0
K25: =J25/$J$27% -> 0
K26: =J26/$J$27% -> 0
B27: TOTAL | G27: =SUM(G16:G26) -> 445.38 | J27: =SUM(J16:J26) -> 2.1314847 | K27: =SUM(K16:K26) -> 100
B29: SECONDARY INGREDIENTS
B30: Product Name | D30: Weight (g) | E30: Price | F30: Price/g | G30: Input/g | H30: Usage(%) | I30: Input+ Usage | J30: Price | K30: Price(%)/ Portion
B32: =Master!$B$150 -> 치킨패키지(대) | C32: =Master!$C$150 -> Chicken Package (L) | D32: =Master!$H$150 -> 400 | E32: =Master!$J$150 -> 99.025402 | F32: =Master!$K$150 -> 0.2475635 | G32: 1 | H32: =Master!$P$150 -> 100 | I32: =G32/H32*100 -> 1 | J32: =F32*I32 -> 0.2475635 | K32: =J32/$J$42% -> 8.4225323
B33: =Master!$B$157 -> 치킨트레이(소) | C33: =Master!$C$157 -> To Go Tray (S) | D33: =Master!$H$157 -> 100 | E33: =Master!$J$157 -> 8.4 | F33: =Master!$K$157 -> 0.084 | G33: 0 | H33: =Master!$P$157 -> 100 | I33: =G33/H33*100 -> 0 | J33: =F33*I33 -> 0 | K33: =J33/$J$42% -> 0
B34: =Master!$B$175 -> 종이백 (S,M) | C34: =Master!$C$175 -> Paper Bag (S,M) | D34: =Master!$H$175 -> 200 | E34: =Master!$J$175 -> 61.106668 | F34: =Master!$K$175 -> 0.30553334 | G34: 1 | H34: =Master!$P$175 -> 100 | I34: =G34/H34*100 -> 1 | J34: =F34*I34 -> 0.30553334 | K34: =J34/$J$42% -> 10.394765
B35: =Master!$B$166 -> 비비큐 냅킨 | C35: =Master!$C$166 -> BBQ New LOGO Napkin | D35: =Master!$H$166 -> 5000 | E35: =Master!$J$166 -> 21.816824 | F35: =Master!$K$166 -> 0.0043633648 | G35: 1 | H35: =Master!$P$166 -> 100 | I35: =G35/H35*100 -> 1 | J35: =F35*I35 -> 0.0043633648 | K35: =J35/$J$42% -> 0.14844911
B36: =Master!$B$164 -> 비비큐 젓가락 | C36: =Master!$C$164 -> BBQ Chopstick Logo | D36: =Master!$H$164 -> 500 | E36: =Master!$J$164 -> 117.86347 | F36: =Master!$K$164 -> 0.23572693 | G36: 1 | H36: =Master!$P$164 -> 100 | I36: =G36/H36*100 -> 1 | J36: =F36*I36 -> 0.23572693 | K36: =J36/$J$42% -> 8.0198319
B37: =Master!$B$165 -> 왁스페이퍼 | C37: =Master!$C$165 -> BBQ Wax Paper Logo / Parchment paper | D37: =Master!$H$165 -> 2500 | E37: =Master!$J$165 -> 36.570748 | F37: =Master!$K$165 -> 0.014628299 | G37: 1 | H37: =Master!$P$165 -> 100 | I37: =G37/H37*100 -> 1 | J37: =F37*I37 -> 0.014628299 | K37: =J37/$J$42% -> 0.49767967
B40: TOTAL | G40: =SUM(G32:G39) -> 5 | J40: =SUM(J32:J39) -> 0.80781544 | K40: =SUM(K32:K39) -> 27.483258
B42: TOTAL INGREDIENTS | J42: =J27+J40 -> 2.9393002 | K42: =K27+K40 -> 127.48326

Sheet BI_Hot Spicy(3)
A1: RECIPE COST CALCULATOR
B3: ITEM NAME | D3: Hot Spicy Chicken_Bone In_3pcs
B5: EST. SALE PRICE | D5: 15
B6: TOTAL COST(Dine In) | D6: =$J$27 -> 3.1972271
B7: TOTAL COST(Take Out) | D7: =$J$42 -> 4.0050425
B9: Food Cost | D9: =IF(D7="","",IF(ISBLANK(D5),"",D7/D5)) -> 0.26700283
B11: NET PROFIT | D11: =D5-D7 -> 10.994957
B13: PRIMARY INGREDIENTS
B14: Product Name | D14: Weight (g) | E14: Price | F14: Price/g | G14: Input/g | H14: Usage(%) | I14: Input+ Usage | J14: Price | K14: Price(%)/ Portion
B16: =Master!$B$6 -> 홀치킨 | C16: =Master!$C$6 -> Whole Chicken | D16: =Master!$H$6 -> 1000 | E16: =Master!$J$6 -> 2.8415359 | F16: =Master!$K$6 -> 0.0028415359 | G16: 390 | H16: =Master!$P$6 -> 98 | I16: =G16/H16*100 -> 397.95918 | J16: =F16*I16 -> 1.1308153 | K16: =J16/$J$27% -> 35.368626
B17: =Master!$B$36 -> #2 마리네이드 파우더 | C17: =Master!$C$36 -> Marinade Powder Mix | D17: =Master!$H$36 -> 20000 | E17: =Master!$J$36 -> 157.81782 | F17: =Master!$K$36 -> 0.0078908912 | G17: =G16*1.3% -> 5.07 | H17: =Master!$P$36 -> 98 | I17: =G17/H17*100 -> 5.1734694 | J17: =F17*I17 -> 0.040823284 | K17: =J17/$J$27% -> 1.2768341
B18: =Master!$B$41 -> 화이트 배터믹스 (White) | C18: =Master!$C$41 -> Battering Powder Mix | D18: =Master!$H$41 -> 20000 | E18: =Master!$J$41 -> 81.402648 | F18: =Master!$K$41 -> 0.0040701324 | G18: =G16*25% -> 97.5 | H18: =Master!$P$41 -> 85 | I18: =G18/H18*100 -> 114.70588 | J18: =F18*I18 -> 0.46686813 | K18: =J18/$J$27% -> 14.602282
B19: =Master!$B$31 -> 해바라기 유 | C19: =Master!$C$31 -> Sunflower Oil | D19: =Master!$H$31 -> 1320 | E19: =Master!$J$31 -> 14.971513 | F19: =Master!$K$31 -> 0.011342055 | G19: =G16*25% -> 97.5 | H19: =Master!$P$31 -> 100 | I19: =G19/H19*100 -> 97.5 | J19: =F19*I19 -> 1.1058504 | K19: =J19/$J$27% -> 34.587795
B20: =Master!$B$50 -> 매운양념 소스 | C20: =Master!$C$50 -> Hot Spicy Sauce | D20: =Master!$H$50 -> 10000 | E20: =Master!$J$50 -> 55.737848 | F20: =Master!$K$50 -> 0.0055737848 | G20: =G16*20% -> 78 | H20: =Master!$P$50 -> 96 | I20: =G20/H20*100 -> 81.25 | J20: =F20*I20 -> 0.45287001 | K20: =J20/$J$27% -> 14.164462
K21: =J21/$J$27% -> 0
K22: =J22/$J$27% -> 0
K23: =J23/$J$27% -> 0
K24: =J24/$J$27% -> 0
K25: =J25/$J$27% -> 0
K26: =J26/$J$27% -> 0
B27: TOTAL | G27: =SUM(G16:G26) -> 668.07 | J27: =SUM(J16:J26) -> 3.1972271 | K27: =SUM(K16:K26) -> 100
B29: SECONDARY INGREDIENTS
B30: Product Name | D30: Weight (g) | E30: Price | F30: Price/g | G30: Input/g | H30: Usage(%) | I30: Input+ Usage | J30: Price | K30: Price(%)/ Portion
B32: =Master!$B$150 -> 치킨패키지(대) | C32: =Master!$C$150 -> Chicken Package (L) | D32: =Master!$H$150 -> 400 | E32: =Master!$J$150 -> 99.025402 | F32: =Master!$K$150 -> 0.2475635 | G32: 1 | H32: =Master!$P$150 -> 100 | I32: =G32/H32*100 -> 1 | J32: =F32*I32 -> 0.2475635 | K32: =J32/$J$42% -> 6.1812953
B33: =Master!$B$157 -> 치킨트레이(소) | C33: =Master!$C$157 -> To Go Tray (S) | D33: =Master!$H$157 -> 100 | E33: =Master!$J$157 -> 8.4 | F33: =Master!$K$157 -> 0.084 | G33: 0 | H33: =Master!$P$157 -> 100 | I33: =G33/H33*100 -> 0 | J33: =F33*I33 -> 0 | K33: =J33/$J$42% -> 0
B34: =Master!$B$175 -> 종이백 (S,M) | C34: =Master!$C$175 -> Paper Bag (S,M) | D34: =Master!$H$175 -> 200 | E34: =Master!$J$175 -> 61.106668 | F34: =Master!$K$175 -> 0.30553334 | G34: 1 | H34: =Master!$P$175 -> 100 | I34: =G34/H34*100 -> 1 | J34: =F34*I34 -> 0.30553334 | K34: =J34/$J$42% -> 7.6287165
B35: =Master!$B$166 -> 비비큐 냅킨 | C35: =Master!$C$166 -> BBQ New LOGO Napkin | D35: =Master!$H$166 -> 5000 | E35: =Master!$J$166 -> 21.816824 | F35: =Master!$K$166 -> 0.0043633648 | G35: 1 | H35: =Master!$P$166 -> 100 | I35: =G35/H35*100 -> 1 | J35: =F35*I35 -> 0.0043633648 | K35: =J35/$J$42% -> 0.10894678
B36: =Master!$B$164 -> 비비큐 젓가락 | C36: =Master!$C$164 -> BBQ Chopstick Logo | D36: =Master!$H$164 -> 500 | E36: =Master!$J$164 -> 117.86347 | F36: =Master!$K$164 -> 0.23572693 | G36: 1 | H36: =Master!$P$164 -> 100 | I36: =G36/H36*100 -> 1 | J36: =F36*I36 -> 0.23572693 | K36: =J36/$J$42% -> 5.8857535
B37: =Master!$B$165 -> 왁스페이퍼 | C37: =Master!$C$165 -> BBQ Wax Paper Logo / Parchment paper | D37: =Master!$H$165 -> 2500 | E37: =Master!$J$165 -> 36.570748 | F37: =Master!$K$165 -> 0.014628299 | G37: 1 | H37: =Master!$P$165 -> 100 | I37: =G37/H37*100 -> 1 | J37: =F37*I37 -> 0.014628299 | K37: =J37/$J$42% -> 0.36524704
B40: TOTAL | G40: =SUM(G32:G39) -> 5 | J40: =SUM(J32:J39) -> 0.80781544 | K40: =SUM(K32:K39) -> 20.169959
B42: TOTAL INGREDIENTS | J42: =J27+J40 -> 4.0050425 | K42: =K27+K40 -> 120.16996

Sheet BI_Hot Spicy(5)
A1: RECIPE COST CALCULATOR
B3: ITEM NAME | D3: Hot Spicy Chicken_Bone In_5pcs
B5: EST. SALE PRICE | D5: 21
B6: TOTAL COST(Dine In) | D6: =$J$27 -> 5.3287118
B7: TOTAL COST(Take Out) | D7: =$J$42 -> 6.1365272
B9: Food Cost | D9: =IF(D7="","",IF(ISBLANK(D5),"",D7/D5)) -> 0.29221558
B11: NET PROFIT | D11: =D5-D7 -> 14.863473
B13: PRIMARY INGREDIENTS
B14: Product Name | D14: Weight (g) | E14: Price | F14: Price/g | G14: Input/g | H14: Usage(%) | I14: Input+ Usage | J14: Price | K14: Price(%)/ Portion
B16: =Master!$B$6 -> 홀치킨 | C16: =Master!$C$6 -> Whole Chicken | D16: =Master!$H$6 -> 1000 | E16: =Master!$J$6 -> 2.8415359 | F16: =Master!$K$6 -> 0.0028415359 | G16: 650 | H16: =Master!$P$6 -> 98 | I16: =G16/H16*100 -> 663.26531 | J16: =F16*I16 -> 1.8846921 | K16: =J16/$J$27% -> 35.368626
B17: =Master!$B$36 -> #2 마리네이드 파우더 | C17: =Master!$C$36 -> Marinade Powder Mix | D17: =Master!$H$36 -> 20000 | E17: =Master!$J$36 -> 157.81782 | F17: =Master!$K$36 -> 0.0078908912 | G17: =G16*1.3% -> 8.45 | H17: =Master!$P$36 -> 98 | I17: =G17/H17*100 -> 8.622449 | J17: =F17*I17 -> 0.068038807 | K17: =J17/$J$27% -> 1.2768341
B18: =Master!$B$41 -> 화이트 배터믹스 (White) | C18: =Master!$C$41 -> Battering Powder Mix | D18: =Master!$H$41 -> 20000 | E18: =Master!$J$41 -> 81.402648 | F18: =Master!$K$41 -> 0.0040701324 | G18: =G16*25% -> 162.5 | H18: =Master!$P$41 -> 85 | I18: =G18/H18*100 -> 191.17647 | J18: =F18*I18 -> 0.77811355 | K18: =J18/$J$27% -> 14.602282
B19: =Master!$B$31 -> 해바라기 유 | C19: =Master!$C$31 -> Sunflower Oil | D19: =Master!$H$31 -> 1320 | E19: =Master!$J$31 -> 14.971513 | F19: =Master!$K$31 -> 0.011342055 | G19: =G16*25% -> 162.5 | H19: =Master!$P$31 -> 100 | I19: =G19/H19*100 -> 162.5 | J19: =F19*I19 -> 1.8430839 | K19: =J19/$J$27% -> 34.587795
B20: =Master!$B$50 -> 매운양념 소스 | C20: =Master!$C$50 -> Hot Spicy Sauce | D20: =Master!$H$50 -> 10000 | E20: =Master!$J$50 -> 55.737848 | F20: =Master!$K$50 -> 0.0055737848 | G20: =G16*20% -> 130 | H20: =Master!$P$50 -> 96 | I20: =G20/H20*100 -> 135.41667 | J20: =F20*I20 -> 0.75478336 | K20: =J20/$J$27% -> 14.164462
K21: =J21/$J$27% -> 0
K22: =J22/$J$27% -> 0
K23: =J23/$J$27% -> 0
K24: =J24/$J$27% -> 0
K25: =J25/$J$27% -> 0
K26: =J26/$J$27% -> 0
B27: TOTAL | G27: =SUM(G16:G26) -> 1113.45 | J27: =SUM(J16:J26) -> 5.3287118 | K27: =SUM(K16:K26) -> 100
B29: SECONDARY INGREDIENTS
B30: Product Name | D30: Weight (g) | E30: Price | F30: Price/g | G30: Input/g | H30: Usage(%) | I30: Input+ Usage | J30: Price | K30: Price(%)/ Portion
B32: =Master!$B$150 -> 치킨패키지(대) | C32: =Master!$C$150 -> Chicken Package (L) | D32: =Master!$H$150 -> 400 | E32: =Master!$J$150 -> 99.025402 | F32: =Master!$K$150 -> 0.2475635 | G32: 1 | H32: =Master!$P$150 -> 100 | I32: =G32/H32*100 -> 1 | J32: =F32*I32 -> 0.2475635 | K32: =J32/$J$42% -> 4.0342607
B33: =Master!$B$157 -> 치킨트레이(소) | C33: =Master!$C$157 -> To Go Tray (S) | D33: =Master!$H$157 -> 100 | E33: =Master!$J$157 -> 8.4 | F33: =Master!$K$157 -> 0.084 | G33: 0 | H33: =Master!$P$157 -> 100 | I33: =G33/H33*100 -> 0 | J33: =F33*I33 -> 0 | K33: =J33/$J$42% -> 0
B34: =Master!$B$175 -> 종이백 (S,M) | C34: =Master!$C$175 -> Paper Bag (S,M) | D34: =Master!$H$175 -> 200 | E34: =Master!$J$175 -> 61.106668 | F34: =Master!$K$175 -> 0.30553334 | G34: 1 | H34: =Master!$P$175 -> 100 | I34: =G34/H34*100 -> 1 | J34: =F34*I34 -> 0.30553334 | K34: =J34/$J$42% -> 4.9789291
B35: =Master!$B$166 -> 비비큐 냅킨 | C35: =Master!$C$166 -> BBQ New LOGO Napkin | D35: =Master!$H$166 -> 5000 | E35: =Master!$J$166 -> 21.816824 | F35: =Master!$K$166 -> 0.0043633648 | G35: 1 | H35: =Master!$P$166 -> 100 | I35: =G35/H35*100 -> 1 | J35: =F35*I35 -> 0.0043633648 | K35: =J35/$J$42% -> 0.07110479
B36: =Master!$B$164 -> 비비큐 젓가락 | C36: =Master!$C$164 -> BBQ Chopstick Logo | D36: =Master!$H$164 -> 500 | E36: =Master!$J$164 -> 117.86347 | F36: =Master!$K$164 -> 0.23572693 | G36: 1 | H36: =Master!$P$164 -> 100 | I36: =G36/H36*100 -> 1 | J36: =F36*I36 -> 0.23572693 | K36: =J36/$J$42% -> 3.8413735
B37: =Master!$B$165 -> 왁스페이퍼 | C37: =Master!$C$165 -> BBQ Wax Paper Logo / Parchment paper | D37: =Master!$H$165 -> 2500 | E37: =Master!$J$165 -> 36.570748 | F37: =Master!$K$165 -> 0.014628299 | G37: 1 | H37: =Master!$P$165 -> 100 | I37: =G37/H37*100 -> 1 | J37: =F37*I37 -> 0.014628299 | K37: =J37/$J$42% -> 0.23838075
B40: TOTAL | G40: =SUM(G32:G39) -> 5 | J40: =SUM(J32:J39) -> 0.80781544 | K40: =SUM(K32:K39) -> 13.164049
B42: TOTAL INGREDIENTS | J42: =J27+J40 -> 6.1365272 | K42: =K27+K40 -> 113.16405

Sheet BI_Honey Garlic(2)
A1: RECIPE COST CALCULATOR
B3: ITEM NAME | D3: Honey Garlic Chicken_Bone In_2PC
B5: EST. SALE PRICE | D5: 11
B6: TOTAL COST(Dine In) | D6: =$J$26 -> 1.8223613
B7: TOTAL COST(Take Out) | D7: =$J$42 -> 2.6301768
B9: Food Cost | D9: =IF(D7="","",IF(ISBLANK(D5),"",D7/D5)) -> 0.23910698
B11: NET PROFIT | D11: =D5-D7 -> 8.3698232
B13: PRIMARY INGREDIENTS
B14: Product Name | D14: Wheigh (g) | E14: Price | F14: Price/g | G14: Input/g | H14: Usage(%) | I14: Input+ Usage | J14: Price | K14: Price(%)/ Portion
B16: =Master!$B$6 -> 홀치킨 | C16: =Master!$C$6 -> Whole Chicken | D16: =Master!$H$6 -> 1000 | E16: =Master!$J$6 -> 2.8415359 | F16: =Master!$K$6 -> 0.0028415359 | G16: 260 | H16: =Master!$P$6 -> 98 | I16: =G16/H16*100 -> 265.30612 | J16: =F16*I16 -> 0.75387686 | K16: =J16/$J$26% -> 41.368133
B17: =Master!$B$43 -> 옐로우 배터믹스 [Battering Powder Mix-C] | C17: =Master!$C$43 -> Battering Powder Mix-C | D17: =Master!$H$43 -> 20000 | E17: =Master!$J$43 -> 89.079647 | F17: =Master!$K$43 -> 0.0044539824 | G17: =G16*10% -> 26 | H17: =Master!$P$43 -> 98 | I17: =G17/H17*100 -> 26.530612 | J17: =F17*I17 -> 0.11816688 | K17: =J17/$J$26% -> 6.4842727
B18: =Master!$B$31 -> 해바라기 유 | C18: =Master!$C$31 -> Sunflower Oil | D18: =Master!$H$31 -> 1320 | E18: =Master!$J$31 -> 14.971513 | F18: =Master!$K$31 -> 0.011342055 | G18: =G16*25% -> 65 | H18: =Master!$P$31 -> 100 | I18: =G18/H18*100 -> 65 | J18: =F18*I18 -> 0.73723358 | K18: =J18/$J$26% -> 40.454852
B19: =Master!$B$51 -> 허니갈릭 소스 | C19: =Master!$C$51 -> Sweet Soy Sauce | D19: =Master!$H$51 -> 10000 | E19: =Master!$J$51 -> 85.549335 | F19: =Master!$K$51 -> 0.0085549335 | G19: =G16*8% -> 20.8 | H19: =Master!$P$51 -> 96 | I19: =G19/H19*100 -> 21.666667 | J19: =F19*I19 -> 0.18535689 | K19: =J19/$J$26% -> 10.171248
B20: =Master!$B$103 -> 마늘 | C20: =Master!$C$103 -> Garlic(Peeled) | D20: =Master!$H$103 -> 997.9024 | E20: =Master!$J$103 -> 6.8612325 | F20: =Master!$K$103 -> 0.0068756549 | G20: =G19*19% -> 3.952 | H20: =Master!$P$103 -> 98 | I20: =G20/H20*100 -> 4.0326531 | J20: =F20*I20 -> 0.027727131 | K20: =J20/$J$26% -> 1.5214947
K21: =J21/$J$26% -> 0
K22: =J22/$J$26% -> 0
K23: =J23/$J$26% -> 0
K24: =J24/$J$26% -> 0
K25: =J25/$J$26% -> 0
B26: TOTAL | G26: =SUM(G16:G25) -> 375.752 | J26: =SUM(J16:J25) -> 1.8223613 | K26: =SUM(K16:K25) -> 100
B28: SECONDARY INGREDIENTS
B29: Product Name | D29: Wheigh (g) | E29: Price | F29: Price/g | G29: Input/g | H29: Usage(%) | I29: Input+ Usage | J29: Price | K29: Price(%)/ Portion
B31: =Master!$B$150 -> 치킨패키지(대) | C31: =Master!$C$150 -> Chicken Package (L) | D31: =Master!$H$150 -> 400 | E31: =Master!$J$150 -> 99.025402 | F31: =Master!$K$150 -> 0.2475635 | G31: 1 | H31: =Master!$P$150 -> 100 | I31: =G31/H31*100 -> 1 | J31: =F31*I31 -> 0.2475635 | K31: =J31/$J$42% -> 9.4124284
B32: =Master!$B$157 -> 치킨트레이(소) | C32: =Master!$C$157 -> To Go Tray (S) | D32: =Master!$H$157 -> 100 | E32: =Master!$J$157 -> 8.4 | F32: =Master!$K$157 -> 0.084 | G32: 0 | H32: =Master!$P$157 -> 100 | I32: =G32/H32*100 -> 0 | J32: =F32*I32 -> 0 | K32: =J32/$J$42% -> 0
B33: =Master!$B$175 -> 종이백 (S,M) | C33: =Master!$C$175 -> Paper Bag (S,M) | D33: =Master!$H$175 -> 200 | E33: =Master!$J$175 -> 61.106668 | F33: =Master!$K$175 -> 0.30553334 | G33: 1 | H33: =Master!$P$175 -> 100 | I33: =G33/H33*100 -> 1 | J33: =F33*I33 -> 0.30553334 | K33: =J33/$J$42% -> 11.616456
B34: =Master!$B$166 -> 비비큐 냅킨 | C34: =Master!$C$166 -> BBQ New LOGO Napkin | D34: =Master!$H$166 -> 5000 | E34: =Master!$J$166 -> 21.816824 | F34: =Master!$K$166 -> 0.0043633648 | G34: 1 | H34: =Master!$P$166 -> 100 | I34: =G34/H34*100 -> 1 | J34: =F34*I34 -> 0.0043633648 | K34: =J34/$J$42% -> 0.16589626
B35: =Master!$B$165 -> 왁스페이퍼 | C35: =Master!$C$165 -> BBQ Wax Paper Logo / Parchment paper | D35: =Master!$H$165 -> 2500 | E35: =Master!$J$165 -> 36.570748 | F35: =Master!$K$165 -> 0.014628299 | G35: 1 | H35: =Master!$P$165 -> 100 | I35: =G35/H35*100 -> 1 | J35: =F35*I35 -> 0.014628299 | K35: =J35/$J$42% -> 0.55617172
B36: =Master!$B$164 -> 비비큐 젓가락 | C36: =Master!$C$164 -> BBQ Chopstick Logo | D36: =Master!$H$164 -> 500 | E36: =Master!$J$164 -> 117.86347 | F36: =Master!$K$164 -> 0.23572693 | G36: 1 | H36: =Master!$P$164 -> 100 | I36: =G36/H36*100 -> 1 | J36: =F36*I36 -> 0.23572693 | K36: =J36/$J$42% -> 8.9623988
B40: TOTAL | G40: =SUM(G31:G39) -> 5 | J40: =SUM(J31:J39) -> 0.80781544 | K40: =SUM(K31:K39) -> 30.713351
B42: TOTAL INGREDIENTS | J42: =J26+J40 -> 2.6301768 | K42: =K26+K40 -> 130.71335

Sheet BI_Honey Garlic(3)
A1: RECIPE COST CALCULATOR
B3: ITEM NAME | D3: Honey Garlic Chicken_Bone In_3PC
B5: EST. SALE PRICE | D5: 15
B6: TOTAL COST(Dine In) | D6: =$J$26 -> 2.733542
B7: TOTAL COST(Take Out) | D7: =$J$42 -> 3.5413574
B9: Food Cost | D9: =IF(D7="","",IF(ISBLANK(D5),"",D7/D5)) -> 0.2360905
B11: NET PROFIT | D11: =D5-D7 -> 11.458643
B13: PRIMARY INGREDIENTS
B14: Product Name | D14: Wheigh (g) | E14: Price | F14: Price/g | G14: Input/g | H14: Usage(%) | I14: Input+ Usage | J14: Price | K14: Price(%)/ Portion
B16: =Master!$B$6 -> 홀치킨 | C16: =Master!$C$6 -> Whole Chicken | D16: =Master!$H$6 -> 1000 | E16: =Master!$J$6 -> 2.8415359 | F16: =Master!$K$6 -> 0.0028415359 | G16: 390 | H16: =Master!$P$6 -> 98 | I16: =G16/H16*100 -> 397.95918 | J16: =F16*I16 -> 1.1308153 | K16: =J16/$J$26% -> 41.368133
B17: =Master!$B$43 -> 옐로우 배터믹스 [Battering Powder Mix-C] | C17: =Master!$C$43 -> Battering Powder Mix-C | D17: =Master!$H$43 -> 20000 | E17: =Master!$J$43 -> 89.079647 | F17: =Master!$K$43 -> 0.0044539824 | G17: =G16*10% -> 39 | H17: =Master!$P$43 -> 98 | I17: =G17/H17*100 -> 39.795918 | J17: =F17*I17 -> 0.17725032 | K17: =J17/$J$26% -> 6.4842727
B18: =Master!$B$31 -> 해바라기 유 | C18: =Master!$C$31 -> Sunflower Oil | D18: =Master!$H$31 -> 1320 | E18: =Master!$J$31 -> 14.971513 | F18: =Master!$K$31 -> 0.011342055 | G18: =G16*25% -> 97.5 | H18: =Master!$P$31 -> 100 | I18: =G18/H18*100 -> 97.5 | J18: =F18*I18 -> 1.1058504 | K18: =J18/$J$26% -> 40.454852
B19: =Master!$B$51 -> 허니갈릭 소스 | C19: =Master!$C$51 -> Sweet Soy Sauce | D19: =Master!$H$51 -> 10000 | E19: =Master!$J$51 -> 85.549335 | F19: =Master!$K$51 -> 0.0085549335 | G19: =G16*8% -> 31.2 | H19: =Master!$P$51 -> 96 | I19: =G19/H19*100 -> 32.5 | J19: =F19*I19 -> 0.27803534 | K19: =J19/$J$26% -> 10.171248
B20: =Master!$B$103 -> 마늘 | C20: =Master!$C$103 -> Garlic(Peeled) | D20: =Master!$H$103 -> 997.9024 | E20: =Master!$J$103 -> 6.8612325 | F20: =Master!$K$103 -> 0.0068756549 | G20: =G19*19% -> 5.928 | H20: =Master!$P$103 -> 98 | I20: =G20/H20*100 -> 6.0489796 | J20: =F20*I20 -> 0.041590696 | K20: =J20/$J$26% -> 1.5214947
K21: =J21/$J$26% -> 0
K22: =J22/$J$26% -> 0
K23: =J23/$J$26% -> 0
K24: =J24/$J$26% -> 0
K25: =J25/$J$26% -> 0
B26: TOTAL | G26: =SUM(G16:G25) -> 563.628 | J26: =SUM(J16:J25) -> 2.733542 | K26: =SUM(K16:K25) -> 100
B28: SECONDARY INGREDIENTS
B29: Product Name | D29: Wheigh (g) | E29: Price | F29: Price/g | G29: Input/g | H29: Usage(%) | I29: Input+ Usage | J29: Price | K29: Price(%)/ Portion
B31: =Master!$B$150 -> 치킨패키지(대) | C31: =Master!$C$150 -> Chicken Package (L) | D31: =Master!$H$150 -> 400 | E31: =Master!$J$150 -> 99.025402 | F31: =Master!$K$150 -> 0.2475635 | G31: 1 | H31: =Master!$P$150 -> 100 | I31: =G31/H31*100 -> 1 | J31: =F31*I31 -> 0.2475635 | K31: =J31/$J$42% -> 6.9906387
B32: =Master!$B$157 -> 치킨트레이(소) | C32: =Master!$C$157 -> To Go Tray (S) | D32: =Master!$H$157 -> 100 | E32: =Master!$J$157 -> 8.4 | F32: =Master!$K$157 -> 0.084 | G32: 0 | H32: =Master!$P$157 -> 100 | I32: =G32/H32*100 -> 0 | J32: =F32*I32 -> 0 | K32: =J32/$J$42% -> 0
B33: =Master!$B$175 -> 종이백 (S,M) | C33: =Master!$C$175 -> Paper Bag (S,M) | D33: =Master!$H$175 -> 200 | E33: =Master!$J$175 -> 61.106668 | F33: =Master!$K$175 -> 0.30553334 | G33: 1 | H33: =Master!$P$175 -> 100 | I33: =G33/H33*100 -> 1 | J33: =F33*I33 -> 0.30553334 | K33: =J33/$J$42% -> 8.6275769
B34: =Master!$B$166 -> 비비큐 냅킨 | C34: =Master!$C$166 -> BBQ New LOGO Napkin | D34: =Master!$H$166 -> 5000 | E34: =Master!$J$166 -> 21.816824 | F34: =Master!$K$166 -> 0.0043633648 | G34: 1 | H34: =Master!$P$166 -> 100 | I34: =G34/H34*100 -> 1 | J34: =F34*I34 -> 0.0043633648 | K34: =J34/$J$42% -> 0.12321165
B35: =Master!$B$165 -> 왁스페이퍼 | C35: =Master!$C$165 -> BBQ Wax Paper Logo / Parchment paper | D35: =Master!$H$165 -> 2500 | E35: =Master!$J$165 -> 36.570748 | F35: =Master!$K$165 -> 0.014628299 | G35: 1 | H35: =Master!$P$165 -> 100 | I35: =G35/H35*100 -> 1 | J35: =F35*I35 -> 0.014628299 | K35: =J35/$J$42% -> 0.4130704
B36: =Master!$B$164 -> 비비큐 젓가락 | C36: =Master!$C$164 -> BBQ Chopstick Logo | D36: =Master!$H$164 -> 500 | E36: =Master!$J$164 -> 117.86347 | F36: =Master!$K$164 -> 0.23572693 | G36: 1 | H36: =Master!$P$164 -> 100 | I36: =G36/H36*100 -> 1 | J36: =F36*I36 -> 0.23572693 | K36: =J36/$J$42% -> 6.6564004
B40: TOTAL | G40: =SUM(G31:G39) -> 5 | J40: =SUM(J31:J39) -> 0.80781544 | K40: =SUM(K31:K39) -> 22.810898
B42: TOTAL INGREDIENTS | J42: =J26+J40 -> 3.5413574 | K42: =K26+K40 -> 122.8109

Sheet BI_Honey Garlic(5)
A1: RECIPE COST CALCULATOR
B3: ITEM NAME | D3: Honey Garlic Chicken_Bone In_5PC
B5: EST. SALE PRICE | D5: 21
B6: TOTAL COST(Dine In) | D6: =$J$26 -> 4.5559033
B7: TOTAL COST(Take Out) | D7: =$J$42 -> 5.3637188
B9: Food Cost | D9: =IF(D7="","",IF(ISBLANK(D5),"",D7/D5)) -> 0.25541518
B11: NET PROFIT | D11: =D5-D7 -> 15.636281
B13: PRIMARY INGREDIENTS
B14: Product Name | D14: Wheigh (g) | E14: Price | F14: Price/g | G14: Input/g | H14: Usage(%) | I14: Input+ Usage | J14: Price | K14: Price(%)/ Portion
B16: =Master!$B$6 -> 홀치킨 | C16: =Master!$C$6 -> Whole Chicken | D16: =Master!$H$6 -> 1000 | E16: =Master!$J$6 -> 2.8415359 | F16: =Master!$K$6 -> 0.0028415359 | G16: 650 | H16: =Master!$P$6 -> 98 | I16: =G16/H16*100 -> 663.26531 | J16: =F16*I16 -> 1.8846921 | K16: =J16/$J$26% -> 41.368133
B17: =Master!$B$43 -> 옐로우 배터믹스 [Battering Powder Mix-C] | C17: =Master!$C$43 -> Battering Powder Mix-C | D17: =Master!$H$43 -> 20000 | E17: =Master!$J$43 -> 89.079647 | F17: =Master!$K$43 -> 0.0044539824 | G17: =G16*10% -> 65 | H17: =Master!$P$43 -> 98 | I17: =G17/H17*100 -> 66.326531 | J17: =F17*I17 -> 0.2954172 | K17: =J17/$J$26% -> 6.4842727
B18: =Master!$B$31 -> 해바라기 유 | C18: =Master!$C$31 -> Sunflower Oil | D18: =Master!$H$31 -> 1320 | E18: =Master!$J$31 -> 14.971513 | F18: =Master!$K$31 -> 0.011342055 | G18: =G16*25% -> 162.5 | H18: =Master!$P$31 -> 100 | I18: =G18/H18*100 -> 162.5 | J18: =F18*I18 -> 1.8430839 | K18: =J18/$J$26% -> 40.454852
B19: =Master!$B$51 -> 허니갈릭 소스 | C19: =Master!$C$51 -> Sweet Soy Sauce | D19: =Master!$H$51 -> 10000 | E19: =Master!$J$51 -> 85.549335 | F19: =Master!$K$51 -> 0.0085549335 | G19: =G16*8% -> 52 | H19: =Master!$P$51 -> 96 | I19: =G19/H19*100 -> 54.166667 | J19: =F19*I19 -> 0.46339223 | K19: =J19/$J$26% -> 10.171248
B20: =Master!$B$103 -> 마늘 | C20: =Master!$C$103 -> Garlic(Peeled) | D20: =Master!$H$103 -> 997.9024 | E20: =Master!$J$103 -> 6.8612325 | F20: =Master!$K$103 -> 0.0068756549 | G20: =G19*19% -> 9.88 | H20: =Master!$P$103 -> 98 | I20: =G20/H20*100 -> 10.081633 | J20: =F20*I20 -> 0.069317827 | K20: =J20/$J$26% -> 1.5214947
K21: =J21/$J$26% -> 0
K22: =J22/$J$26% -> 0
K23: =J23/$J$26% -> 0
K24: =J24/$J$26% -> 0
K25: =J25/$J$26% -> 0
B26: TOTAL | G26: =SUM(G16:G25) -> 939.38 | J26: =SUM(J16:J25) -> 4.5559033 | K26: =SUM(K16:K25) -> 100
B28: SECONDARY INGREDIENTS
B29: Product Name | D29: Wheigh (g) | E29: Price | F29: Price/g | G29: Input/g | H29: Usage(%) | I29: Input+ Usage | J29: Price | K29: Price(%)/ Portion
B31: =Master!$B$150 -> 치킨패키지(대) | C31: =Master!$C$150 -> Chicken Package (L) | D31: =Master!$H$150 -> 400 | E31: =Master!$J$150 -> 99.025402 | F31: =Master!$K$150 -> 0.2475635 | G31: 1 | H31: =Master!$P$150 -> 100 | I31: =G31/H31*100 -> 1 | J31: =F31*I31 -> 0.2475635 | K31: =J31/$J$42% -> 4.6155198
B32: =Master!$B$157 -> 치킨트레이(소) | C32: =Master!$C$157 -> To Go Tray (S) | D32: =Master!$H$157 -> 100 | E32: =Master!$J$157 -> 8.4 | F32: =Master!$K$157 -> 0.084 | G32: 0 | H32: =Master!$P$157 -> 100 | I32: =G32/H32*100 -> 0 | J32: =F32*I32 -> 0 | K32: =J32/$J$42% -> 0
B33: =Master!$B$175 -> 종이백 (S,M) | C33: =Master!$C$175 -> Paper Bag (S,M) | D33: =Master!$H$175 -> 200 | E33: =Master!$J$175 -> 61.106668 | F33: =Master!$K$175 -> 0.30553334 | G33: 1 | H33: =Master!$P$175 -> 100 | I33: =G33/H33*100 -> 1 | J33: =F33*I33 -> 0.30553334 | K33: =J33/$J$42% -> 5.6962967
B34: =Master!$B$166 -> 비비큐 냅킨 | C34: =Master!$C$166 -> BBQ New LOGO Napkin | D34: =Master!$H$166 -> 5000 | E34: =Master!$J$166 -> 21.816824 | F34: =Master!$K$166 -> 0.0043633648 | G34: 1 | H34: =Master!$P$166 -> 100 | I34: =G34/H34*100 -> 1 | J34: =F34*I34 -> 0.0043633648 | K34: =J34/$J$42% -> 0.081349619
B35: =Master!$B$165 -> 왁스페이퍼 | C35: =Master!$C$165 -> BBQ Wax Paper Logo / Parchment paper | D35: =Master!$H$165 -> 2500 | E35: =Master!$J$165 -> 36.570748 | F35: =Master!$K$165 -> 0.014628299 | G35: 1 | H35: =Master!$P$165 -> 100 | I35: =G35/H35*100 -> 1 | J35: =F35*I35 -> 0.014628299 | K35: =J35/$J$42% -> 0.27272681
B36: =Master!$B$164 -> 비비큐 젓가락 | C36: =Master!$C$164 -> BBQ Chopstick Logo | D36: =Master!$H$164 -> 500 | E36: =Master!$J$164 -> 117.86347 | F36: =Master!$K$164 -> 0.23572693 | G36: 1 | H36: =Master!$P$164 -> 100 | I36: =G36/H36*100 -> 1 | J36: =F36*I36 -> 0.23572693 | K36: =J36/$J$42% -> 4.3948413
B40: TOTAL | G40: =SUM(G31:G39) -> 5 | J40: =SUM(J31:J39) -> 0.80781544 | K40: =SUM(K31:K39) -> 15.060734
B42: TOTAL INGREDIENTS | J42: =J26+J40 -> 5.3637188 | K42: =K26+K40 -> 115.06073

Sheet BI_Soy Garlic(2)
A1: RECIPE COST CALCULATOR
B3: ITEM NAME | D3: Soy Garlic Chicken_Bone In_2PC
B5: EST. SALE PRICE | D5: 11
B6: TOTAL COST(Dine In) | D6: =$J$26 -> 1.7412579
B7: TOTAL COST(Take Out) | D7: =$J$42 -> 2.5490733
B9: Food Cost | D9: =IF(D7="","",IF(ISBLANK(D5),"",D7/D5)) -> 0.23173394
B11: NET PROFIT | D11: =D5-D7 -> 8.4509267
B13: PRIMARY INGREDIENTS
B14: Product Name | D14: Wheigh (g) | E14: Price | F14: Price/g | G14: Input/g | H14: Usage(%) | I14: Input+ Usage | J14: Price | K14: Price(%)/ Portion
B16: =Master!$B$6 -> 홀치킨 | C16: =Master!$C$6 -> Whole Chicken | D16: =Master!$H$6 -> 1000 | E16: =Master!$J$6 -> 2.8415359 | F16: =Master!$K$6 -> 0.0028415359 | G16: 260 | H16: =Master!$P$6 -> 98 | I16: =G16/H16*100 -> 265.30612 | J16: =F16*I16 -> 0.75387686 | K16: =J16/$J$26% -> 43.294958
B17: =Master!$B$43 -> 옐로우 배터믹스 [Battering Powder Mix-C] | C17: =Master!$C$43 -> Battering Powder Mix-C | D17: =Master!$H$43 -> 20000 | E17: =Master!$J$43 -> 89.079647 | F17: =Master!$K$43 -> 0.0044539824 | G17: =G16*10% -> 26 | H17: =Master!$P$43 -> 98 | I17: =G17/H17*100 -> 26.530612 | J17: =F17*I17 -> 0.11816688 | K17: =J17/$J$26% -> 6.7862941
B18: =Master!$B$31 -> 해바라기 유 | C18: =Master!$C$31 -> Sunflower Oil | D18: =Master!$H$31 -> 1320 | E18: =Master!$J$31 -> 14.971513 | F18: =Master!$K$31 -> 0.011342055 | G18: =G16*25% -> 65 | H18: =Master!$P$31 -> 100 | I18: =G18/H18*100 -> 65 | J18: =F18*I18 -> 0.73723358 | K18: =J18/$J$26% -> 42.339138
B19: =Master!$B$48 -> 소이갈릭소스 | C19: =Master!$C$48 -> Garlic Flavor Soy Sauce | D19: =Master!$H$48 -> 10000 | E19: =Master!$J$48 -> 69.616112 | F19: =Master!$K$48 -> 0.0069616112 | G19: =G16*7% -> 18.2 | H19: =Master!$P$48 -> 96 | I19: =G19/H19*100 -> 18.958333 | J19: =F19*I19 -> 0.13198055 | K19: =J19/$J$26% -> 7.5796095
K20: =J20/$J$26% -> 0
K21: =J21/$J$26% -> 0
K22: =J22/$J$26% -> 0
K23: =J23/$J$26% -> 0
K24: =J24/$J$26% -> 0
K25: =J25/$J$26% -> 0
B26: TOTAL | G26: =SUM(G16:G25) -> 369.2 | J26: =SUM(J16:J25) -> 1.7412579 | K26: =SUM(K16:K25) -> 100
B28: SECONDARY INGREDIENTS
B29: Product Name | D29: Wheigh (g) | E29: Price | F29: Price/g | G29: Input/g | H29: Usage(%) | I29: Input+ Usage | J29: Price | K29: Price(%)/ Portion
B31: =Master!$B$150 -> 치킨패키지(대) | C31: =Master!$C$150 -> Chicken Package (L) | D31: =Master!$H$150 -> 400 | E31: =Master!$J$150 -> 99.025402 | F31: =Master!$K$150 -> 0.2475635 | G31: 1 | H31: =Master!$P$150 -> 100 | I31: =G31/H31*100 -> 1 | J31: =F31*I31 -> 0.2475635 | K31: =J31/$J$42% -> 9.7119021
B32: =Master!$B$157 -> 치킨트레이(소) | C32: =Master!$C$157 -> To Go Tray (S) | D32: =Master!$H$157 -> 100 | E32: =Master!$J$157 -> 8.4 | F32: =Master!$K$157 -> 0.084 | G32: 0 | H32: =Master!$P$157 -> 100 | I32: =G32/H32*100 -> 0 | J32: =F32*I32 -> 0 | K32: =J32/$J$42% -> 0
B33: =Master!$B$175 -> 종이백 (S,M) | C33: =Master!$C$175 -> Paper Bag (S,M) | D33: =Master!$H$175 -> 200 | E33: =Master!$J$175 -> 61.106668 | F33: =Master!$K$175 -> 0.30553334 | G33: 1 | H33: =Master!$P$175 -> 100 | I33: =G33/H33*100 -> 1 | J33: =F33*I33 -> 0.30553334 | K33: =J33/$J$42% -> 11.986055
B34: =Master!$B$166 -> 비비큐 냅킨 | C34: =Master!$C$166 -> BBQ New LOGO Napkin | D34: =Master!$H$166 -> 5000 | E34: =Master!$J$166 -> 21.816824 | F34: =Master!$K$166 -> 0.0043633648 | G34: 1 | H34: =Master!$P$166 -> 100 | I34: =G34/H34*100 -> 1 | J34: =F34*I34 -> 0.0043633648 | K34: =J34/$J$42% -> 0.17117455
B35: =Master!$B$165 -> 왁스페이퍼 | C35: =Master!$C$165 -> BBQ Wax Paper Logo / Parchment paper | D35: =Master!$H$165 -> 2500 | E35: =Master!$J$165 -> 36.570748 | F35: =Master!$K$165 -> 0.014628299 | G35: 1 | H35: =Master!$P$165 -> 100 | I35: =G35/H35*100 -> 1 | J35: =F35*I35 -> 0.014628299 | K35: =J35/$J$42% -> 0.57386735
B36: =Master!$B$164 -> 비비큐 젓가락 | C36: =Master!$C$164 -> BBQ Chopstick Logo | D36: =Master!$H$164 -> 500 | E36: =Master!$J$164 -> 117.86347 | F36: =Master!$K$164 -> 0.23572693 | G36: 1 | H36: =Master!$P$164 -> 100 | I36: =G36/H36*100 -> 1 | J36: =F36*I36 -> 0.23572693 | K36: =J36/$J$42% -> 9.247554
B40: TOTAL | G40: =SUM(G31:G39) -> 5 | J40: =SUM(J31:J39) -> 0.80781544 | K40: =SUM(K31:K39) -> 31.690553
B42: TOTAL INGREDIENTS | J42: =J26+J40 -> 2.5490733 | K42: =K26+K40 -> 131.69055

Sheet BI_Soy Garlic(3)
A1: RECIPE COST CALCULATOR
B3: ITEM NAME | D3: Soy Garlic Chicken_Bone In_3PC
B5: EST. SALE PRICE | D5: 15
B6: TOTAL COST(Dine In) | D6: =$J$26 -> 2.6118868
B7: TOTAL COST(Take Out) | D7: =$J$42 -> 3.4197022
B9: Food Cost | D9: =IF(D7="","",IF(ISBLANK(D5),"",D7/D5)) -> 0.22798015
B11: NET PROFIT | D11: =D5-D7 -> 11.580298
B13: PRIMARY INGREDIENTS
B14: Product Name | D14: Wheigh (g) | E14: Price | F14: Price/g | G14: Input/g | H14: Usage(%) | I14: Input+ Usage | J14: Price | K14: Price(%)/ Portion
B16: =Master!$B$6 -> 홀치킨 | C16: =Master!$C$6 -> Whole Chicken | D16: =Master!$H$6 -> 1000 | E16: =Master!$J$6 -> 2.8415359 | F16: =Master!$K$6 -> 0.0028415359 | G16: 390 | H16: =Master!$P$6 -> 98 | I16: =G16/H16*100 -> 397.95918 | J16: =F16*I16 -> 1.1308153 | K16: =J16/$J$26% -> 43.294958
B17: =Master!$B$43 -> 옐로우 배터믹스 [Battering Powder Mix-C] | C17: =Master!$C$43 -> Battering Powder Mix-C | D17: =Master!$H$43 -> 20000 | E17: =Master!$J$43 -> 89.079647 | F17: =Master!$K$43 -> 0.0044539824 | G17: =G16*10% -> 39 | H17: =Master!$P$43 -> 98 | I17: =G17/H17*100 -> 39.795918 | J17: =F17*I17 -> 0.17725032 | K17: =J17/$J$26% -> 6.7862941
B18: =Master!$B$31 -> 해바라기 유 | C18: =Master!$C$31 -> Sunflower Oil | D18: =Master!$H$31 -> 1320 | E18: =Master!$J$31 -> 14.971513 | F18: =Master!$K$31 -> 0.011342055 | G18: =G16*25% -> 97.5 | H18: =Master!$P$31 -> 100 | I18: =G18/H18*100 -> 97.5 | J18: =F18*I18 -> 1.1058504 | K18: =J18/$J$26% -> 42.339138
B19: =Master!$B$48 -> 소이갈릭소스 | C19: =Master!$C$48 -> Garlic Flavor Soy Sauce | D19: =Master!$H$48 -> 10000 | E19: =Master!$J$48 -> 69.616112 | F19: =Master!$K$48 -> 0.0069616112 | G19: =G16*7% -> 27.3 | H19: =Master!$P$48 -> 96 | I19: =G19/H19*100 -> 28.4375 | J19: =F19*I19 -> 0.19797082 | K19: =J19/$J$26% -> 7.5796095
K20: =J20/$J$26% -> 0
K21: =J21/$J$26% -> 0
K22: =J22/$J$26% -> 0
K23: =J23/$J$26% -> 0
K24: =J24/$J$26% -> 0
K25: =J25/$J$26% -> 0
B26: TOTAL | G26: =SUM(G16:G25) -> 553.8 | J26: =SUM(J16:J25) -> 2.6118868 | K26: =SUM(K16:K25) -> 100
B28: SECONDARY INGREDIENTS
B29: Product Name | D29: Wheigh (g) | E29: Price | F29: Price/g | G29: Input/g | H29: Usage(%) | I29: Input+ Usage | J29: Price | K29: Price(%)/ Portion
B31: =Master!$B$150 -> 치킨패키지(대) | C31: =Master!$C$150 -> Chicken Package (L) | D31: =Master!$H$150 -> 400 | E31: =Master!$J$150 -> 99.025402 | F31: =Master!$K$150 -> 0.2475635 | G31: 1 | H31: =Master!$P$150 -> 100 | I31: =G31/H31*100 -> 1 | J31: =F31*I31 -> 0.2475635 | K31: =J31/$J$42% -> 7.2393293
B32: =Master!$B$157 -> 치킨트레이(소) | C32: =Master!$C$157 -> To Go Tray (S) | D32: =Master!$H$157 -> 100 | E32: =Master!$J$157 -> 8.4 | F32: =Master!$K$157 -> 0.084 | G32: 0 | H32: =Master!$P$157 -> 100 | I32: =G32/H32*100 -> 0 | J32: =F32*I32 -> 0 | K32: =J32/$J$42% -> 0
B33: =Master!$B$175 -> 종이백 (S,M) | C33: =Master!$C$175 -> Paper Bag (S,M) | D33: =Master!$H$175 -> 200 | E33: =Master!$J$175 -> 61.106668 | F33: =Master!$K$175 -> 0.30553334 | G33: 1 | H33: =Master!$P$175 -> 100 | I33: =G33/H33*100 -> 1 | J33: =F33*I33 -> 0.30553334 | K33: =J33/$J$42% -> 8.9345012
B34: =Master!$B$166 -> 비비큐 냅킨 | C34: =Master!$C$166 -> BBQ New LOGO Napkin | D34: =Master!$H$166 -> 5000 | E34: =Master!$J$166 -> 21.816824 | F34: =Master!$K$166 -> 0.0043633648 | G34: 1 | H34: =Master!$P$166 -> 100 | I34: =G34/H34*100 -> 1 | J34: =F34*I34 -> 0.0043633648 | K34: =J34/$J$42% -> 0.12759488
B35: =Master!$B$165 -> 왁스페이퍼 | C35: =Master!$C$165 -> BBQ Wax Paper Logo / Parchment paper | D35: =Master!$H$165 -> 2500 | E35: =Master!$J$165 -> 36.570748 | F35: =Master!$K$165 -> 0.014628299 | G35: 1 | H35: =Master!$P$165 -> 100 | I35: =G35/H35*100 -> 1 | J35: =F35*I35 -> 0.014628299 | K35: =J35/$J$42% -> 0.4277653
B36: =Master!$B$164 -> 비비큐 젓가락 | C36: =Master!$C$164 -> BBQ Chopstick Logo | D36: =Master!$H$164 -> 500 | E36: =Master!$J$164 -> 117.86347 | F36: =Master!$K$164 -> 0.23572693 | G36: 1 | H36: =Master!$P$164 -> 100 | I36: =G36/H36*100 -> 1 | J36: =F36*I36 -> 0.23572693 | K36: =J36/$J$42% -> 6.8932005
B40: TOTAL | G40: =SUM(G31:G39) -> 5 | J40: =SUM(J31:J39) -> 0.80781544 | K40: =SUM(K31:K39) -> 23.622391
B42: TOTAL INGREDIENTS | J42: =J26+J40 -> 3.4197022 | K42: =K26+K40 -> 123.62239

Sheet BI_Soy Garlic(5)
A1: RECIPE COST CALCULATOR
B3: ITEM NAME | D3: Soy Garlic Chicken_Bone In_5PC
B5: EST. SALE PRICE | D5: 21
B6: TOTAL COST(Dine In) | D6: =$J$26 -> 4.3531447
B7: TOTAL COST(Take Out) | D7: =$J$42 -> 5.1609601
B9: Food Cost | D9: =IF(D7="","",IF(ISBLANK(D5),"",D7/D5)) -> 0.24576
B11: NET PROFIT | D11: =D5-D7 -> 15.83904
B13: PRIMARY INGREDIENTS
B14: Product Name | D14: Wheigh (g) | E14: Price | F14: Price/g | G14: Input/g | H14: Usage(%) | I14: Input+ Usage | J14: Price | K14: Price(%)/ Portion
B16: =Master!$B$6 -> 홀치킨 | C16: =Master!$C$6 -> Whole Chicken | D16: =Master!$H$6 -> 1000 | E16: =Master!$J$6 -> 2.8415359 | F16: =Master!$K$6 -> 0.0028415359 | G16: 650 | H16: =Master!$P$6 -> 98 | I16: =G16/H16*100 -> 663.26531 | J16: =F16*I16 -> 1.8846921 | K16: =J16/$J$26% -> 43.294958
B17: =Master!$B$43 -> 옐로우 배터믹스 [Battering Powder Mix-C] | C17: =Master!$C$43 -> Battering Powder Mix-C | D17: =Master!$H$43 -> 20000 | E17: =Master!$J$43 -> 89.079647 | F17: =Master!$K$43 -> 0.0044539824 | G17: =G16*10% -> 65 | H17: =Master!$P$43 -> 98 | I17: =G17/H17*100 -> 66.326531 | J17: =F17*I17 -> 0.2954172 | K17: =J17/$J$26% -> 6.7862941
B18: =Master!$B$31 -> 해바라기 유 | C18: =Master!$C$31 -> Sunflower Oil | D18: =Master!$H$31 -> 1320 | E18: =Master!$J$31 -> 14.971513 | F18: =Master!$K$31 -> 0.011342055 | G18: =G16*25% -> 162.5 | H18: =Master!$P$31 -> 100 | I18: =G18/H18*100 -> 162.5 | J18: =F18*I18 -> 1.8430839 | K18: =J18/$J$26% -> 42.339138
B19: =Master!$B$48 -> 소이갈릭소스 | C19: =Master!$C$48 -> Garlic Flavor Soy Sauce | D19: =Master!$H$48 -> 10000 | E19: =Master!$J$48 -> 69.616112 | F19: =Master!$K$48 -> 0.0069616112 | G19: =G16*7% -> 45.5 | H19: =Master!$P$48 -> 96 | I19: =G19/H19*100 -> 47.395833 | J19: =F19*I19 -> 0.32995136 | K19: =J19/$J$26% -> 7.5796095
K20: =J20/$J$26% -> 0
K21: =J21/$J$26% -> 0
K22: =J22/$J$26% -> 0
K23: =J23/$J$26% -> 0
K24: =J24/$J$26% -> 0
K25: =J25/$J$26% -> 0
B26: TOTAL | G26: =SUM(G16:G25) -> 923 | J26: =SUM(J16:J25) -> 4.3531447 | K26: =SUM(K16:K25) -> 100
B28: SECONDARY INGREDIENTS
B29: Product Name | D29: Wheigh (g) | E29: Price | F29: Price/g | G29: Input/g | H29: Usage(%) | I29: Input+ Usage | J29: Price | K29: Price(%)/ Portion
B31: =Master!$B$150 -> 치킨패키지(대) | C31: =Master!$C$150 -> Chicken Package (L) | D31: =Master!$H$150 -> 400 | E31: =Master!$J$150 -> 99.025402 | F31: =Master!$K$150 -> 0.2475635 | G31: 1 | H31: =Master!$P$150 -> 100 | I31: =G31/H31*100 -> 1 | J31: =F31*I31 -> 0.2475635 | K31: =J31/$J$42% -> 4.7968498
B32: =Master!$B$157 -> 치킨트레이(소) | C32: =Master!$C$157 -> To Go Tray (S) | D32: =Master!$H$157 -> 100 | E32: =Master!$J$157 -> 8.4 | F32: =Master!$K$157 -> 0.084 | G32: 0 | H32: =Master!$P$157 -> 100 | I32: =G32/H32*100 -> 0 | J32: =F32*I32 -> 0 | K32: =J32/$J$42% -> 0
B33: =Master!$B$175 -> 종이백 (S,M) | C33: =Master!$C$175 -> Paper Bag (S,M) | D33: =Master!$H$175 -> 200 | E33: =Master!$J$175 -> 61.106668 | F33: =Master!$K$175 -> 0.30553334 | G33: 1 | H33: =Master!$P$175 -> 100 | I33: =G33/H33*100 -> 1 | J33: =F33*I33 -> 0.30553334 | K33: =J33/$J$42% -> 5.9200872
B34: =Master!$B$166 -> 비비큐 냅킨 | C34: =Master!$C$166 -> BBQ New LOGO Napkin | D34: =Master!$H$166 -> 5000 | E34: =Master!$J$166 -> 21.816824 | F34: =Master!$K$166 -> 0.0043633648 | G34: 1 | H34: =Master!$P$166 -> 100 | I34: =G34/H34*100 -> 1 | J34: =F34*I34 -> 0.0043633648 | K34: =J34/$J$42% -> 0.084545603
B35: =Master!$B$165 -> 왁스페이퍼 | C35: =Master!$C$165 -> BBQ Wax Paper Logo / Parchment paper | D35: =Master!$H$165 -> 2500 | E35: =Master!$J$165 -> 36.570748 | F35: =Master!$K$165 -> 0.014628299 | G35: 1 | H35: =Master!$P$165 -> 100 | I35: =G35/H35*100 -> 1 | J35: =F35*I35 -> 0.014628299 | K35: =J35/$J$42% -> 0.28344144
B36: =Master!$B$164 -> 비비큐 젓가락 | C36: =Master!$C$164 -> BBQ Chopstick Logo | D36: =Master!$H$164 -> 500 | E36: =Master!$J$164 -> 117.86347 | F36: =Master!$K$164 -> 0.23572693 | G36: 1 | H36: =Master!$P$164 -> 100 | I36: =G36/H36*100 -> 1 | J36: =F36*I36 -> 0.23572693 | K36: =J36/$J$42% -> 4.5675015
B40: TOTAL | G40: =SUM(G31:G39) -> 5 | J40: =SUM(J31:J39) -> 0.80781544 | K40: =SUM(K31:K39) -> 15.652426
B42: TOTAL INGREDIENTS | J42: =J26+J40 -> 5.1609601 | K42: =K26+K40 -> 115.65243

Sheet BI_Galbi(2)
A1: RECIPE COST CALCULATOR
B3: ITEM NAME | D3: Galbi Chicken_Bone In_2PC
B5: EST. SALE PRICE | D5: 11
B6: TOTAL COST(Dine In) | D6: =$J$26 -> 1.9934195
B7: TOTAL COST(Take Out) | D7: =$J$42 -> 2.8012349
B9: Food Cost | D9: =IF(D7="","",IF(ISBLANK(D5),"",D7/D5)) -> 0.25465772
B11: NET PROFIT | D11: =D5-D7 -> 8.1987651
B13: PRIMARY INGREDIENTS
B14: Product Name | D14: Wheigh (g) | E14: Price | F14: Price/g | G14: Input/g | H14: Usage(%) | I14: Input+ Usage | J14: Price | K14: Price(%)/ Portion
B16: =Master!$B$6 -> 홀치킨 | C16: =Master!$C$6 -> Whole Chicken | D16: =Master!$H$6 -> 1000 | E16: =Master!$J$6 -> 2.8415359 | F16: =Master!$K$6 -> 0.0028415359 | G16: 260 | H16: =Master!$P$6 -> 98 | I16: =G16/H16*100 -> 265.30612 | J16: =F16*I16 -> 0.75387686 | K16: =J16/$J$26% -> 37.818275
B17: =Master!$B$43 -> 옐로우 배터믹스 [Battering Powder Mix-C] | C17: =Master!$C$43 -> Battering Powder Mix-C | D17: =Master!$H$43 -> 20000 | E17: =Master!$J$43 -> 89.079647 | F17: =Master!$K$43 -> 0.0044539824 | G17: =G16*10% -> 26 | H17: =Master!$P$43 -> 98 | I17: =G17/H17*100 -> 26.530612 | J17: =F17*I17 -> 0.11816688 | K17: =J17/$J$26% -> 5.9278481
B18: =Master!$B$31 -> 해바라기 유 | C18: =Master!$C$31 -> Sunflower Oil | D18: =Master!$H$31 -> 1320 | E18: =Master!$J$31 -> 14.971513 | F18: =Master!$K$31 -> 0.011342055 | G18: =G16*25% -> 65 | H18: =Master!$P$31 -> 100 | I18: =G18/H18*100 -> 65 | J18: =F18*I18 -> 0.73723358 | K18: =J18/$J$26% -> 36.983363
B19: =Master!$B$52 -> 갈비 소스 | C19: =Master!$C$52 -> Galbi Flavor Sauce | D19: =Master!$H$52 -> 12000 | E19: =Master!$J$52 -> 80.524714 | F19: =Master!$K$52 -> 0.0067103928 | G19: =G16*20% -> 52 | H19: =Master!$P$52 -> 96 | I19: =G19/H19*100 -> 54.166667 | J19: =F19*I19 -> 0.36347961 | K19: =J19/$J$26% -> 18.233975
B20: =Master!$B$105 -> 파 | C20: =Master!$C$105 -> Spring Onion | D20: =Master!$H$105 -> 180 | E20: =Master!$J$105 -> 0.64442515 | F20: =Master!$K$105 -> 0.0035801397 | G20: =G19*5% -> 2.6 | H20: =Master!$P$105 -> 95 | I20: =G20/H20*100 -> 2.7368421 | J20: =F20*I20 -> 0.0097982772 | K20: =J20/$J$26% -> 0.49153112
B21: =Master!$B$79 -> 참깨 | C21: =Master!$C$79 -> Sesame Seeds | D21: =Master!$H$79 -> 453.592 | E21: =Master!$J$79 -> 4.9279571 | F21: =Master!$K$79 -> 0.010864294 | G21: 1 | H21: =Master!$P$79 -> 100 | I21: =G21/H21*100 -> 1 | J21: =F21*I21 -> 0.010864294 | K21: =J21/$J$26% -> 0.54500794
K22: =J22/$J$26% -> 0
K23: =J23/$J$26% -> 0
K24: =J24/$J$26% -> 0
K25: =J25/$J$26% -> 0
B26: TOTAL | G26: =SUM(G16:G25) -> 406.6 | J26: =SUM(J16:J25) -> 1.9934195 | K26: =SUM(K16:K25) -> 100
B28: SECONDARY INGREDIENTS
B29: Product Name | D29: Wheigh (g) | E29: Price | F29: Price/g | G29: Input/g | H29: Usage(%) | I29: Input+ Usage | J29: Price | K29: Price(%)/ Portion
B31: =Master!$B$150 -> 치킨패키지(대) | C31: =Master!$C$150 -> Chicken Package (L) | D31: =Master!$H$150 -> 400 | E31: =Master!$J$150 -> 99.025402 | F31: =Master!$K$150 -> 0.2475635 | G31: 1 | H31: =Master!$P$150 -> 100 | I31: =G31/H31*100 -> 1 | J31: =F31*I31 -> 0.2475635 | K31: =J31/$J$42% -> 8.8376559
B32: =Master!$B$157 -> 치킨트레이(소) | C32: =Master!$C$157 -> To Go Tray (S) | D32: =Master!$H$157 -> 100 | E32: =Master!$J$157 -> 8.4 | F32: =Master!$K$157 -> 0.084 | G32: 0 | H32: =Master!$P$157 -> 100 | I32: =G32/H32*100 -> 0 | J32: =F32*I32 -> 0 | K32: =J32/$J$42% -> 0
B33: =Master!$B$175 -> 종이백 (S,M) | C33: =Master!$C$175 -> Paper Bag (S,M) | D33: =Master!$H$175 -> 200 | E33: =Master!$J$175 -> 61.106668 | F33: =Master!$K$175 -> 0.30553334 | G33: 1 | H33: =Master!$P$175 -> 100 | I33: =G33/H33*100 -> 1 | J33: =F33*I33 -> 0.30553334 | K33: =J33/$J$42% -> 10.907094
B34: =Master!$B$166 -> 비비큐 냅킨 | C34: =Master!$C$166 -> BBQ New LOGO Napkin | D34: =Master!$H$166 -> 5000 | E34: =Master!$J$166 -> 21.816824 | F34: =Master!$K$166 -> 0.0043633648 | G34: 1 | H34: =Master!$P$166 -> 100 | I34: =G34/H34*100 -> 1 | J34: =F34*I34 -> 0.0043633648 | K34: =J34/$J$42% -> 0.15576576
B35: =Master!$B$165 -> 왁스페이퍼 | C35: =Master!$C$165 -> BBQ Wax Paper Logo / Parchment paper | D35: =Master!$H$165 -> 2500 | E35: =Master!$J$165 -> 36.570748 | F35: =Master!$K$165 -> 0.014628299 | G35: 1 | H35: =Master!$P$165 -> 100 | I35: =G35/H35*100 -> 1 | J35: =F35*I35 -> 0.014628299 | K35: =J35/$J$42% -> 0.52220894
B36: =Master!$B$164 -> 비비큐 젓가락 | C36: =Master!$C$164 -> BBQ Chopstick Logo | D36: =Master!$H$164 -> 500 | E36: =Master!$J$164 -> 117.86347 | F36: =Master!$K$164 -> 0.23572693 | G36: 1 | H36: =Master!$P$164 -> 100 | I36: =G36/H36*100 -> 1 | J36: =F36*I36 -> 0.23572693 | K36: =J36/$J$42% -> 8.4151075
B40: TOTAL | G40: =SUM(G31:G39) -> 5 | J40: =SUM(J31:J39) -> 0.80781544 | K40: =SUM(K31:K39) -> 28.837832
B42: TOTAL INGREDIENTS | J42: =J26+J40 -> 2.8012349 | K42: =K26+K40 -> 128.83783

Sheet BI_Galbi(3)
A1: RECIPE COST CALCULATOR
B3: ITEM NAME | D3: Galbi Chicken_Bone In_3PC
B5: EST. SALE PRICE | D5: 15
B6: TOTAL COST(Dine In) | D6: =$J$26 -> 2.9846971
B7: TOTAL COST(Take Out) | D7: =$J$42 -> 3.7925125
B9: Food Cost | D9: =IF(D7="","",IF(ISBLANK(D5),"",D7/D5)) -> 0.25283417
B11: NET PROFIT | D11: =D5-D7 -> 11.207487
B13: PRIMARY INGREDIENTS
B14: Product Name | D14: Wheigh (g) | E14: Price | F14: Price/g | G14: Input/g | H14: Usage(%) | I14: Input+ Usage | J14: Price | K14: Price(%)/ Portion
B16: =Master!$B$6 -> 홀치킨 | C16: =Master!$C$6 -> Whole Chicken | D16: =Master!$H$6 -> 1000 | E16: =Master!$J$6 -> 2.8415359 | F16: =Master!$K$6 -> 0.0028415359 | G16: 390 | H16: =Master!$P$6 -> 98 | I16: =G16/H16*100 -> 397.95918 | J16: =F16*I16 -> 1.1308153 | K16: =J16/$J$26% -> 37.887104
B17: =Master!$B$43 -> 옐로우 배터믹스 [Battering Powder Mix-C] | C17: =Master!$C$43 -> Battering Powder Mix-C | D17: =Master!$H$43 -> 20000 | E17: =Master!$J$43 -> 89.079647 | F17: =Master!$K$43 -> 0.0044539824 | G17: =G16*10% -> 39 | H17: =Master!$P$43 -> 98 | I17: =G17/H17*100 -> 39.795918 | J17: =F17*I17 -> 0.17725032 | K17: =J17/$J$26% -> 5.9386367
B18: =Master!$B$31 -> 해바라기 유 | C18: =Master!$C$31 -> Sunflower Oil | D18: =Master!$H$31 -> 1320 | E18: =Master!$J$31 -> 14.971513 | F18: =Master!$K$31 -> 0.011342055 | G18: =G16*25% -> 97.5 | H18: =Master!$P$31 -> 100 | I18: =G18/H18*100 -> 97.5 | J18: =F18*I18 -> 1.1058504 | K18: =J18/$J$26% -> 37.050673
B19: =Master!$B$52 -> 갈비 소스 | C19: =Master!$C$52 -> Galbi Flavor Sauce | D19: =Master!$H$52 -> 12000 | E19: =Master!$J$52 -> 80.524714 | F19: =Master!$K$52 -> 0.0067103928 | G19: =G16*20% -> 78 | H19: =Master!$P$52 -> 96 | I19: =G19/H19*100 -> 81.25 | J19: =F19*I19 -> 0.54521942 | K19: =J19/$J$26% -> 18.267161
B20: =Master!$B$105 -> 파 | C20: =Master!$C$105 -> Spring Onion | D20: =Master!$H$105 -> 180 | E20: =Master!$J$105 -> 0.64442515 | F20: =Master!$K$105 -> 0.0035801397 | G20: =G19*5% -> 3.9 | H20: =Master!$P$105 -> 95 | I20: =G20/H20*100 -> 4.1052632 | J20: =F20*I20 -> 0.014697416 | K20: =J20/$J$26% -> 0.49242571
B21: =Master!$B$79 -> 참깨 | C21: =Master!$C$79 -> Sesame Seeds | D21: =Master!$H$79 -> 453.592 | E21: =Master!$J$79 -> 4.9279571 | F21: =Master!$K$79 -> 0.010864294 | G21: 1 | H21: =Master!$P$79 -> 100 | I21: =G21/H21*100 -> 1 | J21: =F21*I21 -> 0.010864294 | K21: =J21/$J$26% -> 0.3639999
K22: =J22/$J$26% -> 0
K23: =J23/$J$26% -> 0
K24: =J24/$J$26% -> 0
K25: =J25/$J$26% -> 0
B26: TOTAL | G26: =SUM(G16:G25) -> 609.4 | J26: =SUM(J16:J25) -> 2.9846971 | K26: =SUM(K16:K25) -> 100
B28: SECONDARY INGREDIENTS
B29: Product Name | D29: Wheigh (g) | E29: Price | F29: Price/g | G29: Input/g | H29: Usage(%) | I29: Input+ Usage | J29: Price | K29: Price(%)/ Portion
B31: =Master!$B$150 -> 치킨패키지(대) | C31: =Master!$C$150 -> Chicken Package (L) | D31: =Master!$H$150 -> 400 | E31: =Master!$J$150 -> 99.025402 | F31: =Master!$K$150 -> 0.2475635 | G31: 1 | H31: =Master!$P$150 -> 100 | I31: =G31/H31*100 -> 1 | J31: =F31*I31 -> 0.2475635 | K31: =J31/$J$42% -> 6.5276911
B32: =Master!$B$157 -> 치킨트레이(소) | C32: =Master!$C$157 -> To Go Tray (S) | D32: =Master!$H$157 -> 100 | E32: =Master!$J$157 -> 8.4 | F32: =Master!$K$157 -> 0.084 | G32: 0 | H32: =Master!$P$157 -> 100 | I32: =G32/H32*100 -> 0 | J32: =F32*I32 -> 0 | K32: =J32/$J$42% -> 0
B33: =Master!$B$175 -> 종이백 (S,M) | C33: =Master!$C$175 -> Paper Bag (S,M) | D33: =Master!$H$175 -> 200 | E33: =Master!$J$175 -> 61.106668 | F33: =Master!$K$175 -> 0.30553334 | G33: 1 | H33: =Master!$P$175 -> 100 | I33: =G33/H33*100 -> 1 | J33: =F33*I33 -> 0.30553334 | K33: =J33/$J$42% -> 8.0562249
B34: =Master!$B$166 -> 비비큐 냅킨 | C34: =Master!$C$166 -> BBQ New LOGO Napkin | D34: =Master!$H$166 -> 5000 | E34: =Master!$J$166 -> 21.816824 | F34: =Master!$K$166 -> 0.0043633648 | G34: 1 | H34: =Master!$P$166 -> 100 | I34: =G34/H34*100 -> 1 | J34: =F34*I34 -> 0.0043633648 | K34: =J34/$J$42% -> 0.11505209
B35: =Master!$B$165 -> 왁스페이퍼 | C35: =Master!$C$165 -> BBQ Wax Paper Logo / Parchment paper | D35: =Master!$H$165 -> 2500 | E35: =Master!$J$165 -> 36.570748 | F35: =Master!$K$165 -> 0.014628299 | G35: 1 | H35: =Master!$P$165 -> 100 | I35: =G35/H35*100 -> 1 | J35: =F35*I35 -> 0.014628299 | K35: =J35/$J$42% -> 0.38571525
B36: =Master!$B$164 -> 비비큐 젓가락 | C36: =Master!$C$164 -> BBQ Chopstick Logo | D36: =Master!$H$164 -> 500 | E36: =Master!$J$164 -> 117.86347 | F36: =Master!$K$164 -> 0.23572693 | G36: 1 | H36: =Master!$P$164 -> 100 | I36: =G36/H36*100 -> 1 | J36: =F36*I36 -> 0.23572693 | K36: =J36/$J$42% -> 6.2155874
B40: TOTAL | G40: =SUM(G31:G39) -> 5 | J40: =SUM(J31:J39) -> 0.80781544 | K40: =SUM(K31:K39) -> 21.300271
B42: TOTAL INGREDIENTS | J42: =J26+J40 -> 3.7925125 | K42: =K26+K40 -> 121.30027

Sheet BI_Galbi(5)
A1: RECIPE COST CALCULATOR
B3: ITEM NAME | D3: Galbi Chicken_Bone In_5PC
B5: EST. SALE PRICE | D5: 21
B6: TOTAL COST(Dine In) | D6: =$J$26 -> 4.9672523
B7: TOTAL COST(Take Out) | D7: =$J$42 -> 5.7750677
B9: Food Cost | D9: =IF(D7="","",IF(ISBLANK(D5),"",D7/D5)) -> 0.27500323
B11: NET PROFIT | D11: =D5-D7 -> 15.224932
B13: PRIMARY INGREDIENTS
B14: Product Name | D14: Wheigh (g) | E14: Price | F14: Price/g | G14: Input/g | H14: Usage(%) | I14: Input+ Usage | J14: Price | K14: Price(%)/ Portion
B16: =Master!$B$6 -> 홀치킨 | C16: =Master!$C$6 -> Whole Chicken | D16: =Master!$H$6 -> 1000 | E16: =Master!$J$6 -> 2.8415359 | F16: =Master!$K$6 -> 0.0028415359 | G16: 650 | H16: =Master!$P$6 -> 98 | I16: =G16/H16*100 -> 663.26531 | J16: =F16*I16 -> 1.8846921 | K16: =J16/$J$26% -> 37.942348
B17: =Master!$B$43 -> 옐로우 배터믹스 [Battering Powder Mix-C] | C17: =Master!$C$43 -> Battering Powder Mix-C | D17: =Master!$H$43 -> 20000 | E17: =Master!$J$43 -> 89.079647 | F17: =Master!$K$43 -> 0.0044539824 | G17: =G16*10% -> 65 | H17: =Master!$P$43 -> 98 | I17: =G17/H17*100 -> 66.326531 | J17: =F17*I17 -> 0.2954172 | K17: =J17/$J$26% -> 5.947296
B18: =Master!$B$31 -> 해바라기 유 | C18: =Master!$C$31 -> Sunflower Oil | D18: =Master!$H$31 -> 1320 | E18: =Master!$J$31 -> 14.971513 | F18: =Master!$K$31 -> 0.011342055 | G18: =G16*25% -> 162.5 | H18: =Master!$P$31 -> 100 | I18: =G18/H18*100 -> 162.5 | J18: =F18*I18 -> 1.8430839 | K18: =J18/$J$26% -> 37.104698
B19: =Master!$B$52 -> 갈비 소스 | C19: =Master!$C$52 -> Galbi Flavor Sauce | D19: =Master!$H$52 -> 12000 | E19: =Master!$J$52 -> 80.524714 | F19: =Master!$K$52 -> 0.0067103928 | G19: =G16*20% -> 130 | H19: =Master!$P$52 -> 96 | I19: =G19/H19*100 -> 135.41667 | J19: =F19*I19 -> 0.90869903 | K19: =J19/$J$26% -> 18.293796
B20: =Master!$B$105 -> 파 | C20: =Master!$C$105 -> Spring Onion | D20: =Master!$H$105 -> 180 | E20: =Master!$J$105 -> 0.64442515 | F20: =Master!$K$105 -> 0.0035801397 | G20: =G19*5% -> 6.5 | H20: =Master!$P$105 -> 95 | I20: =G20/H20*100 -> 6.8421053 | J20: =F20*I20 -> 0.024495693 | K20: =J20/$J$26% -> 0.49314372
B21: =Master!$B$79 -> 참깨 | C21: =Master!$C$79 -> Sesame Seeds | D21: =Master!$H$79 -> 453.592 | E21: =Master!$J$79 -> 4.9279571 | F21: =Master!$K$79 -> 0.010864294 | G21: 1 | H21: =Master!$P$79 -> 100 | I21: =G21/H21*100 -> 1 | J21: =F21*I21 -> 0.010864294 | K21: =J21/$J$26% -> 0.21871839
K22: =J22/$J$26% -> 0
K23: =J23/$J$26% -> 0
K24: =J24/$J$26% -> 0
K25: =J25/$J$26% -> 0
B26: TOTAL | G26: =SUM(G16:G25) -> 1015 | J26: =SUM(J16:J25) -> 4.9672523 | K26: =SUM(K16:K25) -> 100
B28: SECONDARY INGREDIENTS
B29: Product Name | D29: Wheigh (g) | E29: Price | F29: Price/g | G29: Input/g | H29: Usage(%) | I29: Input+ Usage | J29: Price | K29: Price(%)/ Portion
B31: =Master!$B$150 -> 치킨패키지(대) | C31: =Master!$C$150 -> Chicken Package (L) | D31: =Master!$H$150 -> 400 | E31: =Master!$J$150 -> 99.025402 | F31: =Master!$K$150 -> 0.2475635 | G31: 1 | H31: =Master!$P$150 -> 100 | I31: =G31/H31*100 -> 1 | J31: =F31*I31 -> 0.2475635 | K31: =J31/$J$42% -> 4.2867636
B32: =Master!$B$157 -> 치킨트레이(소) | C32: =Master!$C$157 -> To Go Tray (S) | D32: =Master!$H$157 -> 100 | E32: =Master!$J$157 -> 8.4 | F32: =Master!$K$157 -> 0.084 | G32: 0 | H32: =Master!$P$157 -> 100 | I32: =G32/H32*100 -> 0 | J32: =F32*I32 -> 0 | K32: =J32/$J$42% -> 0
B33: =Master!$B$175 -> 종이백 (S,M) | C33: =Master!$C$175 -> Paper Bag (S,M) | D33: =Master!$H$175 -> 200 | E33: =Master!$J$175 -> 61.106668 | F33: =Master!$K$175 -> 0.30553334 | G33: 1 | H33: =Master!$P$175 -> 100 | I33: =G33/H33*100 -> 1 | J33: =F33*I33 -> 0.30553334 | K33: =J33/$J$42% -> 5.2905585
B34: =Master!$B$166 -> 비비큐 냅킨 | C34: =Master!$C$166 -> BBQ New LOGO Napkin | D34: =Master!$H$166 -> 5000 | E34: =Master!$J$166 -> 21.816824 | F34: =Master!$K$166 -> 0.0043633648 | G34: 1 | H34: =Master!$P$166 -> 100 | I34: =G34/H34*100 -> 1 | J34: =F34*I34 -> 0.0043633648 | K34: =J34/$J$42% -> 0.075555214
B35: =Master!$B$165 -> 왁스페이퍼 | C35: =Master!$C$165 -> BBQ Wax Paper Logo / Parchment paper | D35: =Master!$H$165 -> 2500 | E35: =Master!$J$165 -> 36.570748 | F35: =Master!$K$165 -> 0.014628299 | G35: 1 | H35: =Master!$P$165 -> 100 | I35: =G35/H35*100 -> 1 | J35: =F35*I35 -> 0.014628299 | K35: =J35/$J$42% -> 0.25330091
B36: =Master!$B$164 -> 비비큐 젓가락 | C36: =Master!$C$164 -> BBQ Chopstick Logo | D36: =Master!$H$164 -> 500 | E36: =Master!$J$164 -> 117.86347 | F36: =Master!$K$164 -> 0.23572693 | G36: 1 | H36: =Master!$P$164 -> 100 | I36: =G36/H36*100 -> 1 | J36: =F36*I36 -> 0.23572693 | K36: =J36/$J$42% -> 4.0818037
B40: TOTAL | G40: =SUM(G31:G39) -> 5 | J40: =SUM(J31:J39) -> 0.80781544 | K40: =SUM(K31:K39) -> 13.987982
B42: TOTAL INGREDIENTS | J42: =J26+J40 -> 5.7750677 | K42: =K26+K40 -> 113.98798

Sheet BI_Hot Galbi(2)
A1: RECIPE COST CALCULATOR
B3: ITEM NAME | D3: Hot Galbi Chicken_Bone In_2PC
B5: EST. SALE PRICE | D5: 11
B6: TOTAL COST(Dine In) | D6: =$J$26 -> 1.9934195
B7: TOTAL COST(Take Out) | D7: =$J$42 -> 2.8012349
B9: Food Cost | D9: =IF(D7="","",IF(ISBLANK(D5),"",D7/D5)) -> 0.25465772
B11: NET PROFIT | D11: =D5-D7 -> 8.1987651
B13: PRIMARY INGREDIENTS
B14: Product Name | D14: Wheigh (g) | E14: Price | F14: Price/g | G14: Input/g | H14: Usage(%) | I14: Input+ Usage | J14: Price | K14: Price(%)/ Portion
B16: =Master!$B$6 -> 홀치킨 | C16: =Master!$C$6 -> Whole Chicken | D16: =Master!$H$6 -> 1000 | E16: =Master!$J$6 -> 2.8415359 | F16: =Master!$K$6 -> 0.0028415359 | G16: 260 | H16: =Master!$P$6 -> 98 | I16: =G16/H16*100 -> 265.30612 | J16: =F16*I16 -> 0.75387686 | K16: =J16/$J$26% -> 37.818275
B17: =Master!$B$43 -> 옐로우 배터믹스 [Battering Powder Mix-C] | C17: =Master!$C$43 -> Battering Powder Mix-C | D17: =Master!$H$43 -> 20000 | E17: =Master!$J$43 -> 89.079647 | F17: =Master!$K$43 -> 0.0044539824 | G17: =G16*10% -> 26 | H17: =Master!$P$43 -> 98 | I17: =G17/H17*100 -> 26.530612 | J17: =F17*I17 -> 0.11816688 | K17: =J17/$J$26% -> 5.9278481
B18: =Master!$B$31 -> 해바라기 유 | C18: =Master!$C$31 -> Sunflower Oil | D18: =Master!$H$31 -> 1320 | E18: =Master!$J$31 -> 14.971513 | F18: =Master!$K$31 -> 0.011342055 | G18: =G16*25% -> 65 | H18: =Master!$P$31 -> 100 | I18: =G18/H18*100 -> 65 | J18: =F18*I18 -> 0.73723358 | K18: =J18/$J$26% -> 36.983363
B19: =Master!$B$55 -> 매운갈비 소스 | C19: =Master!$C$55 -> Hot Galbi Flavor Sauce Mix | D19: =Master!$H$55 -> 12000 | E19: =Master!$J$55 -> 80.524714 | F19: =Master!$K$55 -> 0.0067103928 | G19: =G16*20% -> 52 | H19: =Master!$P$55 -> 96 | I19: =G19/H19*100 -> 54.166667 | J19: =F19*I19 -> 0.36347961 | K19: =J19/$J$26% -> 18.233975
B20: =Master!$B$105 -> 파 | C20: =Master!$C$105 -> Spring Onion | D20: =Master!$H$105 -> 180 | E20: =Master!$J$105 -> 0.64442515 | F20: =Master!$K$105 -> 0.0035801397 | G20: =G19*5% -> 2.6 | H20: =Master!$P$105 -> 95 | I20: =G20/H20*100 -> 2.7368421 | J20: =F20*I20 -> 0.0097982772 | K20: =J20/$J$26% -> 0.49153112
B21: =Master!$B$79 -> 참깨 | C21: =Master!$C$79 -> Sesame Seeds | D21: =Master!$H$79 -> 453.592 | E21: =Master!$J$79 -> 4.9279571 | F21: =Master!$K$79 -> 0.010864294 | G21: 1 | H21: =Master!$P$79 -> 100 | I21: =G21/H21*100 -> 1 | J21: =F21*I21 -> 0.010864294 | K21: =J21/$J$26% -> 0.54500794
K22: =J22/$J$26% -> 0
K23: =J23/$J$26% -> 0
K24: =J24/$J$26% -> 0
K25: =J25/$J$26% -> 0
B26: TOTAL | G26: =SUM(G16:G25) -> 406.6 | J26: =SUM(J16:J25) -> 1.9934195 | K26: =SUM(K16:K25) -> 100
B28: SECONDARY INGREDIENTS
B29: Product Name | D29: Wheigh (g) | E29: Price | F29: Price/g | G29: Input/g | H29: Usage(%) | I29: Input+ Usage | J29: Price | K29: Price(%)/ Portion
B31: =Master!$B$150 -> 치킨패키지(대) | C31: =Master!$C$150 -> Chicken Package (L) | D31: =Master!$H$150 -> 400 | E31: =Master!$J$150 -> 99.025402 | F31: =Master!$K$150 -> 0.2475635 | G31: 1 | H31: =Master!$P$150 -> 100 | I31: =G31/H31*100 -> 1 | J31: =F31*I31 -> 0.2475635 | K31: =J31/$J$42% -> 8.8376559
B32: =Master!$B$157 -> 치킨트레이(소) | C32: =Master!$C$157 -> To Go Tray (S) | D32: =Master!$H$157 -> 100 | E32: =Master!$J$157 -> 8.4 | F32: =Master!$K$157 -> 0.084 | G32: 0 | H32: =Master!$P$157 -> 100 | I32: =G32/H32*100 -> 0 | J32: =F32*I32 -> 0 | K32: =J32/$J$42% -> 0
B33: =Master!$B$175 -> 종이백 (S,M) | C33: =Master!$C$175 -> Paper Bag (S,M) | D33: =Master!$H$175 -> 200 | E33: =Master!$J$175 -> 61.106668 | F33: =Master!$K$175 -> 0.30553334 | G33: 1 | H33: =Master!$P$175 -> 100 | I33: =G33/H33*100 -> 1 | J33: =F33*I33 -> 0.30553334 | K33: =J33/$J$42% -> 10.907094
B34: =Master!$B$166 -> 비비큐 냅킨 | C34: =Master!$C$166 -> BBQ New LOGO Napkin | D34: =Master!$H$166 -> 5000 | E34: =Master!$J$166 -> 21.816824 | F34: =Master!$K$166 -> 0.0043633648 | G34: 1 | H34: =Master!$P$166 -> 100 | I34: =G34/H34*100 -> 1 | J34: =F34*I34 -> 0.0043633648 | K34: =J34/$J$42% -> 0.15576576
B35: =Master!$B$165 -> 왁스페이퍼 | C35: =Master!$C$165 -> BBQ Wax Paper Logo / Parchment paper | D35: =Master!$H$165 -> 2500 | E35: =Master!$J$165 -> 36.570748 | F35: =Master!$K$165 -> 0.014628299 | G35: 1 | H35: =Master!$P$165 -> 100 | I35: 1 | J35: =F35*I35 -> 0.014628299 | K35: =J35/$J$42% -> 0.52220894
B36: =Master!$B$164 -> 비비큐 젓가락 | C36: =Master!$C$164 -> BBQ Chopstick Logo | D36: =Master!$H$164 -> 500 | E36: =Master!$J$164 -> 117.86347 | F36: =Master!$K$164 -> 0.23572693 | G36: 1 | H36: =Master!$P$164 -> 100 | I36: =G36/H36*100 -> 1 | J36: =F36*I36 -> 0.23572693 | K36: =J36/$J$42% -> 8.4151075
B40: TOTAL | G40: =SUM(G31:G39) -> 5 | J40: =SUM(J31:J39) -> 0.80781544 | K40: =SUM(K31:K39) -> 28.837832
B42: TOTAL INGREDIENTS | J42: =J26+J40 -> 2.8012349 | K42: =K26+K40 -> 128.83783

Sheet BI_Hot Galbi(3)
A1: RECIPE COST CALCULATOR
B3: ITEM NAME | D3: Hot Galbi Chicken_Bone In_3PC
B5: EST. SALE PRICE | D5: 15
B6: TOTAL COST(Dine In) | D6: =$J$26 -> 2.9846971
B7: TOTAL COST(Take Out) | D7: =$J$42 -> 3.7925125
B9: Food Cost | D9: =IF(D7="","",IF(ISBLANK(D5),"",D7/D5)) -> 0.25283417
B11: NET PROFIT | D11: =D5-D7 -> 11.207487
B13: PRIMARY INGREDIENTS
B14: Product Name | D14: Wheigh (g) | E14: Price | F14: Price/g | G14: Input/g | H14: Usage(%) | I14: Input+ Usage | J14: Price | K14: Price(%)/ Portion
B16: =Master!$B$6 -> 홀치킨 | C16: =Master!$C$6 -> Whole Chicken | D16: =Master!$H$6 -> 1000 | E16: =Master!$J$6 -> 2.8415359 | F16: =Master!$K$6 -> 0.0028415359 | G16: 390 | H16: =Master!$P$6 -> 98 | I16: =G16/H16*100 -> 397.95918 | J16: =F16*I16 -> 1.1308153 | K16: =J16/$J$26% -> 37.887104
B17: =Master!$B$43 -> 옐로우 배터믹스 [Battering Powder Mix-C] | C17: =Master!$C$43 -> Battering Powder Mix-C | D17: =Master!$H$43 -> 20000 | E17: =Master!$J$43 -> 89.079647 | F17: =Master!$K$43 -> 0.0044539824 | G17: =G16*10% -> 39 | H17: =Master!$P$43 -> 98 | I17: =G17/H17*100 -> 39.795918 | J17: =F17*I17 -> 0.17725032 | K17: =J17/$J$26% -> 5.9386367
B18: =Master!$B$31 -> 해바라기 유 | C18: =Master!$C$31 -> Sunflower Oil | D18: =Master!$H$31 -> 1320 | E18: =Master!$J$31 -> 14.971513 | F18: =Master!$K$31 -> 0.011342055 | G18: =G16*25% -> 97.5 | H18: =Master!$P$31 -> 100 | I18: =G18/H18*100 -> 97.5 | J18: =F18*I18 -> 1.1058504 | K18: =J18/$J$26% -> 37.050673
B19: =Master!$B$55 -> 매운갈비 소스 | C19: =Master!$C$55 -> Hot Galbi Flavor Sauce Mix | D19: =Master!$H$55 -> 12000 | E19: =Master!$J$55 -> 80.524714 | F19: =Master!$K$55 -> 0.0067103928 | G19: =G16*20% -> 78 | H19: =Master!$P$55 -> 96 | I19: =G19/H19*100 -> 81.25 | J19: =F19*I19 -> 0.54521942 | K19: =J19/$J$26% -> 18.267161
B20: =Master!$B$105 -> 파 | C20: =Master!$C$105 -> Spring Onion | D20: =Master!$H$105 -> 180 | E20: =Master!$J$105 -> 0.64442515 | F20: =Master!$K$105 -> 0.0035801397 | G20: =G19*5% -> 3.9 | H20: =Master!$P$105 -> 95 | I20: =G20/H20*100 -> 4.1052632 | J20: =F20*I20 -> 0.014697416 | K20: =J20/$J$26% -> 0.49242571
B21: =Master!$B$79 -> 참깨 | C21: =Master!$C$79 -> Sesame Seeds | D21: =Master!$H$79 -> 453.592 | E21: =Master!$J$79 -> 4.9279571 | F21: =Master!$K$79 -> 0.010864294 | G21: 1 | H21: =Master!$P$79 -> 100 | I21: =G21/H21*100 -> 1 | J21: =F21*I21 -> 0.010864294 | K21: =J21/$J$26% -> 0.3639999
K22: =J22/$J$26% -> 0
K23: =J23/$J$26% -> 0
K24: =J24/$J$26% -> 0
K25: =J25/$J$26% -> 0
B26: TOTAL | G26: =SUM(G16:G25) -> 609.4 | J26: =SUM(J16:J25) -> 2.9846971 | K26: =SUM(K16:K25) -> 100
B28: SECONDARY INGREDIENTS
B29: Product Name | D29: Wheigh (g) | E29: Price | F29: Price/g | G29: Input/g | H29: Usage(%) | I29: Input+ Usage | J29: Price | K29: Price(%)/ Portion
B31: =Master!$B$150 -> 치킨패키지(대) | C31: =Master!$C$150 -> Chicken Package (L) | D31: =Master!$H$150 -> 400 | E31: =Master!$J$150 -> 99.025402 | F31: =Master!$K$150 -> 0.2475635 | G31: 1 | H31: =Master!$P$150 -> 100 | I31: =G31/H31*100 -> 1 | J31: =F31*I31 -> 0.2475635 | K31: =J31/$J$42% -> 6.5276911
B32: =Master!$B$157 -> 치킨트레이(소) | C32: =Master!$C$157 -> To Go Tray (S) | D32: =Master!$H$157 -> 100 | E32: =Master!$J$157 -> 8.4 | F32: =Master!$K$157 -> 0.084 | G32: 0 | H32: =Master!$P$157 -> 100 | I32: =G32/H32*100 -> 0 | J32: =F32*I32 -> 0 | K32: =J32/$J$42% -> 0
B33: =Master!$B$175 -> 종이백 (S,M) | C33: =Master!$C$175 -> Paper Bag (S,M) | D33: =Master!$H$175 -> 200 | E33: =Master!$J$175 -> 61.106668 | F33: =Master!$K$175 -> 0.30553334 | G33: 1 | H33: =Master!$P$175 -> 100 | I33: =G33/H33*100 -> 1 | J33: =F33*I33 -> 0.30553334 | K33: =J33/$J$42% -> 8.0562249
B34: =Master!$B$166 -> 비비큐 냅킨 | C34: =Master!$C$166 -> BBQ New LOGO Napkin | D34: =Master!$H$166 -> 5000 | E34: =Master!$J$166 -> 21.816824 | F34: =Master!$K$166 -> 0.0043633648 | G34: 1 | H34: =Master!$P$166 -> 100 | I34: =G34/H34*100 -> 1 | J34: =F34*I34 -> 0.0043633648 | K34: =J34/$J$42% -> 0.11505209
B35: =Master!$B$165 -> 왁스페이퍼 | C35: =Master!$C$165 -> BBQ Wax Paper Logo / Parchment paper | D35: =Master!$H$165 -> 2500 | E35: =Master!$J$165 -> 36.570748 | F35: =Master!$K$165 -> 0.014628299 | G35: 1 | H35: =Master!$P$165 -> 100 | I35: 1 | J35: =F35*I35 -> 0.014628299 | K35: =J35/$J$42% -> 0.38571525
